Workbook

Sheet Sector-wise Analysis
A1: Sector | B1: Company | C1: Metric | D1: Year | E1: Value | F1: Type
A2: BFSI | B2: Axis Bank | C2: AUM | D2: 2020 | E2: ='[1]Balance Sheet-Banks'!$B$75 -> 582958.8 | F2: =IF(VALUE(D2)>2024,"Forecast","Actual") -> Actual
A3: BFSI | B3: Axis Bank | C3: AUM | D3: 2021 | E3: ='[1]Balance Sheet-Banks'!$C$75 -> 625749.9 | F3: =IF(VALUE(D3)>2024,"Forecast","Actual") -> Actual
A4: BFSI | B4: Axis Bank | C4: AUM | D4: 2022 | E4: ='[1]Balance Sheet-Banks'!$D$75 -> 725125.5 | F4: =IF(VALUE(D4)>2024,"Forecast","Actual") -> Actual
A5: BFSI | B5: Axis Bank | C5: AUM | D5: 2023 | E5: ='[1]Balance Sheet-Banks'!$E$75 -> 868387.54 | F5: =IF(VALUE(D5)>2024,"Forecast","Actual") -> Actual
A6: BFSI | B6: Axis Bank | C6: AUM | D6: 2024 | E6: ='[1]Balance Sheet-Banks'!$F$75 -> 999333.48 | F6: =IF(VALUE(D6)>2024,"Forecast","Actual") -> Actual
A7: BFSI | B7: Axis Bank | C7: AUM | D7: 2025 | E7: ='[1]Financial Projections'!$D$5 -> 1113076.3 | F7: =IF(VALUE(D7)>2024,"Forecast","Actual") -> Forecast
A8: BFSI | B8: Axis Bank | C8: AUM | D8: 2026 | E8: ='[1]Financial Projections'!$E$5 -> 1239765.3 | F8: =IF(VALUE(D8)>2024,"Forecast","Actual") -> Forecast
A9: BFSI | B9: Axis Bank | C9: AUM | D9: 2027 | E9: ='[1]Financial Projections'!$F$5 -> 1380873.8 | F9: =IF(VALUE(D9)>2024,"Forecast","Actual") -> Forecast
A10: BFSI | B10: Axis Bank | C10: AUM | D10: 2028 | E10: ='[1]Financial Projections'!$G$5 -> 1538043.1 | F10: =IF(VALUE(D10)>2024,"Forecast","Actual") -> Forecast
A11: BFSI | B11: Axis Bank | C11: AUM | D11: 2029 | E11: ='[1]Financial Projections'!$H$5 -> 1713101.2 | F11: =IF(VALUE(D11)>2024,"Forecast","Actual") -> Forecast
A12: BFSI | B12: Axis Bank | C12: AUM | D12: 2030 | E12: ='[1]Financial Projections'!$I$5 -> 1908084.2 | F12: =IF(VALUE(D12)>2024,"Forecast","Actual") -> Forecast
A13: BFSI | B13: HDFC Bank | C13: AUM | D13: 2020 | E13: ='[1]Balance Sheet-Banks'!$G$75 -> 1043670.8 | F13: =IF(VALUE(D13)>2024,"Forecast","Actual") -> Actual
A14: BFSI | B14: HDFC Bank | C14: AUM | D14: 2021 | E14: ='[1]Balance Sheet-Banks'!$H$75 -> 1185283.5 | F14: =IF(VALUE(D14)>2024,"Forecast","Actual") -> Actual
A15: BFSI | B15: HDFC Bank | C15: AUM | D15: 2022 | E15: ='[1]Balance Sheet-Banks'!$I$75 -> 1420942.3 | F15: =IF(VALUE(D15)>2024,"Forecast","Actual") -> Actual
A16: BFSI | B16: HDFC Bank | C16: AUM | D16: 2023 | E16: ='[1]Balance Sheet-Banks'!$J$75 -> 1661949.3 | F16: =IF(VALUE(D16)>2024,"Forecast","Actual") -> Actual
A17: BFSI | B17: HDFC Bank | C17: AUM | D17: 2024 | E17: ='[1]Balance Sheet-Banks'!$K$75 -> 2565891.4 | F17: =IF(VALUE(D17)>2024,"Forecast","Actual") -> Actual
A18: BFSI | B18: HDFC Bank | C18: AUM | D18: 2025 | E18: ='[1]Financial Projections'!$M$5 -> 3071660.5 | F18: =IF(VALUE(D18)>2024,"Forecast","Actual") -> Forecast
A19: BFSI | B19: HDFC Bank | C19: AUM | D19: 2026 | E19: ='[1]Financial Projections'!$N$5 -> 3677123 | F19: =IF(VALUE(D19)>2024,"Forecast","Actual") -> Forecast
A20: BFSI | B20: HDFC Bank | C20: AUM | D20: 2027 | E20: ='[1]Financial Projections'!$O$5 -> 4401929.7 | F20: =IF(VALUE(D20)>2024,"Forecast","Actual") -> Forecast
A21: BFSI | B21: HDFC Bank | C21: AUM | D21: 2028 | E21: ='[1]Financial Projections'!$P$5 -> 5269604.9 | F21: =IF(VALUE(D21)>2024,"Forecast","Actual") -> Forecast
A22: BFSI | B22: HDFC Bank | C22: AUM | D22: 2029 | E22: ='[1]Financial Projections'!$Q$5 -> 6308309.6 | F22: =IF(VALUE(D22)>2024,"Forecast","Actual") -> Forecast
A23: BFSI | B23: HDFC Bank | C23: AUM | D23: 2030 | E23: ='[1]Financial Projections'!$R$5 -> 7551755.9 | F23: =IF(VALUE(D23)>2024,"Forecast","Actual") -> Forecast
A24: BFSI | B24: ICICI Bank | C24: AUM | D24: 2020 | E24: ='[1]Balance Sheet-Banks'!$L$75 -> 706246.09 | F24: =IF(VALUE(D24)>2024,"Forecast","Actual") -> Actual
A25: BFSI | B25: ICICI Bank | C25: AUM | D25: 2021 | E25: ='[1]Balance Sheet-Banks'!$M$75 -> 733729.04 | F25: =IF(VALUE(D25)>2024,"Forecast","Actual") -> Actual
A26: BFSI | B26: ICICI Bank | C26: AUM | D26: 2022 | E26: ='[1]Balance Sheet-Banks'!$N$75 -> 859020.4 | F26: =IF(VALUE(D26)>2024,"Forecast","Actual") -> Actual
A27: BFSI | B27: ICICI Bank | C27: AUM | D27: 2023 | E27: ='[1]Balance Sheet-Banks'!$O$75 -> 1083866.3 | F27: =IF(VALUE(D27)>2024,"Forecast","Actual") -> Actual
A28: BFSI | B28: ICICI Bank | C28: AUM | D28: 2024 | E28: ='[1]Balance Sheet-Banks'!$P$75 -> 1260776.2 | F28: =IF(VALUE(D28)>2024,"Forecast","Actual") -> Actual
A29: BFSI | B29: ICICI Bank | C29: AUM | D29: 2025 | E29: ='[1]Financial Projections'!$V$5 -> 1415710.3 | F29: =IF(VALUE(D29)>2024,"Forecast","Actual") -> Forecast
A30: BFSI | B30: ICICI Bank | C30: AUM | D30: 2026 | E30: ='[1]Financial Projections'!$W$5 -> 1589683.9 | F30: =IF(VALUE(D30)>2024,"Forecast","Actual") -> Forecast
A31: BFSI | B31: ICICI Bank | C31: AUM | D31: 2027 | E31: ='[1]Financial Projections'!$X$5 -> 1785036.7 | F31: =IF(VALUE(D31)>2024,"Forecast","Actual") -> Forecast
A32: BFSI | B32: ICICI Bank | C32: AUM | D32: 2028 | E32: ='[1]Financial Projections'!$Y$5 -> 2004396.1 | F32: =IF(VALUE(D32)>2024,"Forecast","Actual") -> Forecast
A33: BFSI | B33: ICICI Bank | C33: AUM | D33: 2029 | E33: ='[1]Financial Projections'!$Z$5 -> 2250712 | F33: =IF(VALUE(D33)>2024,"Forecast","Actual") -> Forecast
A34: BFSI | B34: ICICI Bank | C34: AUM | D34: 2030 | E34: ='[1]Financial Projections'!$AA$5 -> 2527297.2 | F34: =IF(VALUE(D34)>2024,"Forecast","Actual") -> Forecast
A35: BFSI | B35: SBI | C35: AUM | D35: 2020 | E35: ='[1]Balance Sheet-Banks'!$Q$75 -> 2374311.2 | F35: =IF(VALUE(D35)>2024,"Forecast","Actual") -> Actual
A36: BFSI | B36: SBI | C36: AUM | D36: 2021 | E36: ='[1]Balance Sheet-Banks'!$R$75 -> 2500599 | F36: =IF(VALUE(D36)>2024,"Forecast","Actual") -> Actual
A37: BFSI | B37: SBI | C37: AUM | D37: 2022 | E37: ='[1]Balance Sheet-Banks'!$S$75 -> 2794076 | F37: =IF(VALUE(D37)>2024,"Forecast","Actual") -> Actual
A38: BFSI | B38: SBI | C38: AUM | D38: 2023 | E38: ='[1]Balance Sheet-Banks'!$T$75 -> 3267902.1 | F38: =IF(VALUE(D38)>2024,"Forecast","Actual") -> Actual
A39: BFSI | B39: SBI | C39: AUM | D39: 2024 | E39: ='[1]Balance Sheet-Banks'!$U$75 -> 3784272.7 | F39: =IF(VALUE(D39)>2024,"Forecast","Actual") -> Actual
A40: BFSI | B40: SBI | C40: AUM | D40: 2025 | E40: ='[1]Financial Projections'!$AE$5 -> 4154046.7 | F40: =IF(VALUE(D40)>2024,"Forecast","Actual") -> Forecast
A41: BFSI | B41: SBI | C41: AUM | D41: 2026 | E41: ='[1]Financial Projections'!$AF$5 -> 4559952.7 | F41: =IF(VALUE(D41)>2024,"Forecast","Actual") -> Forecast
A42: BFSI | B42: SBI | C42: AUM | D42: 2027 | E42: ='[1]Financial Projections'!$AG$5 -> 5005521.1 | F42: =IF(VALUE(D42)>2024,"Forecast","Actual") -> Forecast
A43: BFSI | B43: SBI | C43: AUM | D43: 2028 | E43: ='[1]Financial Projections'!$AH$5 -> 5494627.5 | F43: =IF(VALUE(D43)>2024,"Forecast","Actual") -> Forecast
A44: BFSI | B44: SBI | C44: AUM | D44: 2029 | E44: ='[1]Financial Projections'!$AI$5 -> 6031526.1 | F44: =IF(VALUE(D44)>2024,"Forecast","Actual") -> Forecast
A45: BFSI | B45: SBI | C45: AUM | D45: 2030 | E45: ='[1]Financial Projections'!$AJ$5 -> 6620886.9 | F45: =IF(VALUE(D45)>2024,"Forecast","Actual") -> Forecast
A46: BFSI | B46: Bajaj Housing Finance | C46: AUM | D46: 2020 | E46: ='[1]Balance Sheet-NBFCs'!$B$27 -> 27975.41 | F46: =IF(VALUE(D46)>2024,"Forecast","Actual") -> Actual
A47: BFSI | B47: Bajaj Housing Finance | C47: AUM | D47: 2021 | E47: ='[1]Balance Sheet-NBFCs'!$C$27 -> 33418.9 | F47: =IF(VALUE(D47)>2024,"Forecast","Actual") -> Actual
A48: BFSI | B48: Bajaj Housing Finance | C48: AUM | D48: 2022 | E48: ='[1]Balance Sheet-NBFCs'!$D$27 -> 46482.07 | F48: =IF(VALUE(D48)>2024,"Forecast","Actual") -> Actual
A49: BFSI | B49: Bajaj Housing Finance | C49: AUM | D49: 2023 | E49: ='[1]Balance Sheet-NBFCs'!$E$27 -> 62113.89 | F49: =IF(VALUE(D49)>2024,"Forecast","Actual") -> Actual
A50: BFSI | B50: Bajaj Housing Finance | C50: AUM | D50: 2024 | E50: ='[1]Balance Sheet-NBFCs'!$F$27 -> 79300.75 | F50: =IF(VALUE(D50)>2024,"Forecast","Actual") -> Actual
A51: BFSI | B51: Bajaj Housing Finance | C51: AUM | D51: 2025 | E51: ='[1]Financial Projections'!$AN$5 -> 97673.66 | F51: =IF(VALUE(D51)>2024,"Forecast","Actual") -> Forecast
A52: BFSI | B52: Bajaj Housing Finance | C52: AUM | D52: 2026 | E52: ='[1]Financial Projections'!$AO$5 -> 120303.32 | F52: =IF(VALUE(D52)>2024,"Forecast","Actual") -> Forecast
A53: BFSI | B53: Bajaj Housing Finance | C53: AUM | D53: 2027 | E53: ='[1]Financial Projections'!$AP$5 -> 148175.98 | F53: =IF(VALUE(D53)>2024,"Forecast","Actual") -> Forecast
A54: BFSI | B54: Bajaj Housing Finance | C54: AUM | D54: 2028 | E54: ='[1]Financial Projections'!$AQ$5 -> 182506.34 | F54: =IF(VALUE(D54)>2024,"Forecast","Actual") -> Forecast
A55: BFSI | B55: Bajaj Housing Finance | C55: AUM | D55: 2029 | E55: ='[1]Financial Projections'!$AR$5 -> 224790.59 | F55: =IF(VALUE(D55)>2024,"Forecast","Actual") -> Forecast
A56: BFSI | B56: Bajaj Housing Finance | C56: AUM | D56: 2030 | E56: ='[1]Financial Projections'!$AS$5 -> 276871.53 | F56: =IF(VALUE(D56)>2024,"Forecast","Actual") -> Forecast
A57: BFSI | B57: Bajaj Finserv | C57: AUM | D57: 2020 | E57: ='[1]Balance Sheet-NBFCs'!$G$27 -> 141376.05 | F57: =IF(VALUE(D57)>2024,"Forecast","Actual") -> Actual
A58: BFSI | B58: Bajaj Finserv | C58: AUM | D58: 2021 | E58: ='[1]Balance Sheet-NBFCs'!$H$27 -> 146686.87 | F58: =IF(VALUE(D58)>2024,"Forecast","Actual") -> Actual
A59: BFSI | B59: Bajaj Finserv | C59: AUM | D59: 2022 | E59: ='[1]Balance Sheet-NBFCs'!$I$27 -> 191423.25 | F59: =IF(VALUE(D59)>2024,"Forecast","Actual") -> Actual
A60: BFSI | B60: Bajaj Finserv | C60: AUM | D60: 2023 | E60: ='[1]Balance Sheet-NBFCs'!$J$27 -> 242268.93 | F60: =IF(VALUE(D60)>2024,"Forecast","Actual") -> Actual
A61: BFSI | B61: Bajaj Finserv | C61: AUM | D61: 2024 | E61: ='[1]Balance Sheet-NBFCs'!$K$27 -> 326293.32 | F61: =IF(VALUE(D61)>2024,"Forecast","Actual") -> Actual
A62: BFSI | B62: Bajaj Finserv | C62: AUM | D62: 2025 | E62: ='[1]Financial Projections'!$AW$5 -> 385704.45 | F62: =IF(VALUE(D62)>2024,"Forecast","Actual") -> Forecast
A63: BFSI | B63: Bajaj Finserv | C63: AUM | D63: 2026 | E63: ='[1]Financial Projections'!$AX$5 -> 455933.1 | F63: =IF(VALUE(D63)>2024,"Forecast","Actual") -> Forecast
A64: BFSI | B64: Bajaj Finserv | C64: AUM | D64: 2027 | E64: ='[1]Financial Projections'!$AY$5 -> 538948.9 | F64: =IF(VALUE(D64)>2024,"Forecast","Actual") -> Forecast
A65: BFSI | B65: Bajaj Finserv | C65: AUM | D65: 2028 | E65: ='[1]Financial Projections'!$AZ$5 -> 637080.12 | F65: =IF(VALUE(D65)>2024,"Forecast","Actual") -> Forecast
A66: BFSI | B66: Bajaj Finserv | C66: AUM | D66: 2029 | E66: ='[1]Financial Projections'!$BA$5 -> 753078.97 | F66: =IF(VALUE(D66)>2024,"Forecast","Actual") -> Forecast
A67: BFSI | B67: Bajaj Finserv | C67: AUM | D67: 2030 | E67: ='[1]Financial Projections'!$BB$5 -> 890198.77 | F67: =IF(VALUE(D67)>2024,"Forecast","Actual") -> Forecast
A68: BFSI | B68: Muthoot Finance | C68: AUM | D68: 2020 | E68: ='[1]Balance Sheet-NBFCs'!$L$27 -> 470677.41 | F68: =IF(VALUE(D68)>2024,"Forecast","Actual") -> Actual
A69: BFSI | B69: Muthoot Finance | C69: AUM | D69: 2021 | E69: ='[1]Balance Sheet-NBFCs'!$M$27 -> 588085.17 | F69: =IF(VALUE(D69)>2024,"Forecast","Actual") -> Actual
A70: BFSI | B70: Muthoot Finance | C70: AUM | D70: 2022 | E70: ='[1]Balance Sheet-NBFCs'!$N$27 -> 645276.41 | F70: =IF(VALUE(D70)>2024,"Forecast","Actual") -> Actual
A71: BFSI | B71: Muthoot Finance | C71: AUM | D71: 2023 | E71: ='[1]Balance Sheet-NBFCs'!$O$27 -> 705543.84 | F71: =IF(VALUE(D71)>2024,"Forecast","Actual") -> Actual
A72: BFSI | B72: Muthoot Finance | C72: AUM | D72: 2024 | E72: ='[1]Balance Sheet-NBFCs'!$P$27 -> 881871.71 | F72: =IF(VALUE(D72)>2024,"Forecast","Actual") -> Actual
A73: BFSI | B73: Muthoot Finance | C73: AUM | D73: 2025 | E73: ='[1]Financial Projections'!$BF$5 -> 999866.05 | F73: =IF(VALUE(D73)>2024,"Forecast","Actual") -> Forecast
A74: BFSI | B74: Muthoot Finance | C74: AUM | D74: 2026 | E74: ='[1]Financial Projections'!$BG$5 -> 1133648 | F74: =IF(VALUE(D74)>2024,"Forecast","Actual") -> Forecast
A75: BFSI | B75: Muthoot Finance | C75: AUM | D75: 2027 | E75: ='[1]Financial Projections'!$BH$5 -> 1285330 | F75: =IF(VALUE(D75)>2024,"Forecast","Actual") -> Forecast
A76: BFSI | B76: Muthoot Finance | C76: AUM | D76: 2028 | E76: ='[1]Financial Projections'!$BI$5 -> 1457307 | F76: =IF(VALUE(D76)>2024,"Forecast","Actual") -> Forecast
A77: BFSI | B77: Muthoot Finance | C77: AUM | D77: 2029 | E77: ='[1]Financial Projections'!$BJ$5 -> 1652294.5 | F77: =IF(VALUE(D77)>2024,"Forecast","Actual") -> Forecast
A78: BFSI | B78: Muthoot Finance | C78: AUM | D78: 2030 | E78: ='[1]Financial Projections'!$BK$5 -> 1873371.4 | F78: =IF(VALUE(D78)>2024,"Forecast","Actual") -> Forecast
A79: BFSI | B79: Axis Bank | C79: Revenue | D79: 2020 | E79: ='[1]Income Statement-Banks'!$B$7-'[1]Income Statement-Banks'!$B$9 -> 42061.73 | F79: =IF(VALUE(D79)>2024,"Forecast","Actual") -> Actual
A80: BFSI | B80: Axis Bank | C80: Revenue | D80: 2021 | E80: ='[1]Income Statement-Banks'!$C$7-'[1]Income Statement-Banks'!$C$9 -> 43346.9 | F80: =IF(VALUE(D80)>2024,"Forecast","Actual") -> Actual
A81: BFSI | B81: Axis Bank | C81: Revenue | D81: 2022 | E81: ='[1]Income Statement-Banks'!$D$7-'[1]Income Statement-Banks'!$D$9 -> 51191.53 | F81: =IF(VALUE(D81)>2024,"Forecast","Actual") -> Actual
A82: BFSI | B82: Axis Bank | C82: Revenue | D82: 2023 | E82: ='[1]Income Statement-Banks'!$E$7-'[1]Income Statement-Banks'!$E$9 -> 62408.15 | F82: =IF(VALUE(D82)>2024,"Forecast","Actual") -> Actual
A83: BFSI | B83: Axis Bank | C83: Revenue | D83: 2024 | E83: ='[1]Income Statement-Banks'!$F$7-'[1]Income Statement-Banks'!$F$9 -> 76598.62 | F83: =IF(VALUE(D83)>2024,"Forecast","Actual") -> Actual
A84: BFSI | B84: Axis Bank | C84: Revenue | D84: 2025 | E84: ='[1]Financial Projections'!$D$8 -> 86510.21 | F84: =IF(VALUE(D84)>2024,"Forecast","Actual") -> Forecast
A85: BFSI | B85: Axis Bank | C85: Revenue | D85: 2026 | E85: ='[1]Financial Projections'!$E$8 -> 97760.527 | F85: =IF(VALUE(D85)>2024,"Forecast","Actual") -> Forecast
A86: BFSI | B86: Axis Bank | C86: Revenue | D86: 2027 | E86: ='[1]Financial Projections'!$F$8 -> 110536.24 | F86: =IF(VALUE(D86)>2024,"Forecast","Actual") -> Forecast
A87: BFSI | B87: Axis Bank | C87: Revenue | D87: 2028 | E87: ='[1]Financial Projections'!$G$8 -> 125050.62 | F87: =IF(VALUE(D87)>2024,"Forecast","Actual") -> Forecast
A88: BFSI | B88: Axis Bank | C88: Revenue | D88: 2029 | E88: ='[1]Financial Projections'!$H$8 -> 141547.42 | F88: =IF(VALUE(D88)>2024,"Forecast","Actual") -> Forecast
A89: BFSI | B89: Axis Bank | C89: Revenue | D89: 2030 | E89: ='[1]Financial Projections'!$I$8 -> 160305.23 | F89: =IF(VALUE(D89)>2024,"Forecast","Actual") -> Forecast
A90: BFSI | B90: HDFC Bank | C90: Revenue | D90: 2020 | E90: ='[1]Income Statement-Banks'!$G$7-'[1]Income Statement-Banks'!$G$9 -> 84930.845 | F90: =IF(VALUE(D90)>2024,"Forecast","Actual") -> Actual
A91: BFSI | B91: HDFC Bank | C91: Revenue | D91: 2021 | E91: ='[1]Income Statement-Banks'!$H$7-'[1]Income Statement-Banks'!$H$9 -> 96637.694 | F91: =IF(VALUE(D91)>2024,"Forecast","Actual") -> Actual
A92: BFSI | B92: HDFC Bank | C92: Revenue | D92: 2022 | E92: ='[1]Income Statement-Banks'!$I$7-'[1]Income Statement-Banks'!$I$9 -> 109111.07 | F92: =IF(VALUE(D92)>2024,"Forecast","Actual") -> Actual
A93: BFSI | B93: HDFC Bank | C93: Revenue | D93: 2023 | E93: ='[1]Income Statement-Banks'!$J$7-'[1]Income Statement-Banks'!$J$9 -> 126886.16 | F93: =IF(VALUE(D93)>2024,"Forecast","Actual") -> Actual
A94: BFSI | B94: HDFC Bank | C94: Revenue | D94: 2024 | E94: ='[1]Income Statement-Banks'!$K$7-'[1]Income Statement-Banks'!$K$9 -> 253856.22 | F94: =IF(VALUE(D94)>2024,"Forecast","Actual") -> Actual
A95: BFSI | B95: HDFC Bank | C95: Revenue | D95: 2025 | E95: ='[1]Financial Projections'!$M$8 -> 322579.04 | F95: =IF(VALUE(D95)>2024,"Forecast","Actual") -> Forecast
A96: BFSI | B96: HDFC Bank | C96: Revenue | D96: 2026 | E96: ='[1]Financial Projections'!$N$8 -> 412796.94 | F96: =IF(VALUE(D96)>2024,"Forecast","Actual") -> Forecast
A97: BFSI | B97: HDFC Bank | C97: Revenue | D97: 2027 | E97: ='[1]Financial Projections'!$O$8 -> 531906.68 | F97: =IF(VALUE(D97)>2024,"Forecast","Actual") -> Forecast
A98: BFSI | B98: HDFC Bank | C98: Revenue | D98: 2028 | E98: ='[1]Financial Projections'!$P$8 -> 689986.14 | F98: =IF(VALUE(D98)>2024,"Forecast","Actual") -> Forecast
A99: BFSI | B99: HDFC Bank | C99: Revenue | D99: 2029 | E99: ='[1]Financial Projections'!$Q$8 -> 900791.13 | F99: =IF(VALUE(D99)>2024,"Forecast","Actual") -> Forecast
A100: BFSI | B100: HDFC Bank | C100: Revenue | D100: 2030 | E100: ='[1]Financial Projections'!$R$8 -> 1183127 | F100: =IF(VALUE(D100)>2024,"Forecast","Actual") -> Forecast
...

Sheet Tables-BFSI
A1: KPI | B1: 2020 | C1: 2021 | D1: 2022 | E1: 2023 | F1: 2024 | H1: KPI | I1: 2025 | J1: 2026 | K1: 2027 | L1: 2028 | M1: 2029 | N1: 2030
A2: Loan Book | B2: ='[7]Balance Sheet-Banks'!G75 -> 1043670.8 | C2: ='[7]Balance Sheet-Banks'!H75 -> 1185283.5 | D2: ='[7]Balance Sheet-Banks'!I75 -> 1420942.3 | E2: ='[7]Balance Sheet-Banks'!J75 -> 1661949.3 | F2: ='[7]Balance Sheet-Banks'!K75 -> 2565891.4 | H2: Loan Book | I2: ='[7]Financial Projections'!M5 -> 3071660.5 | J2: ='[7]Financial Projections'!N5 -> 3677123 | K2: ='[7]Financial Projections'!O5 -> 4401929.7 | L2: ='[7]Financial Projections'!P5 -> 5269604.9 | M2: ='[7]Financial Projections'!Q5 -> 6308309.6 | N2: ='[7]Financial Projections'!R5 -> 7551755.9 | Q2: HDFC bank | R2: =(N3-I3)/I3 -> 0.98672201 | S2: =(N3/I3)^(1/6)-1 -> 0.1212166
A3: Deposits | B3: ='[7]Balance Sheet-Banks'!G13 -> 1146207.1 | C3: ='[7]Balance Sheet-Banks'!H13 -> 1333720.9 | D3: ='[7]Balance Sheet-Banks'!I13 -> 1558003 | E3: ='[7]Balance Sheet-Banks'!J13 -> 1882663.2 | F3: ='[7]Balance Sheet-Banks'!K13 -> 2376887.3 | H3: PAT | I3: ='[7]Financial Projections'!M14 -> 82628.654 | J3: ='[7]Financial Projections'!N14 -> 94913.599 | K3: ='[7]Financial Projections'!O14 -> 108199.59 | L3: ='[7]Financial Projections'!P14 -> 123663.11 | M3: ='[7]Financial Projections'!Q14 -> 141977.35 | N3: ='[7]Financial Projections'!R14 -> 164160.17 | Q3: ICICI Bank | R3: =(N9-I9)/I9 -> 1.287401 | S3: =(N9/I9)^(1/6)-1 -> 0.14786386
A4: NIM | B4: ='[7]Financial Ratios-Banks'!H5 -> 0.041907401 | C4: ='[7]Financial Ratios-Banks'!I5 -> 0.042672577 | D4: ='[7]Financial Ratios-Banks'!J5 -> 0.041360189 | E4: ='[7]Financial Ratios-Banks'!K5 -> 0.042775608 | F4: ='[7]Financial Ratios-Banks'!L5 -> 0.036261465 | H4: Revenue | I4: ='[7]Financial Projections'!M8 -> 322579.04 | J4: ='[7]Financial Projections'!N8 -> 412796.94 | K4: ='[7]Financial Projections'!O8 -> 531906.68 | L4: ='[7]Financial Projections'!P8 -> 689986.14 | M4: ='[7]Financial Projections'!Q8 -> 900791.13 | N4: ='[7]Financial Projections'!R8 -> 1183127 | Q4: SBI | R4: =(N15-I15)/I15 -> 0.34433338 | S4: =(N15/I15)^(1/6)-1 -> 0.050552668
A5: NPA | B5: ='[7]Financial Ratios-Banks'!H13 -> 0.004 | C5: ='[7]Financial Ratios-Banks'!I13 -> 0.0032 | D5: ='[7]Financial Ratios-Banks'!J13 -> 0.0027 | E5: ='[7]Financial Ratios-Banks'!K13 -> 0.0033 | F5: ='[7]Financial Ratios-Banks'!L13 -> 0.0043 | H5: PBT | I5: ='[7]Financial Projections'!M12 -> 110421.83 | J5: ='[7]Financial Projections'!N12 -> 126838.97 | K5: ='[7]Financial Projections'!O12 -> 144593.86 | L5: ='[7]Financial Projections'!P12 -> 165258.74 | M5: ='[7]Financial Projections'!Q12 -> 189733.2 | N5: ='[7]Financial Projections'!R12 -> 219377.48 | Q5: Axis | R5: =(N21-I21)/I21 -> 0.95399723 | S5: =(N21/I21)^(1/6)-1 -> 0.11811719
A6: ROA | B6: ='[7]Financial Ratios-Banks'!H6 -> 0.017972094 | C6: ='[7]Financial Ratios-Banks'!I6 -> 0.018238548 | D6: ='[7]Financial Ratios-Banks'!J6 -> 0.016239044 | E6: ='[7]Financial Ratios-Banks'!K6 -> 0.00815039 | F6: ='[7]Financial Ratios-Banks'!L6 -> 0.013160156 | Q6: Muthoot | R6: =(N27-I27)/I27 -> 0.88887761 | S6: =(N27/I27)^(1/6)-1 -> 0.11181869
A7: ROE | B7: ='[7]Financial Ratios-Banks'!H7 -> 0.15427255 | C7: ='[7]Financial Ratios-Banks'!I7 -> 0.1513796 | D7: ='[7]Financial Ratios-Banks'!J7 -> 0.15380539 | E7: ='[7]Financial Ratios-Banks'!K7 -> 0.15897022 | F7: ='[7]Financial Ratios-Banks'!L7 -> 0.13931348 | H7: KPI | I7: 2025 | J7: 2026 | K7: 2027 | L7: 2028 | M7: 2029 | N7: 2030 | Q7: Bajaj Finance | R7: =(N33-I33)/I33 -> 1.2408536 | S7: =(N33/I33)^(1/6)-1 -> 0.14393737
A8: CAR | B8: ='[7]Financial Ratios-Banks'!H16 -> 0.18523669 | C8: ='[7]Financial Ratios-Banks'!I16 -> 0.18790386 | D8: ='[7]Financial Ratios-Banks'!J16 -> 0.1889416 | E8: ='[7]Financial Ratios-Banks'!K16 -> 0.19258674 | F8: ='[7]Financial Ratios-Banks'!L16 -> 0.18800549 | H8: Loan Book | I8: ='[7]Financial Projections'!V5 -> 1415710.3 | J8: ='[7]Financial Projections'!W5 -> 1589683.9 | K8: ='[7]Financial Projections'!X5 -> 1785036.7 | L8: ='[7]Financial Projections'!Y5 -> 2004396.1 | M8: ='[7]Financial Projections'!Z5 -> 2250712 | N8: ='[7]Financial Projections'!AA5 -> 2527297.2 | Q8: BHFL | R8: =(N39-I39)/I39 -> 1.6061922 | S8: =(N39/I39)^(1/6)-1 -> 0.1730983
H9: PAT | I9: ='[7]Financial Projections'!V14 -> 52473.033 | J9: ='[7]Financial Projections'!W14 -> 63887.542 | K9: ='[7]Financial Projections'!X14 -> 74552.191 | L9: ='[7]Financial Projections'!Y14 -> 87219.296 | M9: ='[7]Financial Projections'!Z14 -> 102240.55 | N9: ='[7]Financial Projections'!AA14 -> 120026.87 | R9: =AVERAGE(R2:R8) -> 1.0440538 | S9: =AVERAGE(S2:S8) -> 0.12380067
A10: KPI | B10: 2020 | C10: 2021 | D10: 2022 | E10: 2023 | F10: 2024 | H10: Revenue | I10: ='[7]Financial Projections'!V8 -> 178387.83 | J10: ='[7]Financial Projections'!W8 -> 197195.77 | K10: ='[7]Financial Projections'!X8 -> 218724.97 | L10: ='[7]Financial Projections'!Y8 -> 243407.19 | M10: ='[7]Financial Projections'!Z8 -> 271744.09 | N10: ='[7]Financial Projections'!AA8 -> 304318.63
A11: Loan Book | B11: ='[7]Balance Sheet-Banks'!L75 -> 706246.09 | C11: ='[7]Balance Sheet-Banks'!M75 -> 733729.04 | D11: ='[7]Balance Sheet-Banks'!N75 -> 859020.4 | E11: ='[7]Balance Sheet-Banks'!O75 -> 1083866.3 | F11: ='[7]Balance Sheet-Banks'!P75 -> 1260776.2 | H11: PBT | I11: ='[7]Financial Projections'!V12 -> 70122.989 | J11: ='[7]Financial Projections'!W12 -> 85376.91 | K11: ='[7]Financial Projections'!X12 -> 99628.746 | L11: ='[7]Financial Projections'!Y12 -> 116556.59 | M11: ='[7]Financial Projections'!Z12 -> 136630.43 | N11: ='[7]Financial Projections'!AA12 -> 160399.39
A12: Deposits | B12: ='[7]Balance Sheet-Banks'!L13 -> 800784.45 | C12: ='[7]Balance Sheet-Banks'!M13 -> 932522.15 | D12: ='[7]Balance Sheet-Banks'!N13 -> 1064571.6 | E12: ='[7]Balance Sheet-Banks'!O13 -> 1210832.1 | F12: ='[7]Balance Sheet-Banks'!P13 -> 1443579.9
A13: NIM | B13: ='[7]Financial Ratios-Banks'!N5 -> 0.0349392 | C13: ='[7]Financial Ratios-Banks'!O5 -> 0.038412647 | D13: ='[7]Financial Ratios-Banks'!P5 -> 0.04059494 | E13: ='[7]Financial Ratios-Banks'!Q5 -> 0.040920667 | F13: ='[7]Financial Ratios-Banks'!R5 -> 0.040905303 | H13: KPI | I13: 2025 | J13: 2026 | K13: 2027 | L13: 2028 | M13: 2029 | N13: 2030
A14: NPA | B14: ='[7]Financial Ratios-Banks'!N13 -> 0.0114 | C14: ='[7]Financial Ratios-Banks'!O13 -> 0.0076 | D14: ='[7]Financial Ratios-Banks'!P13 -> 0.0048 | E14: ='[7]Financial Ratios-Banks'!Q13 -> 0.0042 | F14: ='[7]Financial Ratios-Banks'!R13 -> 0.0039 | H14: Loan Book | I14: ='[7]Financial Projections'!AE5 -> 4154046.7 | J14: ='[7]Financial Projections'!AF5 -> 4559952.7 | K14: ='[7]Financial Projections'!AG5 -> 5005521.1 | L14: ='[7]Financial Projections'!AH5 -> 5494627.5 | M14: ='[7]Financial Projections'!AI5 -> 6031526.1 | N14: ='[7]Financial Projections'!AJ5 -> 6620886.9
A15: ROA | B15: ='[7]Financial Ratios-Banks'!N6 -> 0.016537611 | C15: ='[7]Financial Ratios-Banks'!O6 -> 0.017596731 | D15: ='[7]Financial Ratios-Banks'!P6 -> 0.01903788 | E15: ='[7]Financial Ratios-Banks'!Q6 -> 0.0043304005 | F15: ='[7]Financial Ratios-Banks'!R6 -> 0.0050106544 | H15: PAT | I15: ='[7]Financial Projections'!AE14 -> 65752.222 | J15: ='[7]Financial Projections'!AF14 -> 78715.149 | K15: ='[7]Financial Projections'!AG14 -> 81703.994 | L15: ='[7]Financial Projections'!AH14 -> 84386.945 | M15: ='[7]Financial Projections'!AI14 -> 86658.405 | N15: ='[7]Financial Projections'!AJ14 -> 88392.907
A16: ROE | B16: ='[7]Financial Ratios-Banks'!N7 -> 0.086512931 | C16: ='[7]Financial Ratios-Banks'!O7 -> 0.10977408 | D16: ='[7]Financial Ratios-Banks'!P7 -> 0.13687891 | E16: ='[7]Financial Ratios-Banks'!Q7 -> 0.15581121 | F16: ='[7]Financial Ratios-Banks'!R7 -> 0.16667176 | H16: Revenue | I16: ='[7]Financial Projections'!AE8 -> 368705.01 | J16: ='[7]Financial Projections'!AF8 -> 406003.48 | K16: ='[7]Financial Projections'!AG8 -> 447082.82 | L16: ='[7]Financial Projections'!AH8 -> 492327.07 | M16: ='[7]Financial Projections'!AI8 -> 542159.37 | N16: ='[7]Financial Projections'!AJ8 -> 597045.88
A17: CAR | B17: ='[7]Financial Ratios-Banks'!N16 -> 0 | C17: ='[7]Financial Ratios-Banks'!O16 -> 0.1912 | D17: ='[7]Financial Ratios-Banks'!P16 -> 0.1916 | E17: ='[7]Financial Ratios-Banks'!Q16 -> 0 | F17: ='[7]Financial Ratios-Banks'!R16 -> 0 | H17: PBT | I17: ='[7]Financial Projections'!AE12 -> 87669.63 | J17: ='[7]Financial Projections'!AF12 -> 104953.53 | K17: ='[7]Financial Projections'!AG12 -> 108938.66 | L17: ='[7]Financial Projections'!AH12 -> 112515.93 | M17: ='[7]Financial Projections'!AI12 -> 115544.54 | N17: ='[7]Financial Projections'!AJ12 -> 117857.21
A19: KPI | B19: 2020 | C19: 2021 | D19: 2022 | E19: 2023 | F19: 2024 | H19: KPI | I19: 2025 | J19: 2026 | K19: 2027 | L19: 2028 | M19: 2029 | N19: 2030
A20: Loan Book | B20: ='[7]Balance Sheet-Banks'!Q75 -> 2374311.2 | C20: ='[7]Balance Sheet-Banks'!R75 -> 2500599 | D20: ='[7]Balance Sheet-Banks'!S75 -> 2794076 | E20: ='[7]Balance Sheet-Banks'!T75 -> 3267902.1 | F20: ='[7]Balance Sheet-Banks'!U75 -> 3784272.7 | H20: Loan Book | I20: ='[7]Financial Projections'!D5 -> 1113076.3 | J20: ='[7]Financial Projections'!E5 -> 1239765.3 | K20: ='[7]Financial Projections'!F5 -> 1380873.8 | L20: ='[7]Financial Projections'!G5 -> 1538043.1 | M20: ='[7]Financial Projections'!H5 -> 1713101.2 | N20: ='[7]Financial Projections'!I5 -> 1908084.2
A21: Deposits | B21: ='[7]Balance Sheet-Banks'!Q13 -> 3274160.6 | C21: ='[7]Balance Sheet-Banks'!R13 -> 3715331.2 | D21: ='[7]Balance Sheet-Banks'!S13 -> 4087410.6 | E21: ='[7]Balance Sheet-Banks'!T13 -> 4468535.5 | F21: ='[7]Balance Sheet-Banks'!U13 -> 4966537.5 | H21: PAT | I21: ='[7]Financial Projections'!D14 -> 26450.45 | J21: ='[7]Financial Projections'!E14 -> 34713.369 | K21: ='[7]Financial Projections'!F14 -> 38340.122 | L21: ='[7]Financial Projections'!G14 -> 42350.052 | M21: ='[7]Financial Projections'!H14 -> 46783.318 | N21: ='[7]Financial Projections'!I14 -> 51684.106
A22: NIM | B22: ='[7]Financial Ratios-Banks'!T5 -> 0.030180423 | C22: ='[7]Financial Ratios-Banks'!U5 -> 0.029813056 | D22: ='[7]Financial Ratios-Banks'!V5 -> 0.029269536 | E22: ='[7]Financial Ratios-Banks'!W5 -> 0.031048727 | F22: ='[7]Financial Ratios-Banks'!X5 -> 0.030442395 | H22: Revenue | I22: ='[7]Financial Projections'!D8 -> 86510.21 | J22: ='[7]Financial Projections'!E8 -> 97760.527 | K22: ='[7]Financial Projections'!F8 -> 110536.24 | L22: ='[7]Financial Projections'!G8 -> 125050.62 | M22: ='[7]Financial Projections'!H8 -> 141547.42 | N22: ='[7]Financial Projections'!I8 -> 160305.23
A23: NPA | B23: ='[7]Financial Ratios-Banks'!T13 -> 0.015 | C23: ='[7]Financial Ratios-Banks'!U13 -> 0.0102 | D23: ='[7]Financial Ratios-Banks'!V13 -> 0.0067 | E23: ='[7]Financial Ratios-Banks'!W13 -> 0.0057 | F23: ='[7]Financial Ratios-Banks'!X13 -> 0.0047 | H23: PBT | I23: ='[7]Financial Projections'!D12 -> 35347.388 | J23: ='[7]Financial Projections'!E12 -> 46389.642 | K23: ='[7]Financial Projections'!F12 -> 51236.299 | L23: ='[7]Financial Projections'!G12 -> 56595.018 | M23: ='[7]Financial Projections'!H12 -> 62519.468 | N23: ='[7]Financial Projections'!I12 -> 69068.697
A24: ROA | B24: ='[7]Financial Ratios-Banks'!T6 -> 0.0067817501 | C24: ='[7]Financial Ratios-Banks'!U6 -> 0.0094985652 | D24: ='[7]Financial Ratios-Banks'!V6 -> 0.010118874 | E24: ='[7]Financial Ratios-Banks'!W6 -> 0.0094985652 | F24: ='[7]Financial Ratios-Banks'!X6 -> 0.010118874
A25: ROE | B25: ='[7]Financial Ratios-Banks'!T7 -> 0.070179713 | C25: ='[7]Financial Ratios-Banks'!U7 -> 0.085135999 | D25: ='[7]Financial Ratios-Banks'!V7 -> 0.11476229 | E25: ='[7]Financial Ratios-Banks'!W7 -> 0.1521337 | F25: ='[7]Financial Ratios-Banks'!X7 -> 0.15825603 | H25: KPI | I25: 2025 | J25: 2026 | K25: 2027 | L25: 2028 | M25: 2029 | N25: 2030
A26: CAR | B26: ='[7]Financial Ratios-Banks'!T16 -> 0 | C26: ='[7]Financial Ratios-Banks'!U16 -> 0 | D26: ='[7]Financial Ratios-Banks'!V16 -> 0 | E26: ='[7]Financial Ratios-Banks'!W16 -> 0 | F26: ='[7]Financial Ratios-Banks'!X16 -> 0 | H26: Loan Book | I26: ='[7]Financial Projections'!BF5 -> 999866.05 | J26: ='[7]Financial Projections'!BG5 -> 1133648 | K26: ='[7]Financial Projections'!BH5 -> 1285330 | L26: ='[7]Financial Projections'!BI5 -> 1457307 | M26: ='[7]Financial Projections'!BJ5 -> 1652294.5 | N26: ='[7]Financial Projections'!BK5 -> 1873371.4
H27: PAT | I27: ='[7]Financial Projections'!BF14 -> 70110.225 | J27: ='[7]Financial Projections'!BG14 -> 79613.828 | K27: ='[7]Financial Projections'!BH14 -> 90409.088 | L27: ='[7]Financial Projections'!BI14 -> 102672.11 | M27: ='[7]Financial Projections'!BJ14 -> 116603.08 | N27: ='[7]Financial Projections'!BK14 -> 132429.63
A28: KPI | B28: 2020 | C28: 2021 | D28: 2022 | E28: 2023 | F28: 2024 | H28: Revenue | I28: ='[7]Financial Projections'!BF8 -> 121936.1 | J28: ='[7]Financial Projections'!BG8 -> 138463.52 | K28: ='[7]Financial Projections'!BH8 -> 157237.01 | L28: ='[7]Financial Projections'!BI8 -> 178562.77 | M28: ='[7]Financial Projections'!BJ8 -> 202788.87 | N28: ='[7]Financial Projections'!BK8 -> 230311.06
A29: Loan Book | B29: ='[7]Balance Sheet-Banks'!B75 -> 582958.8 | C29: ='[7]Balance Sheet-Banks'!C75 -> 625749.9 | D29: ='[7]Balance Sheet-Banks'!D75 -> 725125.5 | E29: ='[7]Balance Sheet-Banks'!E75 -> 868387.54 | F29: ='[7]Balance Sheet-Banks'!F75 -> 999333.48 | H29: PBT | I29: ='[7]Financial Projections'!BF12 -> 93692.669 | J29: ='[7]Financial Projections'!BG12 -> 106392.93 | K29: ='[7]Financial Projections'!BH12 -> 120819.31 | L29: ='[7]Financial Projections'!BI12 -> 137207.14 | M29: ='[7]Financial Projections'!BJ12 -> 155823.98 | N29: ='[7]Financial Projections'!BK12 -> 176973.99
A30: Deposits | B30: ='[7]Balance Sheet-Banks'!B13 -> 642157.2 | C30: ='[7]Balance Sheet-Banks'!C13 -> 698302.63 | D30: ='[7]Balance Sheet-Banks'!D13 -> 820914.16 | E30: ='[7]Balance Sheet-Banks'!E13 -> 945824.72 | F30: ='[7]Balance Sheet-Banks'!F13 -> 1067102.4
A31: NIM | B31: ='[7]Financial Ratios-Banks'!B5 -> 0.034839247 | C31: ='[7]Financial Ratios-Banks'!C5 -> 0.034978829 | D31: ='[7]Financial Ratios-Banks'!D5 -> 0.033932439 | E31: ='[7]Financial Ratios-Banks'!E5 -> 0.038097615 | F31: ='[7]Financial Ratios-Banks'!F5 -> 0.038573855 | H31: KPI | I31: 2025 | J31: 2026 | K31: 2027 | L31: 2028 | M31: 2029 | N31: 2030
A32: NPA | B32: ='[7]Financial Ratios-Banks'!B13 -> 0.0156 | C32: ='[7]Financial Ratios-Banks'!C13 -> 0.0105 | D32: ='[7]Financial Ratios-Banks'!D13 -> 0.0073 | E32: ='[7]Financial Ratios-Banks'!E13 -> 0.0039 | F32: ='[7]Financial Ratios-Banks'!F13 -> 0.0031 | H32: Loan Book | I32: ='[7]Financial Projections'!AW5 -> 385704.45 | J32: ='[7]Financial Projections'!AX5 -> 455933.1 | K32: ='[7]Financial Projections'!AY5 -> 538948.9 | L32: ='[7]Financial Projections'!AZ5 -> 637080.12 | M32: ='[7]Financial Projections'!BA5 -> 753078.97 | N32: ='[7]Financial Projections'!BB5 -> 890198.77
A33: ROA | B33: ='[7]Financial Ratios-Banks'!B6 -> 0.011847773 | C33: ='[7]Financial Ratios-Banks'!C6 -> 0.0080723855 | D33: ='[7]Financial Ratios-Banks'!D6 -> 0.017404077 | E33: ='[7]Financial Ratios-Banks'!E6 -> 0.017267152 | F33: ='[7]Financial Ratios-Banks'!F6 -> 0.017703058 | H33: PAT | I33: ='[7]Financial Projections'!AW14 -> 19512.441 | J33: ='[7]Financial Projections'!AX14 -> 22922.014 | K33: ='[7]Financial Projections'!AY14 -> 26931.852 | L33: ='[7]Financial Projections'!AZ14 -> 31648.302 | M33: ='[7]Financial Projections'!BA14 -> 37196.653 | N33: ='[7]Financial Projections'!BB14 -> 43724.524
A34: ROE | B34: ='[7]Financial Ratios-Banks'!B7 -> 0.021731233 | C34: ='[7]Financial Ratios-Banks'!C7 -> 0.069890799 | D34: ='[7]Financial Ratios-Banks'!D7 -> 0.11950818 | E34: ='[7]Financial Ratios-Banks'!E7 -> 0.083369707 | F34: ='[7]Financial Ratios-Banks'!F7 -> 0.16774405 | H34: Revenue | I34: ='[7]Financial Projections'!AW8 -> 40392.276 | J34: ='[7]Financial Projections'!AX8 -> 47451.994 | K34: ='[7]Financial Projections'!AY8 -> 55754.839 | L34: ='[7]Financial Projections'!AZ8 -> 65521.09 | M34: ='[7]Financial Projections'!BA8 -> 77010.265 | N34: ='[7]Financial Projections'!BB8 -> 90528.139
A35: CAR | B35: ='[7]Financial Ratios-Banks'!B16 -> 0.17526661 | C35: ='[7]Financial Ratios-Banks'!C16 -> 0.19119999 | D35: ='[7]Financial Ratios-Banks'!D16 -> 0.18539112 | E35: ='[7]Financial Ratios-Banks'!E16 -> 0.1763865 | F35: ='[7]Financial Ratios-Banks'!F16 -> 0.16632526 | H35: PBT | I35: ='[7]Financial Projections'!AW12 -> 26075.694 | J35: ='[7]Financial Projections'!AX12 -> 30632.119 | K35: ='[7]Financial Projections'!AY12 -> 35990.715 | L35: ='[7]Financial Projections'!AZ12 -> 42293.601 | M35: ='[7]Financial Projections'!BA12 -> 49708.21 | N35: ='[7]Financial Projections'!BB12 -> 58431.811
A37: KPI | B37: 2020 | C37: 2021 | D37: 2022 | E37: 2023 | F37: 2024 | H37: KPI | I37: 20252 | J37: 2026 | K37: 2027 | L37: 2028 | M37: 2029 | N37: 2030
A38: Loan Book | B38: ='[7]Balance Sheet-NBFCs'!L27 -> 470677.41 | C38: ='[7]Balance Sheet-NBFCs'!M27 -> 588085.17 | D38: ='[7]Balance Sheet-NBFCs'!N27 -> 645276.41 | E38: ='[7]Balance Sheet-NBFCs'!O27 -> 705543.84 | F38: ='[7]Balance Sheet-NBFCs'!P27 -> 881871.71 | H38: Loan Book | I38: ='[7]Financial Projections'!AN5 -> 97673.66 | J38: ='[7]Financial Projections'!AO5 -> 120303.32 | K38: ='[7]Financial Projections'!AP5 -> 148175.98 | L38: ='[7]Financial Projections'!AQ5 -> 182506.34 | M38: ='[7]Financial Projections'!AR5 -> 224790.59 | N38: ='[7]Financial Projections'!AS5 -> 276871.53
A39: Deposits | B39: ='[7]Balance Sheet-NBFCs'!L14 -> 2560.06 | C39: ='[7]Balance Sheet-NBFCs'!M14 -> 2579.53 | D39: ='[7]Balance Sheet-NBFCs'!N14 -> 2235.26 | E39: ='[7]Balance Sheet-NBFCs'!O14 -> 3314.76 | F39: ='[7]Balance Sheet-NBFCs'!P14 -> 4018.26 | H39: PAT | I39: ='[7]Financial Projections'!AN14 -> 1973.3077 | J39: ='[7]Financial Projections'!AO14 -> 2376.9939 | K39: ='[7]Financial Projections'!AP14 -> 2872.1259 | L39: ='[7]Financial Projections'!AQ14 -> 3479.8093 | M39: ='[7]Financial Projections'!AR14 -> 4226.0367 | N39: ='[7]Financial Projections'!AS14 -> 5142.8191
A40: NIM | B40: ='[7]Financial Ratios-NBFCs'!L5 -> 0.13088292 | C40: ='[7]Financial Ratios-NBFCs'!M5 -> 0.11923922 | D40: ='[7]Financial Ratios-NBFCs'!N5 -> 0.1178799 | E40: ='[7]Financial Ratios-NBFCs'!O5 -> 0.10332415 | F40: ='[7]Financial Ratios-NBFCs'!P5 -> 0.10253835 | H40: Revenue | I40: ='[7]Financial Projections'!AN8 -> 3130.5905 | J40: ='[7]Financial Projections'!AO8 -> 3772.7275 | K40: ='[7]Financial Projections'!AP8 -> 4560.4009 | L40: ='[7]Financial Projections'!AQ8 -> 5527.2035 | M40: ='[7]Financial Projections'!AR8 -> 6714.5059 | N40: ='[7]Financial Projections'!AS8 -> 8173.2592
A41: NPA | B41: ='[7]Financial Ratios-NBFCs'!L13 -> 0.0196 | C41: ='[7]Financial Ratios-NBFCs'!M13 -> 0.0078 | D41: ='[7]Financial Ratios-NBFCs'!N13 -> 0.0271 | E41: ='[7]Financial Ratios-NBFCs'!O13 -> 0.0345 | F41: ='[7]Financial Ratios-NBFCs'!P13 -> 0.0293 | H41: PBT | I41: ='[7]Financial Projections'!AN12 -> 2637.0543 | J41: ='[7]Financial Projections'!AO12 -> 3176.5253 | K41: ='[7]Financial Projections'!AP12 -> 3838.2011 | L41: ='[7]Financial Projections'!AQ12 -> 4650.2864 | M41: ='[7]Financial Projections'!AR12 -> 5647.5166 | N41: ='[7]Financial Projections'!AS12 -> 6872.6702
A42: ROA | B42: ='[7]Financial Ratios-NBFCs'!L6 -> 0.057736576 | C42: ='[7]Financial Ratios-NBFCs'!M6 -> 0.055635055 | D42: ='[7]Financial Ratios-NBFCs'!N6 -> 0.052823772 | E42: ='[7]Financial Ratios-NBFCs'!O6 -> 0.045786843 | F42: ='[7]Financial Ratios-NBFCs'!P6 -> 0.046310986
A43: ROE | B43: ='[7]Financial Ratios-NBFCs'!L7 -> 0.264027 | C43: ='[7]Financial Ratios-NBFCs'!M7 -> 0.24232024 | D43: ='[7]Financial Ratios-NBFCs'!N7 -> 0.21064614 | E43: ='[7]Financial Ratios-NBFCs'!O7 -> 0.16565695 | F43: ='[7]Financial Ratios-NBFCs'!P7 -> 0.17347158
A44: CET 1 | B44: ='[7]Financial Ratios-NBFCs'!L18 -> 0.2429986 | C44: ='[7]Financial Ratios-NBFCs'!M18 -> 0.26314143 | D44: ='[7]Financial Ratios-NBFCs'!N18 -> 0.29098575 | E44: ='[7]Financial Ratios-NBFCs'!O18 -> 0.31011667 | F44: ='[7]Financial Ratios-NBFCs'!P18 -> 0.29607881 | H44: KPI | I44: 2020 | J44: 2021 | K44: 2022 | L44: 2023 | M44: 2024
H45: Loan Book | I45: ='[7]Balance Sheet-NBFCs'!B27 -> 27975.41 | J45: ='[7]Balance Sheet-NBFCs'!C27 -> 33418.9 | K45: ='[7]Balance Sheet-NBFCs'!D27 -> 46482.07 | L45: ='[7]Balance Sheet-NBFCs'!E27 -> 62113.89 | M45: ='[7]Balance Sheet-NBFCs'!F27 -> 79300.75
A46: KPI | B46: 2020 | C46: 2021 | D46: 2022 | E46: 2023 | F46: 2024 | H46: Deposits | I46: ='[7]Balance Sheet-NBFCs'!B14 -> 0 | J46: ='[7]Balance Sheet-NBFCs'!C14 -> 0 | K46: ='[7]Balance Sheet-NBFCs'!D14 -> 510 | L46: ='[7]Balance Sheet-NBFCs'!E14 -> 175.77 | M46: ='[7]Balance Sheet-NBFCs'!F14 -> 184.26
A47: Loan Book | B47: ='[7]Balance Sheet-NBFCs'!G27 -> 141376.05 | C47: ='[7]Balance Sheet-NBFCs'!H27 -> 146686.87 | D47: ='[7]Balance Sheet-NBFCs'!I27 -> 191423.25 | E47: ='[7]Balance Sheet-NBFCs'!J27 -> 242268.93 | F47: ='[7]Balance Sheet-NBFCs'!K27 -> 326293.32 | H47: NIM | I47: ='[7]Financial Ratios-NBFCs'!B5 -> 0.022538474 | J47: ='[7]Financial Ratios-NBFCs'!C5 -> 0.02484833 | K47: ='[7]Financial Ratios-NBFCs'!D5 -> 0.02779029 | L47: ='[7]Financial Ratios-NBFCs'!E5 -> 0.032097425 | M47: ='[7]Financial Ratios-NBFCs'!F5 -> 0.030893292
A48: Deposits | B48: ='[7]Balance Sheet-NBFCs'!G14 -> 21427.1 | C48: ='[7]Balance Sheet-NBFCs'!H14 -> 25803.43 | D48: ='[7]Balance Sheet-NBFCs'!I14 -> 30799.52 | E48: ='[7]Balance Sheet-NBFCs'!J14 -> 44665.56 | F48: ='[7]Balance Sheet-NBFCs'!K14 -> 60150.92 | H48: NPA | I48: ='[7]Financial Ratios-NBFCs'!B13 -> 0.0005 | J48: ='[7]Financial Ratios-NBFCs'!C13 -> 0.0018 | K48: ='[7]Financial Ratios-NBFCs'!D13 -> 0.0014 | L48: ='[7]Financial Ratios-NBFCs'!E13 -> 0.0008 | M48: ='[7]Financial Ratios-NBFCs'!F13 -> 0.001
A49: NIM | B49: ='[7]Financial Ratios-NBFCs'!G5 -> 0.084930684 | C49: ='[7]Financial Ratios-NBFCs'!H5 -> 0.08413534 | D49: ='[7]Financial Ratios-NBFCs'!I5 -> 0.08602948 | E49: ='[7]Financial Ratios-NBFCs'!J5 -> 0.086742937 | F49: ='[7]Financial Ratios-NBFCs'!K5 -> 0.082822133 | H49: ROA | I49: ='[7]Financial Ratios-NBFCs'!B6 -> 0.013429949 | J49: ='[7]Financial Ratios-NBFCs'!C6 -> 0.011970975 | K49: ='[7]Financial Ratios-NBFCs'!D6 -> 0.014623175 | L49: ='[7]Financial Ratios-NBFCs'!E6 -> 0.019454284 | M49: ='[7]Financial Ratios-NBFCs'!F6 -> 0.021157052
A50: NPA | B50: ='[7]Financial Ratios-NBFCs'!G13 -> 0.0065 | C50: ='[7]Financial Ratios-NBFCs'!H13 -> 0.0075 | D50: ='[7]Financial Ratios-NBFCs'!I13 -> 0.0068 | E50: ='[7]Financial Ratios-NBFCs'!J13 -> 0.0034 | F50: ='[7]Financial Ratios-NBFCs'!K13 -> 0.0037 | H50: ROE | I50: ='[7]Financial Ratios-NBFCs'!B7 -> 0.075437814 | J50: ='[7]Financial Ratios-NBFCs'!C7 -> 0.075128228 | K50: ='[7]Financial Ratios-NBFCs'!D7 -> 0.10526363 | L50: ='[7]Financial Ratios-NBFCs'!E7 -> 0.11975409 | M50: ='[7]Financial Ratios-NBFCs'!F7 -> 0.14151469
A51: ROA | B51: ='[7]Financial Ratios-NBFCs'!G6 -> 0.032019625 | C51: ='[7]Financial Ratios-NBFCs'!H6 -> 0.025775994 | D51: ='[7]Financial Ratios-NBFCs'!I6 -> 0.033073189 | E51: ='[7]Financial Ratios-NBFCs'!J6 -> 0.041811737 | F51: ='[7]Financial Ratios-NBFCs'!K6 -> 0.038460392 | H51: CAR | I51: ='[7]Financial Ratios-NBFCs'!B16 -> 0.25151808 | J51: ='[7]Financial Ratios-NBFCs'!C16 -> 0.21333963 | K51: ='[7]Financial Ratios-NBFCs'!D16 -> 0.197179 | L51: ='[7]Financial Ratios-NBFCs'!E16 -> 0.22971673 | M51: ='[7]Financial Ratios-NBFCs'!F16 -> 0.21282128
A52: ROE | B52: ='[7]Financial Ratios-NBFCs'!G7 -> 0.16282511 | C52: ='[7]Financial Ratios-NBFCs'!H7 -> 0.11971859 | D52: ='[7]Financial Ratios-NBFCs'!I7 -> 0.16078237 | E52: ='[7]Financial Ratios-NBFCs'!J7 -> 0.21164743 | F52: ='[7]Financial Ratios-NBFCs'!K7 -> 0.18842303
A53: CET 1 | B53: ='[7]Financial Ratios-NBFCs'!G18 -> 0.196 | C53: ='[7]Financial Ratios-NBFCs'!H18 -> 0.236 | D53: ='[7]Financial Ratios-NBFCs'!I18 -> 0.238 | E53: ='[7]Financial Ratios-NBFCs'!J18 -> 0.232 | F53: ='[7]Financial Ratios-NBFCs'!K18 -> 0.227

Sheet Tables-FMCG
A1: KPI | B1: 2020 | C1: 2021 | D1: 2022 | E1: 2023 | F1: 2024 | G1: 2025 | I1: KPI | J1: 2020 | K1: 2021 | L1: 2022 | M1: 2023 | N1: 2024 | O1: 2025 | Q1: KPI | R1: 2020 | S1: 2021 | T1: 2022 | U1: 2023 | V1: 2024 | W1: 2025
A2: Revenue | B2: ='[8]Income Statement'!B6 -> 24930.19 | C2: ='[8]Income Statement'!C6 -> 24339.27 | D2: ='[8]Income Statement'!D6 -> 31093.76 | E2: ='[8]Income Statement'!E6 -> 42968.9 | F2: ='[8]Income Statement'!F6 -> 50935.28 | G2: ='[8]Income Statement'!G6 -> 59482.36 | I2: Revenue | J2: ='[8]Income Statement'!Q6 -> 53991.36 | K2: ='[8]Income Statement'!R6 -> 55787.68 | L2: ='[8]Income Statement'!S6 -> 67041.31 | M2: ='[8]Income Statement'!T6 -> 78498.7 | N2: ='[8]Income Statement'!U6 -> 76584.65 | O2: ='[8]Income Statement'!V6 -> 84142.47 | Q2: Revenue | R2: ='[8]Income Statement'!AG6 -> 3635.4 | S2: ='[8]Income Statement'!AH6 -> 2794.56 | T2: ='[8]Income Statement'!AI6 -> 4673.23 | U2: ='[8]Income Statement'!AJ6 -> 8502.94 | V2: ='[8]Income Statement'!AK6 -> 12664.38 | W2: ='[8]Income Statement'!AL6 -> 17353.17
A3: EBITDA | B3: ='[8]Income Statement'!B15+'[8]Income Statement'!B11+'[8]Income Statement'!B12 -> 2188.3 | C3: ='[8]Income Statement'!C15+'[8]Income Statement'!C11+'[8]Income Statement'!C12 -> 1939.26 | D3: ='[8]Income Statement'!D15+'[8]Income Statement'!D11+'[8]Income Statement'!D12 -> 2615.99 | E3: ='[8]Income Statement'!E15+'[8]Income Statement'!E11+'[8]Income Statement'!E12 -> 3766.37 | F3: ='[8]Income Statement'!F15+'[8]Income Statement'!F11+'[8]Income Statement'!F12 -> 4250.22 | G3: ='[8]Income Statement'!G15+'[8]Income Statement'!G11+'[8]Income Statement'!G12 -> 4611.64 | I3: EBITDA | J3: ='[8]Income Statement'!Q18+'[8]Income Statement'!Q13+'[8]Income Statement'!Q14 -> 21866.27 | K3: ='[8]Income Statement'!R18+'[8]Income Statement'!R13+'[8]Income Statement'!R14 -> 19628.34 | L3: ='[8]Income Statement'!S18+'[8]Income Statement'!S13+'[8]Income Statement'!S14 -> 22512.24 | M3: ='[8]Income Statement'!T18+'[8]Income Statement'!T13+'[8]Income Statement'!T14 -> 27694.46 | N3: ='[8]Income Statement'!U18+'[8]Income Statement'!U13+'[8]Income Statement'!U14 -> 27957.44 | O3: ='[8]Income Statement'!V18+'[8]Income Statement'!V13+'[8]Income Statement'!V14 -> 28618.32 | Q3: EBITDA | R3: ='[8]Income Statement'!AG15+'[8]Income Statement'!$AG$11+'[8]Income Statement'!$AG$12 -> 688.46 | S3: ='[8]Income Statement'!AH15+'[8]Income Statement'!$AG$11+'[8]Income Statement'!$AG$12 -> 360.59 | T3: ='[8]Income Statement'!AI15+'[8]Income Statement'!$AG$11+'[8]Income Statement'!$AG$12 -> 626.56 | U3: ='[8]Income Statement'!AJ15+'[8]Income Statement'!$AG$11+'[8]Income Statement'!$AG$12 -> 964.7 | V3: ='[8]Income Statement'!AK15+'[8]Income Statement'!$AG$11+'[8]Income Statement'!$AG$12 -> 1714.23 | W3: ='[8]Income Statement'!AL15+'[8]Income Statement'!$AG$11+'[8]Income Statement'!$AG$12 -> 2436.28 | Z3: Dmart | AA3: =(F11-B11)/B11 -> 0.63910992 | AB3: =(F11/B11)^(1/5)-1 -> 0.10387937
A4: Net Profit | B4: ='[8]Income Statement'!$B$21 -> 1300.98 | C4: ='[8]Income Statement'!$B$21 -> 1300.98 | D4: ='[8]Income Statement'!$B$21 -> 1300.98 | E4: ='[8]Income Statement'!$B$21 -> 1300.98 | F4: ='[8]Income Statement'!$B$21 -> 1300.98 | G4: ='[8]Income Statement'!$B$21 -> 1300.98 | I4: Net Profit | J4: ='[8]Income Statement'!$Q$30 -> 15592.78 | K4: ='[8]Income Statement'!$Q$30 -> 15592.78 | L4: ='[8]Income Statement'!$Q$30 -> 15592.78 | M4: ='[8]Income Statement'!$Q$30 -> 15592.78 | N4: ='[8]Income Statement'!$Q$30 -> 15592.78 | O4: ='[8]Income Statement'!$Q$30 -> 15592.78 | Q4: Net Profit | R4: ='[8]Income Statement'!AG25 -> 105.98 | S4: ='[8]Income Statement'!AH25 -> -181.13 | T4: ='[8]Income Statement'!AI25 -> 34.6 | U4: ='[8]Income Statement'!AJ25 -> 393.69 | V4: ='[8]Income Statement'!AK25 -> 1477.39 | W4: ='[8]Income Statement'!AL25 -> 1534.41 | Z4: HUL | AA4: =(G25-B25)/B25 -> 0.14387076 | AB4: =(G25/B25)^(1/6)-1 -> 0.022655818
A5: EBITDA Margin | B5: =[8]!Table40[[#This Row],[2020]] -> 0.1360556 | C5: =[8]!Table40[[#This Row],[2021]] -> 0.1378773 | D5: =[8]!Table40[[#This Row],[2022]] -> 0.13379597 | E5: =[8]!Table40[[#This Row],[2023]] -> 0.13722527 | F5: =[8]!Table40[[#This Row],[2024]] -> 0.13530239 | G5: =[8]!Table40[[#This Row],[2025]] -> 0.13463532 | I5: EBITDA Margin | J5: =J3/J2 -> 0.40499573 | K5: =K3/K2 -> 0.35184005 | L5: =L3/L2 -> 0.33579654 | M5: =M3/M2 -> 0.35280151 | N5: =N3/N2 -> 0.36505279 | O5: =O3/O2 -> 0.34011742 | Q5: EBITDA Margin | R5: =R3/R2 -> 0.18937668 | S5: =S3/S2 -> 0.12903284 | T5: =T3/T2 -> 0.13407429 | U5: =U3/U2 -> 0.11345488 | V5: =V3/V2 -> 0.13535838 | W5: =W3/W2 -> 0.14039395 | Z5: ITC | AA5: =(V11-R11)/R11 -> 2.1604419 | AB5: =(V11/R11)^(1/5)-1 -> 0.25877921
A6: Net Profit Margin | B6: =[8]!Table40[[#This Row],[2020]] -> 0.052310798 | C6: =[8]!Table40[[#This Row],[2021]] -> 0.045538138 | D6: =[8]!Table40[[#This Row],[2022]] -> 0.048178816 | E6: =[8]!Table40[[#This Row],[2023]] -> 0.055517377 | F6: =[8]!Table40[[#This Row],[2024]] -> 0.04992456 | G6: =[8]!Table40[[#This Row],[2025]] -> 0.045612179 | I6: Net Profit Margin | J6: =J4/J2 -> 0.28880139 | K6: =K4/K2 -> 0.27950221 | L6: =L4/L2 -> 0.23258466 | M6: =M4/M2 -> 0.19863743 | N6: =N4/N2 -> 0.2036019 | O6: =O4/O2 -> 0.18531403 | Q6: Net Profit Margin | R6: =R4/R2 -> 0.029152225 | S6: =S4/S2 -> -0.064815212 | T6: =T4/T2 -> 0.0074038727 | U6: =U4/U2 -> 0.046300456 | V6: =V4/V2 -> 0.11665711 | W6: =W4/W2 -> 0.088422461 | Z6: Titan | AA6: =(N25-J25)/J25 -> 1.0528355 | AB6: =(N11/J11)^(1/5)-1 -> 0.0031827774
Z7: Trent | AA7: =(W25-R25)/R25 -> 0.97596433 | AB7: =(N25/J25)^(1/5)-1 -> 0.15470442
A8: Forecasts | B8: 2026 | C8: 2027 | D8: 2028 | E8: 2029 | F8: 2030 | I8: Forecasts | J8: 2026 | K8: 2027 | L8: 2028 | M8: 2029 | N8: 2030 | Q8: Forecasts | R8: 2026 | S8: 2027 | T8: 2028 | U8: 2029 | V8: 2030 | Z8: VBL | AA8: =(N11-J11)/J11 -> 0.016015511 | AB8: =(W25/R25)^(1/6)-1 -> 0.12020245
A9: Revenue | B9: ='[8]Income Statement Forecast'!D6 -> 68759.671 | C9: ='[8]Income Statement Forecast'!E6 -> 79484.029 | D9: ='[8]Income Statement Forecast'!F6 -> 91881.154 | E9: ='[8]Income Statement Forecast'!G6 -> 106211.97 | F9: ='[8]Income Statement Forecast'!H6 -> 122778.12 | I9: Revenue | J9: ='[8]Income Statement Forecast'!W6 -> 90670.71 | K9: ='[8]Income Statement Forecast'!X6 -> 97722.988 | L9: ='[8]Income Statement Forecast'!Y6 -> 105341.29 | M9: ='[8]Income Statement Forecast'!Z6 -> 113570.96 | N9: ='[8]Income Statement Forecast'!AA6 -> 122461 | Q9: Revenue | R9: ='[8]Income Statement Forecast'!AO6 -> 22575.396 | S9: ='[8]Income Statement Forecast'!AP6 -> 29381.465 | T9: ='[8]Income Statement Forecast'!AQ6 -> 38252.548 | U9: ='[8]Income Statement Forecast'!AR6 -> 49816.053 | V9: ='[8]Income Statement Forecast'!AS6 -> 64890.066 | AA9: =AVERAGE(AA3:AA8) -> 0.83137299 | AB9: =AVERAGE(AB3:AB8) -> 0.11056734
A10: EBITDA | B10: ='[8]Income Statement Forecast'!D12 -> 4698.078 | C10: ='[8]Income Statement Forecast'!E12 -> 5412.4404 | D10: ='[8]Income Statement Forecast'!F12 -> 6235.1236 | E10: ='[8]Income Statement Forecast'!G12 -> 7182.4997 | F10: ='[8]Income Statement Forecast'!H12 -> 8273.4063 | I10: EBITDA | J10: ='[8]Income Statement Forecast'!W12 -> 32462.98 | K10: ='[8]Income Statement Forecast'!X12 -> 34987.918 | L10: ='[8]Income Statement Forecast'!Y12 -> 37715.511 | M10: ='[8]Income Statement Forecast'!Z12 -> 40661.995 | N10: ='[8]Income Statement Forecast'!AA12 -> 43844.908 | Q10: EBITDA | R10: ='[8]Income Statement Forecast'!AO12 -> 3711.5639 | S10: ='[8]Income Statement Forecast'!AP12 -> 4830.5324 | T10: ='[8]Income Statement Forecast'!AQ12 -> 6289.0048 | U10: ='[8]Income Statement Forecast'!AR12 -> 8190.1315 | V10: ='[8]Income Statement Forecast'!AS12 -> 10668.412
A11: Net Profit | B11: ='[8]Income Statement Forecast'!D18 -> 2632.8514 | C11: ='[8]Income Statement Forecast'!E18 -> 2965.0562 | D11: ='[8]Income Statement Forecast'!F18 -> 3350.9217 | E11: ='[8]Income Statement Forecast'!G18 -> 3798.1351 | F11: ='[8]Income Statement Forecast'!H18 -> 4315.5329 | I11: Net Profit | J11: ='[8]Income Statement Forecast'!W18 -> 30948.524 | K11: ='[8]Income Statement Forecast'!X18 -> 25159.063 | L11: ='[8]Income Statement Forecast'!Y18 -> 27092.187 | M11: ='[8]Income Statement Forecast'!Z18 -> 29183.086 | N11: ='[8]Income Statement Forecast'!AA18 -> 31444.181 | Q11: Net Profit | R11: ='[8]Income Statement Forecast'!AO18 -> 1477.9384 | S11: ='[8]Income Statement Forecast'!AP18 -> 2039.1123 | T11: ='[8]Income Statement Forecast'!AQ18 -> 2716.9239 | U11: ='[8]Income Statement Forecast'!AR18 -> 3571.8102 | V11: ='[8]Income Statement Forecast'!AS18 -> 4670.9384
A12: EBITDA Margin | B12: =B10/B9 -> 0.068326069 | C12: =C10/C9 -> 0.068094691 | D12: =D10/D9 -> 0.067860745 | E12: =E10/E9 -> 0.0676242 | F12: =F10/F9 -> 0.067385023 | I12: EBITDA Margin | J12: =J10/J9 -> 0.35803161 | K12: =K10/K9 -> 0.35803161 | L12: =L10/L9 -> 0.35803161 | M12: =M10/M9 -> 0.35803161 | N12: =N10/N9 -> 0.35803161 | Q12: EBITDA Margin | R12: =R10/R9 -> 0.16440747 | S12: =S10/S9 -> 0.16440747 | T12: =T10/T9 -> 0.16440747 | U12: =U10/U9 -> 0.16440747 | V12: =V10/V9 -> 0.16440747
A13: Net Profit Margin | B13: =B11/B9 -> 0.038290634 | C13: =C11/C9 -> 0.037303798 | D13: =D11/D9 -> 0.036470174 | E13: =E11/E9 -> 0.035759952 | F13: =F11/F9 -> 0.035149039 | I13: Net Profit Margin | J13: =J11/J9 -> 0.3413288 | K13: =K11/K9 -> 0.25745286 | L13: =L11/L9 -> 0.25718488 | M13: =M11/M9 -> 0.25695904 | N13: =N11/N9 -> 0.25676894 | Q13: Net Profit Margin | R13: =R11/R9 -> 0.065466775 | S13: =S11/S9 -> 0.069401316 | T13: =T11/T9 -> 0.071025959 | U13: =U11/U9 -> 0.071699984 | V13: =V11/V9 -> 0.071982335
A15: KPI | B15: 2020 | C15: 2021 | D15: 2022 | E15: 2023 | F15: 2024 | I15: KPI | J15: 2020 | K15: 2021 | L15: 2022 | M15: 2023 | N15: 2024 | O15: 2025 | Q15: KPI | R15: 2020 | S15: 2021 | T15: 2022 | U15: 2023 | V15: 2024
A16: Revenue | B16: ='[8]Income Statement'!J6 -> 40415 | C16: ='[8]Income Statement'!K6 -> 47438 | D16: ='[8]Income Statement'!L6 -> 52704 | E16: ='[8]Income Statement'!M6 -> 61092 | F16: ='[8]Income Statement'!N6 -> 62707 | I16: Revenue | J16: ='[8]Income Statement'!Y6 -> 21205 | K16: ='[8]Income Statement'!Z6 -> 21830 | L16: ='[8]Income Statement'!AA6 -> 29033 | M16: ='[8]Income Statement'!AB6 -> 40883 | N16: ='[8]Income Statement'!AC6 -> 51617 | O16: ='[8]Income Statement'!AD6 -> 60942 | Q16: Revenue | R16: ='[8]Income Statement'!AO6 -> 6592.76 | S16: ='[8]Income Statement'!AP6 -> 9026.216 | T16: ='[8]Income Statement'!AQ6 -> 13429.407 | U16: ='[8]Income Statement'!AR6 -> 16400.422 | V16: ='[8]Income Statement'!AS6 -> 20602.596
A17: EBITDA | B17: ='[8]Income Statement'!J16+'[8]Income Statement'!J12+'[8]Income Statement'!J13 -> 10493 | C17: ='[8]Income Statement'!K16+'[8]Income Statement'!K12+'[8]Income Statement'!K13 -> 12036 | D17: ='[8]Income Statement'!L16+'[8]Income Statement'!L12+'[8]Income Statement'!L13 -> 13115 | E17: ='[8]Income Statement'!M16+'[8]Income Statement'!M12+'[8]Income Statement'!M13 -> 14660 | F17: ='[8]Income Statement'!N16+'[8]Income Statement'!N12+'[8]Income Statement'!N13 -> 15474 | I17: EBITDA | J17: ='[8]Income Statement'!Y16+'[8]Income Statement'!Y12+'[8]Income Statement'!Y13 -> 2620 | K17: ='[8]Income Statement'!Z16+'[8]Income Statement'!Z12+'[8]Income Statement'!Z13 -> 1910 | L17: ='[8]Income Statement'!AA16+'[8]Income Statement'!AA12+'[8]Income Statement'!AA13 -> 3575 | M17: ='[8]Income Statement'!AB16+'[8]Income Statement'!AB12+'[8]Income Statement'!AB13 -> 5187 | N17: ='[8]Income Statement'!AC16+'[8]Income Statement'!AC12+'[8]Income Statement'!AC13 -> 5825 | O17: ='[8]Income Statement'!AD16+'[8]Income Statement'!AD12+'[8]Income Statement'!AD13 -> 6180 | Q17: EBITDA | R17: =[8]!VBL_IS[[#This Row],[2020]]+'[8]Income Statement'!AO13+'[8]Income Statement'!AO14 -> 1238.837 | S17: =[8]!VBL_IS[[#This Row],[2021]]+'[8]Income Statement'!AP13+'[8]Income Statement'!AP14 -> 1722.57 | T17: =[8]!VBL_IS[[#This Row],[2022]]+'[8]Income Statement'!AQ13+'[8]Income Statement'!AQ14 -> 2826.954 | U17: =[8]!VBL_IS[[#This Row],[2023]]+'[8]Income Statement'!AR13+'[8]Income Statement'!AR14 -> 3688.844 | V17: =[8]!VBL_IS[[#This Row],[2024]]+'[8]Income Statement'!AS13+'[8]Income Statement'!AS14 -> 4832.339
A18: Net Profit | B18: ='[8]Income Statement'!$J$27 -> 6756 | C18: ='[8]Income Statement'!$J$27 -> 6756 | D18: ='[8]Income Statement'!$J$27 -> 6756 | E18: ='[8]Income Statement'!$J$27 -> 6756 | F18: ='[8]Income Statement'!$J$27 -> 6756 | I18: Net Profit | J18: ='[8]Income Statement'!Y28 -> 1493 | K18: ='[8]Income Statement'!Z28 -> 974 | L18: ='[8]Income Statement'!AA28 -> 2198 | M18: ='[8]Income Statement'!AB28 -> 3274 | N18: ='[8]Income Statement'!AC28 -> 3496 | O18: ='[8]Income Statement'!AD28 -> 3337 | Q18: Net Profit | R18: ='[8]Income Statement'!AO27 -> 357.268 | S18: ='[8]Income Statement'!AP27 -> 746.052 | T18: ='[8]Income Statement'!AQ27 -> 1550.114 | U18: ='[8]Income Statement'!AR27 -> 2101.813 | V18: ='[8]Income Statement'!AS27 -> 2634.284
A19: EBITDA Margin | B19: =B17/B16 -> 0.25963133 | C19: =C17/C16 -> 0.25372065 | D19: =D17/D16 -> 0.24884259 | E19: =E17/E16 -> 0.23996595 | F19: =F17/F16 -> 0.24676671 | I19: EBITDA Margin | J19: =J17/J16 -> 0.12355577 | K19: =K17/K16 -> 0.087494274 | L19: =L17/L16 -> 0.12313574 | M19: =M17/M16 -> 0.12687425 | N19: =N17/N16 -> 0.11285042 | O19: =O17/O16 -> 0.1014079 | Q19: EBITDA Margin | R19: =R17/R16 -> 0.18790871 | S19: =S17/S16 -> 0.19084077 | T19: =T17/T16 -> 0.21050475 | U19: =U17/U16 -> 0.22492372 | V19: =V17/V16 -> 0.23455001
A20: Net Profit Margin | B20: =B18/B16 -> 0.16716566 | C20: =C18/C16 -> 0.14241747 | D20: =D18/D16 -> 0.12818761 | E20: =E18/E16 -> 0.11058731 | F20: =F18/F16 -> 0.10773917 | I20: Net Profit Margin | J20: =J18/J16 -> 0.070407923 | K20: =K18/K16 -> 0.044617499 | L20: =L18/L16 -> 0.075706954 | M20: =M18/M16 -> 0.080082186 | N20: =N18/N16 -> 0.067729624 | O20: =O18/O16 -> 0.054756982 | Q20: Net Profit Margin | R20: =R18/R16 -> 0.054190961 | S20: =S18/S16 -> 0.082653905 | T20: =T18/T16 -> 0.11542684 | U20: =U18/U16 -> 0.12815603 | V20: =V18/V16 -> 0.12786175
A22: Forecasts | B22: 2025 | C22: 2026 | D22: 2027 | E22: 2028 | F22: 2029 | G22: 2030 | I22: Forecasts | J22: 2026 | K22: 2027 | L22: 2028 | M22: 2029 | N22: 2030 | Q22: Forecasts | R22: 2025 | S22: 2026 | T22: 2027 | U22: 2028 | V22: 2029 | W22: 2030
A23: Revenue | B23: ='[8]Income Statement Forecast'!M6 -> 67473.415 | C23: ='[8]Income Statement Forecast'!N6 -> 72603.056 | D23: ='[8]Income Statement Forecast'!O6 -> 78123.642 | E23: ='[8]Income Statement Forecast'!P6 -> 84065.008 | F23: ='[8]Income Statement Forecast'!Q6 -> 90459.271 | G23: ='[8]Income Statement Forecast'!R6 -> 97340.997 | I23: Revenue | J23: ='[8]Income Statement Forecast'!AF6 -> 72666.305 | K23: ='[8]Income Statement Forecast'!AG6 -> 86646.384 | L23: ='[8]Income Statement Forecast'!AH6 -> 103316.29 | M23: ='[8]Income Statement Forecast'!AI6 -> 123193.61 | N23: ='[8]Income Statement Forecast'!AJ6 -> 146895.54 | Q23: Revenue | R23: ='[8]Income Statement Forecast'!AX6 -> 24911.41 | S23: ='[8]Income Statement Forecast'!AY6 -> 30121.378 | T23: ='[8]Income Statement Forecast'!AZ6 -> 36420.972 | U23: ='[8]Income Statement Forecast'!BA6 -> 44038.083 | V23: ='[8]Income Statement Forecast'!BB6 -> 53248.263 | W23: ='[8]Income Statement Forecast'!BC6 -> 64384.698
A24: EBITDA | B24: ='[8]Income Statement Forecast'!M12 -> 16382.398 | C24: ='[8]Income Statement Forecast'!N12 -> 17741.328 | D24: ='[8]Income Statement Forecast'!O12 -> 19210.801 | E24: ='[8]Income Statement Forecast'!P12 -> 20799.659 | F24: ='[8]Income Statement Forecast'!Q12 -> 22517.439 | G24: ='[8]Income Statement Forecast'!R12 -> 24374.429 | I24: EBITDA | J24: ='[8]Income Statement Forecast'!AF12 -> 8178.8149 | K24: ='[8]Income Statement Forecast'!AG12 -> 9752.3155 | L24: ='[8]Income Statement Forecast'!AH12 -> 11628.565 | M24: ='[8]Income Statement Forecast'!AI12 -> 13865.818 | N24: ='[8]Income Statement Forecast'!AJ12 -> 16533.543 | Q24: EBITDA | R24: ='[8]Income Statement Forecast'!AX12 -> 5659.2597 | S24: ='[8]Income Statement Forecast'!AY12 -> 6842.8364 | T24: ='[8]Income Statement Forecast'!AZ12 -> 8273.9492 | U24: ='[8]Income Statement Forecast'!BA12 -> 10004.369 | V24: ='[8]Income Statement Forecast'!BB12 -> 12096.696 | W24: ='[8]Income Statement Forecast'!BC12 -> 14626.62
A25: Net Profit | B25: ='[8]Income Statement Forecast'!M18 -> 14602.833 | C25: ='[8]Income Statement Forecast'!N18 -> 11942.975 | D25: ='[8]Income Statement Forecast'!O18 -> 13021.884 | E25: ='[8]Income Statement Forecast'!P18 -> 14169.15 | F25: ='[8]Income Statement Forecast'!Q18 -> 15393.528 | G25: ='[8]Income Statement Forecast'!R18 -> 16703.753 | I25: Net Profit | J25: ='[8]Income Statement Forecast'!AF18 -> 5173.7368 | K25: ='[8]Income Statement Forecast'!AG18 -> 6215.2795 | L25: ='[8]Income Statement Forecast'!AH18 -> 7442.2486 | M25: ='[8]Income Statement Forecast'!AI18 -> 8895.1786 | N25: ='[8]Income Statement Forecast'!AJ18 -> 10620.831 | Q25: Net Profit | R25: ='[8]Income Statement Forecast'!AX18 -> 4306.8035 | S25: ='[8]Income Statement Forecast'!AY18 -> 4009.3708 | T25: ='[8]Income Statement Forecast'!AZ18 -> 4835.3868 | U25: ='[8]Income Statement Forecast'!BA18 -> 5835.4005 | V25: ='[8]Income Statement Forecast'!BB18 -> 7045.6798 | W25: ='[8]Income Statement Forecast'!BC18 -> 8510.09
A26: EBITDA Margin | B26: =B24/B23 -> 0.24279781 | C26: =C24/C23 -> 0.24436062 | D26: =D24/D23 -> 0.24590253 | E26: =E24/E23 -> 0.24742351 | F26: =F24/F23 -> 0.24892351 | G26: =G24/G23 -> 0.2504025 | I26: EBITDA Margin | J26: =J24/J23 -> 0.11255306 | K26: =K24/K23 -> 0.11255306 | L26: =L24/L23 -> 0.11255306 | M26: =M24/M23 -> 0.11255306 | N26: =N24/N23 -> 0.11255306 | Q26: EBITDA Margin | R26: =R24/R23 -> 0.22717541 | S26: =S24/S23 -> 0.22717541 | T26: =T24/T23 -> 0.22717541 | U26: =U24/U23 -> 0.22717541 | V26: =V24/V23 -> 0.22717541 | W26: =W24/W23 -> 0.22717541
A27: Net Profit Margin | B27: =B25/B23 -> 0.2164235 | C27: =C25/C23 -> 0.16449686 | D27: =D25/D23 -> 0.16668302 | E27: =E25/E23 -> 0.16854992 | F27: =F25/F23 -> 0.17017081 | G27: =G25/G23 -> 0.17160039 | I27: Net Profit Margin | J27: =J25/J23 -> 0.071198567 | K27: =K25/K23 -> 0.07173155 | L27: =L25/L23 -> 0.072033641 | M27: =M25/M23 -> 0.072204867 | N27: =N25/N23 -> 0.072301925 | Q27: Net Profit Margin | R27: =R25/R23 -> 0.17288477 | S27: =S25/S23 -> 0.13310715 | T27: =T25/T23 -> 0.1327638 | U27: =U25/U23 -> 0.13250805 | V27: =V25/V23 -> 0.13231755 | W27: =W25/W23 -> 0.13217566

Sheet Tables-Pharma
A1: KPI | B1: 2020 | C1: 2021 | D1: 2022 | E1: 2023 | F1: 2024 | G1: 2025 | I1: KPI | J1: 2020 | K1: 2021 | L1: 2022 | M1: 2023 | N1: 2024 | O1: 2025
A2: Revenue | B2: ='[9]Income Statement'!B7 -> 5584.05 | C2: ='[9]Income Statement'!C7 -> 7031.96 | D2: ='[9]Income Statement'!D7 -> 9073.7 | E2: ='[9]Income Statement'!E7 -> 8112.17 | F2: ='[9]Income Statement'!F7 -> 8184 | G2: ='[9]Income Statement'!G7 -> 9712 | I2: Revenue | J2: ='[9]Income Statement'!Z9 -> 18137.6 | K2: ='[9]Income Statement'!AA9 -> 19338.9 | L2: ='[9]Income Statement'!AB9 -> 22029.6 | M2: ='[9]Income Statement'!AC9 -> 25725.2 | N2: ='[9]Income Statement'!AD9 -> 28905.4 | O2: ='[9]Income Statement'!AE9 -> 33741.2 | R2: Divis | S2: =(F15-B15)/B15 -> 0.40998179 | T2: =(F15/B15)^(1/5)-1 -> 0.071131276
A3: EBITDA | B3: ='[9]Income Statement'!B17+'[9]Income Statement'!B13+'[9]Income Statement'!B14 -> 2011.8 | C3: ='[9]Income Statement'!C17+'[9]Income Statement'!C13+'[9]Income Statement'!C14 -> 2922.5 | D3: ='[9]Income Statement'!D17+'[9]Income Statement'!D13+'[9]Income Statement'!D14 -> 3995.81 | E3: ='[9]Income Statement'!E17+'[9]Income Statement'!E13+'[9]Income Statement'!E14 -> 2712.48 | F3: ='[9]Income Statement'!F17+'[9]Income Statement'!F13+'[9]Income Statement'!F14 -> 2544 | G3: ='[9]Income Statement'!G17+'[9]Income Statement'!G13+'[9]Income Statement'!G14 -> 3320 | I3: EBITDA | J3: ='[9]Income Statement'!Z20+'[9]Income Statement'!Z17+'[9]Income Statement'!Z15 -> 3091 | K3: ='[9]Income Statement'!AA20+'[9]Income Statement'!AA17+'[9]Income Statement'!AA15 -> 4161.3 | L3: ='[9]Income Statement'!AB20+'[9]Income Statement'!AB17+'[9]Income Statement'!AB15 -> 4252.1 | M3: ='[9]Income Statement'!AC20+'[9]Income Statement'!AC17+'[9]Income Statement'!AC15 -> 7404.5 | N3: ='[9]Income Statement'!AD20+'[9]Income Statement'!AD17+'[9]Income Statement'!AD15 -> 8827.4 | O3: ='[9]Income Statement'!AE20+'[9]Income Statement'!AE17+'[9]Income Statement'!AE15 -> 9644.4 | R3: Sun | S3: =(F34-B34)/B34 -> 0.41423184 | T3: =(F34/B34)^(1/5)-1 -> 0.071776232
A4: Net Profit | B4: ='[9]Income Statement'!B21 -> 1376.54 | C4: ='[9]Income Statement'!C21 -> 1984.29 | D4: ='[9]Income Statement'!D21 -> 2960.45 | E4: ='[9]Income Statement'!E21 -> 1823.38 | F4: ='[9]Income Statement'!F21 -> 1600 | G4: ='[9]Income Statement'!G21 -> 2191 | I4: Net Profit | J4: ='[9]Income Statement'!Z26 -> 2026 | K4: ='[9]Income Statement'!AA26 -> 1951.6 | L4: ='[9]Income Statement'!AB26 -> 2182.5 | M4: ='[9]Income Statement'!AC26 -> 4507.3 | N4: ='[9]Income Statement'!AD26 -> 5577.9 | O4: ='[9]Income Statement'!AE26 -> 5725.2 | R4: Mankind | S4: =(F53-B53)/B53 -> 1.1786749 | T4: =(F53/B53)^(1/5)-1 -> 0.16852628
A5: EBITDA Margin | B5: =B3/B2 -> 0.36027614 | C5: =C3/C2 -> 0.41560248 | D5: =D3/D2 -> 0.44037273 | E5: =E3/E2 -> 0.33437169 | F5: =F3/F2 -> 0.31085044 | G5: =G3/G2 -> 0.34184514 | I5: EBITDA Margin | J5: =J3/J2 -> 0.17041946 | K5: =K3/K2 -> 0.2151777 | L5: =L3/L2 -> 0.19301758 | M5: =M3/M2 -> 0.28783061 | N5: =N3/N2 -> 0.3053893 | O5: =O3/O2 -> 0.28583453 | R5: Reddy's | S5: =(N15-J15)/J15 -> 0.42055822 | T5: =(N15/J15)^(1/5)-1 -> 0.072733411
A6: Net Profit Margin | B6: =B4/B2 -> 0.24651284 | C6: =C4/C2 -> 0.28218164 | D6: =D4/D2 -> 0.32626712 | E6: =E4/E2 -> 0.22477093 | F6: =F4/F2 -> 0.19550342 | G6: =G4/G2 -> 0.2255972 | I6: Net Profit Margin | J6: =J4/J2 -> 0.11170166 | K6: =K4/K2 -> 0.10091577 | L6: =L4/L2 -> 0.09907125 | M6: =M4/M2 -> 0.17520952 | N6: =N4/N2 -> 0.19297086 | O6: =O4/O2 -> 0.1696798 | R6: Torrent | S6: =(N34-J34)/J34 -> 0.25485485 | T6: =(N34/J34)^(1/5)-1 -> 0.046450521
A7: R&D expense ratio | B7: ='[9]Ratio Analysis'!B25 -> 0.0091797172 | C7: ='[9]Ratio Analysis'!C25 -> 0.07289575 | D7: ='[9]Ratio Analysis'!D25 -> 0.022813185 | E7: ='[9]Ratio Analysis'!E25 -> 0.028475735 | F7: ='[9]Ratio Analysis'!F25 -> 0.034934018 | G7: ='[9]Ratio Analysis'!G25 -> 0.024299835 | I7: R&D expense ratio | J7: ='[9]Ratio Analysis'!Z25 -> 0.084961627 | K7: ='[9]Ratio Analysis'!AA25 -> 0.085532269 | L7: ='[9]Ratio Analysis'!AB25 -> 0.079356865 | M7: ='[9]Ratio Analysis'!AC25 -> 0.075338579 | N7: ='[9]Ratio Analysis'!AD25 -> 0.079130543 | O7: ='[9]Ratio Analysis'!AE25 -> 0.081147084 | R7: Cipla | S7: =(N53-J53)/J53 -> -0.15851917 | T7: =(N53/J53)^(1/5)-1 -> -0.033929445
A8: Export Revenue ratio | B8: ='[9]Ratio Analysis'!B26 -> 0.81063207 | C8: ='[9]Ratio Analysis'!C26 -> 0.88 | D8: ='[9]Ratio Analysis'!D26 -> 0.9 | E8: ='[9]Ratio Analysis'!E26 -> 0.88 | F8: ='[9]Ratio Analysis'!F26 -> 0.87 | G8: ='[9]Ratio Analysis'!G26 -> 0.86 | I8: Export Revenue ratio | J8: ='[9]Ratio Analysis'!Z26 -> 0.834 | K8: ='[9]Ratio Analysis'!AA26 -> 0.8 | L8: ='[9]Ratio Analysis'!AB26 -> 0.69 | M8: ='[9]Ratio Analysis'!AC26 -> 0.79 | N8: ='[9]Ratio Analysis'!AD26 -> 0.834 | O8: ='[9]Ratio Analysis'!AE26 -> 0.835 | S8: =AVERAGE(S2:S7) -> 0.41996373 | T8: =AVERAGE(T2:T7) -> 0.066114713
A9: ROE | B9: ='[9]Ratio Analysis'!B10 -> 0.18831123 | C9: ='[9]Ratio Analysis'!C10 -> 0.21348825 | D9: ='[9]Ratio Analysis'!D10 -> 0.25242194 | E9: ='[9]Ratio Analysis'!E10 -> 0.14281876 | F9: ='[9]Ratio Analysis'!F10 -> 0.11789846 | G9: ='[9]Ratio Analysis'!G10 -> 0.14636916 | I9: ROE | J9: ='[9]Ratio Analysis'!Z10 -> 1.2933626 | K9: ='[9]Ratio Analysis'!AA10 -> 1.2397684 | L9: ='[9]Ratio Analysis'!AB10 -> 1.2487232 | M9: ='[9]Ratio Analysis'!AC10 -> 1.3389894 | N9: ='[9]Ratio Analysis'!AD10 -> 1.0230262 | O9: ='[9]Ratio Analysis'!AE10 -> 0.99451181
A10: Debt to Equity | B10: ='[9]Ratio Analysis'!B16 -> 0.0053146956 | C10: ='[9]Ratio Analysis'!C16 -> 0.00051965602 | D10: ='[9]Ratio Analysis'!D16 -> 0.00031462682 | E10: ='[9]Ratio Analysis'!E16 -> 0.00025534401 | F10: ='[9]Ratio Analysis'!F16 -> 0.00022105961 | G10: ='[9]Ratio Analysis'!G16 -> 0.00026721892 | I10: Debt to Equity | J10: ='[9]Ratio Analysis'!Z16 -> 0.24406714 | K10: ='[9]Ratio Analysis'!AA16 -> 0.11434213 | L10: ='[9]Ratio Analysis'!AB16 -> 0.16690002 | M10: ='[9]Ratio Analysis'!AC16 -> 0.17086881 | N10: ='[9]Ratio Analysis'!AD16 -> 0.070855218 | O10: ='[9]Ratio Analysis'!AE16 -> 0.13784139
A12: Forecasts | B12: 2026 | C12: 2027 | D12: 2028 | E12: 2029 | F12: 2030 | I12: Forecasts | J12: 2026 | K12: 2027 | L12: 2028 | M12: 2029 | N12: 2030
A13: Revenue | B13: ='[9]Income Statement Forecast'!B5 -> 10264.451 | C13: ='[9]Income Statement Forecast'!C5 -> 11256.3 | D13: ='[9]Income Statement Forecast'!D5 -> 12343.989 | E13: ='[9]Income Statement Forecast'!E5 -> 13536.782 | F13: ='[9]Income Statement Forecast'!F5 -> 14844.833 | I13: Revenue | J13: ='[9]Income Statement Forecast'!W7 -> 37419.188 | K13: ='[9]Income Statement Forecast'!X7 -> 41498.198 | L13: ='[9]Income Statement Forecast'!Y7 -> 46021.964 | M13: ='[9]Income Statement Forecast'!Z7 -> 51038.992 | N13: ='[9]Income Statement Forecast'!AA7 -> 56603.076
A14: EBITDA | B14: =[9]!Table31[[#This Row],[2026]] -> #REF! | C14: =[9]!Table31[[#This Row],[2027]] -> #REF! | D14: =[9]!Table31[[#This Row],[2028]] -> #REF! | E14: =[9]!Table31[[#This Row],[2029]] -> #REF! | F14: =[9]!Table31[[#This Row],[2030]] -> #REF! | I14: EBITDA | J14: =[9]!Table34[[#This Row],[2026]] -> 8145.0945 | K14: =[9]!Table34[[#This Row],[2027]] -> #REF! | L14: =[9]!Table34[[#This Row],[2028]] -> #REF! | M14: =[9]!Table34[[#This Row],[2029]] -> #REF! | N14: =[9]!Table34[[#This Row],[2030]] -> #REF!
A15: Net Profit | B15: ='[9]Income Statement Forecast'!B20 -> 2380.5325 | C15: ='[9]Income Statement Forecast'!C20 -> 2589.5902 | D15: ='[9]Income Statement Forecast'!D20 -> 2820.5626 | E15: ='[9]Income Statement Forecast'!E20 -> 3075.4626 | F15: ='[9]Income Statement Forecast'!F20 -> 3356.5075 | I15: Net Profit | J15: ='[9]Income Statement Forecast'!W20 -> 4063.0566 | K15: ='[9]Income Statement Forecast'!X20 -> 4411.8729 | L15: ='[9]Income Statement Forecast'!Y20 -> 4810.4398 | M15: ='[9]Income Statement Forecast'!Z20 -> 5262.3447 | N15: ='[9]Income Statement Forecast'!AA20 -> 5771.8085
A16: EBITDA Margin | B16: =B14/B13 -> #REF! | C16: =C14/C13 -> #REF! | D16: =D14/D13 -> #REF! | E16: =E14/E13 -> #REF! | F16: =F14/F13 -> #REF! | I16: EBITDA Margin | J16: =J14/J13 -> 0.2176716 | K16: =K14/K13 -> #REF! | L16: =L14/L13 -> #REF! | M16: =M14/M13 -> #REF! | N16: =N14/N13 -> #REF!
A17: Net Profit Margin | B17: =B15/B13 -> 0.23192009 | C17: =C15/C13 -> 0.23005697 | D17: =D15/D13 -> 0.22849684 | E17: =E15/E13 -> 0.22719304 | F17: =F15/F13 -> 0.22610611 | I17: Net Profit Margin | J17: =J15/J13 -> 0.10858217 | K17: =K15/K13 -> 0.10631481 | L17: =L15/L13 -> 0.10452487 | M17: =M15/M13 -> 0.1031044 | N17: =N15/N13 -> 0.10196987
A18: R&D expense ratio | B18: ='[9]Income Statement Forecast'!$B$11/'[9]Income Statement Forecast'!$B$7 -> 0.032099707 | C18: ='[9]Income Statement Forecast'!$B$11/'[9]Income Statement Forecast'!$B$7 -> 0.032099707 | D18: ='[9]Income Statement Forecast'!$B$11/'[9]Income Statement Forecast'!$B$7 -> 0.032099707 | E18: ='[9]Income Statement Forecast'!$B$11/'[9]Income Statement Forecast'!$B$7 -> 0.032099707 | F18: ='[9]Income Statement Forecast'!$B$11/'[9]Income Statement Forecast'!$B$7 -> 0.032099707 | I18: R&D expense ratio | J18: ='[9]Income Statement Forecast'!W11/'[9]Income Statement Forecast'!W7 -> 0.078302055 | K18: ='[9]Income Statement Forecast'!X11/'[9]Income Statement Forecast'!X7 -> 0.078324086 | L18: ='[9]Income Statement Forecast'!Y11/'[9]Income Statement Forecast'!Y7 -> 0.078345936 | M18: ='[9]Income Statement Forecast'!Z11/'[9]Income Statement Forecast'!Z7 -> 0.078367608 | N18: ='[9]Income Statement Forecast'!AA11/'[9]Income Statement Forecast'!AA7 -> 0.078389103
A20: KPI | B20: 2020 | C20: 2021 | D20: 2022 | E20: 2023 | F20: 2024 | G20: 2025 | I20: KPI | J20: 2020 | K20: 2021 | L20: 2022 | M20: 2023 | N20: 2024 | O20: 2025
A21: Revenue | B21: ='[9]Income Statement'!J7 -> 33473.48 | C21: ='[9]Income Statement'!K7 -> 34333.66 | D21: ='[9]Income Statement'!L7 -> 39576 | E21: ='[9]Income Statement'!M7 -> 44520.2 | F21: ='[9]Income Statement'!N7 -> 49851.04 | G21: ='[9]Income Statement'!O7 -> 54543.48 | I21: Revenue | J21: ='[9]Income Statement'!AH7 -> 8060.61 | K21: ='[9]Income Statement'!AI7 -> 8061.48 | L21: ='[9]Income Statement'!AJ7 -> 8704.6 | M21: ='[9]Income Statement'!AK7 -> 9665.29 | N21: ='[9]Income Statement'!AL7 -> 10785.75 | O21: ='[9]Income Statement'!AM7 -> 11539.36
A22: EBITDA | B22: ='[9]Income Statement'!J18+'[9]Income Statement'!J13+'[9]Income Statement'!J14 -> 7625.74 | C22: ='[9]Income Statement'!K18+'[9]Income Statement'!K13+'[9]Income Statement'!K14 -> 9326.89 | D22: ='[9]Income Statement'!L18+'[9]Income Statement'!L13+'[9]Income Statement'!L14 -> 11319.23 | E22: ='[9]Income Statement'!M18+'[9]Income Statement'!M13+'[9]Income Statement'!M14 -> 12281.31 | F22: ='[9]Income Statement'!N18+'[9]Income Statement'!N13+'[9]Income Statement'!N14 -> 14377.32 | G22: ='[9]Income Statement'!O18+'[9]Income Statement'!O13+'[9]Income Statement'!O14 -> 17236.73 | I22: EBITDA | J22: ='[9]Income Statement'!AH17+'[9]Income Statement'!AH13+'[9]Income Statement'!AH14 -> 2291.66 | K22: ='[9]Income Statement'!AI17+'[9]Income Statement'!AI13+'[9]Income Statement'!AI14 -> 2542.33 | L22: ='[9]Income Statement'!AJ17+'[9]Income Statement'!AJ13+'[9]Income Statement'!AJ14 -> 2627.83 | M22: ='[9]Income Statement'!AK17+'[9]Income Statement'!AK13+'[9]Income Statement'!AK14 -> 2887.19 | N22: ='[9]Income Statement'!AL17+'[9]Income Statement'!AL13+'[9]Income Statement'!AL14 -> 3425.56 | O22: ='[9]Income Statement'!AM17+'[9]Income Statement'!AM13+'[9]Income Statement'!AM14 -> 3744.26
A23: Net Profit | B23: ='[9]Income Statement'!J30 -> 3764.93 | C23: ='[9]Income Statement'!K30 -> 2903.82 | D23: ='[9]Income Statement'!L30 -> 3272.73 | E23: ='[9]Income Statement'!M30 -> 8473.58 | F23: ='[9]Income Statement'!N30 -> 9576.38 | G23: ='[9]Income Statement'!O30 -> 10929.04 | I23: Net Profit | J23: ='[9]Income Statement'!AH25 -> 1024.72 | K23: ='[9]Income Statement'!AI25 -> 1251.88 | L23: ='[9]Income Statement'!AJ25 -> 777.18 | M23: ='[9]Income Statement'!AK25 -> 1245.23 | N23: ='[9]Income Statement'!AL25 -> 1656.38 | O23: ='[9]Income Statement'!AM25 -> 1911.25
A24: EBITDA Margin | B24: =B22/B21 -> 0.22781438 | C24: =C22/C21 -> 0.27165441 | D24: =D22/D21 -> 0.28601248 | E24: =E22/E21 -> 0.27585927 | F24: =F22/F21 -> 0.28840562 | G24: =G22/G21 -> 0.31601816 | I24: EBITDA Margin | J24: =J22/J21 -> 0.28430355 | K24: =K22/K21 -> 0.31536765 | L24: =L22/L21 -> 0.30188981 | M24: =M22/M21 -> 0.29871737 | N24: =N22/N21 -> 0.31760054 | O24: =O22/O21 -> 0.32447727
A25: Net Profit Margin | B25: =B23/B21 -> 0.11247501 | C25: =C23/C21 -> 0.084576477 | D25: =D23/D21 -> 0.082694815 | E25: =E23/E21 -> 0.19033113 | F25: =F23/F21 -> 0.1920999 | G25: =G23/G21 -> 0.20037299 | I25: Net Profit Margin | J25: =J23/J21 -> 0.12712686 | K25: =K23/K21 -> 0.15529158 | L25: =L23/L21 -> 0.089283827 | M25: =M23/M21 -> 0.12883524 | N25: =N23/N21 -> 0.15357115 | O25: =O23/O21 -> 0.16562877
A26: R&D expense ratio | B26: ='[9]Ratio Analysis'!J25 -> 0.068785797 | C26: ='[9]Ratio Analysis'!K25 -> 0.062617851 | D26: ='[9]Ratio Analysis'!L25 -> 0.056094603 | E26: ='[9]Ratio Analysis'!M25 -> 0.053180354 | F26: ='[9]Ratio Analysis'!N25 -> 0.065013689 | G26: ='[9]Ratio Analysis'!O25 -> 0.059556156 | I26: R&D expense ratio | J26: ='[9]Ratio Analysis'!AH25 -> 0.047254488 | K26: ='[9]Ratio Analysis'!AI25 -> 0.060410743 | L26: ='[9]Ratio Analysis'!AJ25 -> 0.059279002 | M26: ='[9]Ratio Analysis'!AK25 -> 0.053386913 | N26: ='[9]Ratio Analysis'!AL25 -> 0.047 | O26: ='[9]Ratio Analysis'!AM25 -> 0.050349413
A27: Export Revenue ratio | B27: ='[9]Ratio Analysis'!J26 -> 0.12561452 | C27: ='[9]Ratio Analysis'!K26 -> 0.68 | D27: ='[9]Ratio Analysis'!L26 -> 0.48 | E27: ='[9]Ratio Analysis'!M26 -> 0.689 | F27: ='[9]Ratio Analysis'!N26 -> 0.727 | G27: ='[9]Ratio Analysis'!O26 -> 0.7 | I27: Export Revenue ratio | J27: ='[9]Ratio Analysis'!AH26 -> 0.54859372 | K27: ='[9]Ratio Analysis'!AI26 -> 0.53426914 | L27: ='[9]Ratio Analysis'!AJ26 -> 0.45 | M27: ='[9]Ratio Analysis'!AK26 -> 0.41 | N27: ='[9]Ratio Analysis'!AL26 -> 0.425 | O27: ='[9]Ratio Analysis'!AM26 -> 0.24
A28: ROE | B28: ='[9]Ratio Analysis'!J10 -> 0.07664028 | C28: ='[9]Ratio Analysis'!K10 -> 0.058686944 | D28: ='[9]Ratio Analysis'!L10 -> 0.133103 | E28: ='[9]Ratio Analysis'!M10 -> 0.35680695 | F28: ='[9]Ratio Analysis'!N10 -> 0.14266288 | G28: ='[9]Ratio Analysis'!O10 -> 0.1507746 | I28: ROE | J28: ='[9]Ratio Analysis'!AH10 -> 0.21245558 | K28: ='[9]Ratio Analysis'!AI10 -> 0.21446694 | L28: ='[9]Ratio Analysis'!AJ10 -> 0.13055376 | M28: ='[9]Ratio Analysis'!AK10 -> 0.20090609 | N28: ='[9]Ratio Analysis'!AL10 -> 0.2415904 | O28: ='[9]Ratio Analysis'!AM10 -> 0.2517887
A29: Debt to Equity | B29: ='[9]Ratio Analysis'!J16 -> 0.15426662 | C29: ='[9]Ratio Analysis'!K16 -> 0.06756349 | D29: ='[9]Ratio Analysis'!L16 -> 0.20636287 | E29: ='[9]Ratio Analysis'!M16 -> 0.32805718 | F29: ='[9]Ratio Analysis'!N16 -> 0.050431622 | G29: ='[9]Ratio Analysis'!O16 -> 0.034096125 | I29: Debt to Equity | J29: ='[9]Ratio Analysis'!AH16 -> 0.90521892 | K29: ='[9]Ratio Analysis'!AI16 -> 0.62452695 | L29: ='[9]Ratio Analysis'!AJ16 -> 0.68363584 | M29: ='[9]Ratio Analysis'!AK16 -> 0.8661664 | N29: ='[9]Ratio Analysis'!AL16 -> 0.58661785 | O29: ='[9]Ratio Analysis'!AM16 -> 0.42187469
A31: Forecasts | B31: 2026 | C31: 2027 | D31: 2028 | E31: 2029 | F31: 2030 | I31: Forecasts | J31: 2026 | K31: 2027 | L31: 2028 | M31: 2029 | N31: 2030
A32: Revenue | B32: ='[9]Income Statement Forecast'!I7 -> 61539.01 | C32: ='[9]Income Statement Forecast'!J7 -> 67045.589 | D32: ='[9]Income Statement Forecast'!K7 -> 73078.883 | E32: ='[9]Income Statement Forecast'!L7 -> 79695.933 | F32: ='[9]Income Statement Forecast'!M7 -> 86961.178 | I32: Revenue | J32: ='[9]Income Statement Forecast'!AD7 -> 12268.084 | K32: ='[9]Income Statement Forecast'!AE7 -> 13018.699 | L32: ='[9]Income Statement Forecast'!AF7 -> 13816.852 | M32: ='[9]Income Statement Forecast'!AG7 -> 14665.162 | N32: ='[9]Income Statement Forecast'!AH7 -> 15566.486
A33: EBITDA | B33: ='[9]Income Statement Forecast'!I14 -> 15133.714 | C33: ='[9]Income Statement Forecast'!J14 -> 16706.207 | D33: ='[9]Income Statement Forecast'!K14 -> 18471.897 | E33: ='[9]Income Statement Forecast'!L14 -> 20459.55 | F33: ='[9]Income Statement Forecast'!M14 -> 22702.933 | I33: EBITDA | J33: ='[9]Income Statement Forecast'!AD14 -> 3130.656 | K33: ='[9]Income Statement Forecast'!AE14 -> 3318.2259 | L33: ='[9]Income Statement Forecast'!AF14 -> 3518.6384 | M33: ='[9]Income Statement Forecast'!AG14 -> 3732.3759 | N33: ='[9]Income Statement Forecast'!AH14 -> 3960.0248
A34: Net Profit | B34: ='[9]Income Statement Forecast'!I20 -> 9131.1205 | C34: ='[9]Income Statement Forecast'!J20 -> 9814.8393 | D34: ='[9]Income Statement Forecast'!K20 -> 10664.489 | E34: ='[9]Income Statement Forecast'!L20 -> 11691.789 | F34: ='[9]Income Statement Forecast'!M20 -> 12913.521 | I34: Net Profit | J34: ='[9]Income Statement Forecast'!AD20 -> 1195.7329 | K34: ='[9]Income Statement Forecast'!AE20 -> 1263.8407 | L34: ='[9]Income Statement Forecast'!AF20 -> 1337.2696 | M34: ='[9]Income Statement Forecast'!AG20 -> 1416.0991 | N34: ='[9]Income Statement Forecast'!AH20 -> 1500.4712
A35: EBITDA Margin | B35: =B33/B32 -> 0.24592066 | C35: =C33/C32 -> 0.24917683 | D35: =D33/D32 -> 0.25276655 | E35: =E33/E32 -> 0.25672012 | F35: =F33/F32 -> 0.26106974 | I35: EBITDA Margin | J35: =J33/J32 -> 0.25518704 | K35: =K33/K32 -> 0.25488152 | L35: =L33/L32 -> 0.25466281 | M35: =M33/M32 -> 0.25450628 | N35: =N33/N32 -> 0.25439426
A36: Net Profit Margin | B36: =B34/B32 -> 0.14837939 | C36: =C34/C32 -> 0.14639053 | D36: =D34/D32 -> 0.1459312 | E36: =E34/E32 -> 0.14670497 | F36: =F34/F32 -> 0.14849754 | I36: Net Profit Margin | J36: =J34/J32 -> 0.097466961 | K36: =K34/K32 -> 0.097078879 | L36: =L34/L32 -> 0.096785403 | M36: =M34/M32 -> 0.096562114 | N36: =N34/N32 -> 0.096391127
A37: R&D expense ratio | B37: ='[9]Income Statement Forecast'!I11/'[9]Income Statement Forecast'!I7 -> 0.058528824 | C37: ='[9]Income Statement Forecast'!J11/'[9]Income Statement Forecast'!J7 -> 0.058276093 | D37: ='[9]Income Statement Forecast'!K11/'[9]Income Statement Forecast'!K7 -> 0.057997472 | E37: ='[9]Income Statement Forecast'!L11/'[9]Income Statement Forecast'!L7 -> 0.05769061 | F37: ='[9]Income Statement Forecast'!M11/'[9]Income Statement Forecast'!M7 -> 0.057353009 | I37: R&D expense ratio | J37: ='[9]Income Statement Forecast'!AD11/'[9]Income Statement Forecast'!AD7 -> 0.052870491 | K37: ='[9]Income Statement Forecast'!AE11/'[9]Income Statement Forecast'!AE7 -> 0.052892178 | L37: ='[9]Income Statement Forecast'!AF11/'[9]Income Statement Forecast'!AF7 -> 0.052907703 | M37: ='[9]Income Statement Forecast'!AG11/'[9]Income Statement Forecast'!AG7 -> 0.052918815 | N37: ='[9]Income Statement Forecast'!AH11/'[9]Income Statement Forecast'!AH7 -> 0.052926766
A39: KPI | B39: 2020 | C39: 2021 | D39: 2022 | E39: 2023 | F39: 2024 | G39: 2025 | I39: KPI | J39: 2020 | K39: 2021 | L39: 2022 | M39: 2023 | N39: 2024 | O39: 2025
A40: Revenue | B40: ='[9]Income Statement'!R7 -> 5975.6529 | C40: ='[9]Income Statement'!S7 -> 6385.3803 | D40: ='[9]Income Statement'!T7 -> 7977.5847 | E40: ='[9]Income Statement'!U7 -> 8877.9998 | F40: ='[9]Income Statement'!V7 -> 10540.66 | G40: ='[9]Income Statement'!W7 -> 12744.23 | I40: Revenue | J40: ='[9]Income Statement'!AP8 -> 17476.19 | K40: ='[9]Income Statement'!AQ8 -> 19425.58 | L40: ='[9]Income Statement'!AR8 -> 22044.25 | M40: ='[9]Income Statement'!AS8 -> 23228.57 | N40: ='[9]Income Statement'!AT8 -> 26520.66 | O40: ='[9]Income Statement'!AU8 -> 28409.49
A41: EBITDA | B41: ='[9]Income Statement'!R20+'[9]Income Statement'!R13+'[9]Income Statement'!R14 -> 1558.7653 | C41: ='[9]Income Statement'!S20+'[9]Income Statement'!S13+'[9]Income Statement'!S14 -> 1830.7295 | D41: ='[9]Income Statement'!T20+'[9]Income Statement'!T13+'[9]Income Statement'!T14 -> 2199.8302 | E41: ='[9]Income Statement'!U20+'[9]Income Statement'!U13+'[9]Income Statement'!U14 -> 2041.6276 | F41: ='[9]Income Statement'!V20+'[9]Income Statement'!V13+'[9]Income Statement'!V14 -> 2809.11 | G41: ='[9]Income Statement'!W20+'[9]Income Statement'!W13+'[9]Income Statement'!W14 -> 3566.96 | I41: EBITDA | J41: ='[9]Income Statement'!AP18+'[9]Income Statement'!AP14+'[9]Income Statement'!AP15 -> 3550.19 | K41: ='[9]Income Statement'!AQ18+'[9]Income Statement'!AQ14+'[9]Income Statement'!AQ15 -> 4518.42 | L41: ='[9]Income Statement'!AR18+'[9]Income Statement'!AR14+'[9]Income Statement'!AR15 -> 4833.69 | M41: ='[9]Income Statement'!AS18+'[9]Income Statement'!AS14+'[9]Income Statement'!AS15 -> 5502.42 | N41: ='[9]Income Statement'!AT18+'[9]Income Statement'!AT14+'[9]Income Statement'!AT15 -> 7037.62 | O41: ='[9]Income Statement'!AU18+'[9]Income Statement'!AU14+'[9]Income Statement'!AU15 -> 7989.77
A42: Net Profit | B42: ='[9]Income Statement'!R25 -> 1056.1402 | C42: ='[9]Income Statement'!S25 -> 1293.0279 | D42: ='[9]Income Statement'!T25 -> 1452.9571 | E42: ='[9]Income Statement'!U25 -> 1309.6758 | F42: ='[9]Income Statement'!V25 -> 1940.79 | G42: ='[9]Income Statement'!W25 -> 2006.59 | I42: Net Profit | J42: ='[9]Income Statement'!AP26 -> 1499.52 | K42: ='[9]Income Statement'!AQ26 -> 2388.51 | L42: ='[9]Income Statement'!AR26 -> 2728.77 | M42: ='[9]Income Statement'!AS26 -> 3015.31 | N42: ='[9]Income Statement'!AT26 -> 4348.54 | O42: ='[9]Income Statement'!AU26 -> 5269.2
A43: EBITDA Margin | B43: =B41/B40 -> 0.26085272 | C43: =C41/C40 -> 0.28670642 | D43: =D41/D40 -> 0.27575141 | E43: =E41/E40 -> 0.22996482 | F43: =F41/F40 -> 0.26650229 | G43: =G41/G40 -> 0.27988823 | I43: EBITDA Margin | J43: =J41/J40 -> 0.20314439 | K43: =K41/K40 -> 0.23260155 | L43: =L41/L40 -> 0.21927215 | M43: =M41/M40 -> 0.23688156 | N43: =N41/N40 -> 0.26536368 | O43: =O41/O40 -> 0.28123595
A44: Net Profit Margin | B44: =B42/B40 -> 0.17674055 | C44: =C42/C40 -> 0.20249818 | D44: =D42/D40 -> 0.18212995 | E44: =E42/E40 -> 0.14751924 | F44: =F42/F40 -> 0.18412414 | G44: =G42/G40 -> 0.15745086 | I44: Net Profit Margin | J44: =J42/J40 -> 0.085803599 | K44: =K42/K40 -> 0.12295695 | L44: =L42/L40 -> 0.12378602 | M44: =M42/M40 -> 0.1298104 | N44: =N42/N40 -> 0.16396802 | O44: =O42/O40 -> 0.18547323
A45: R&D expense ratio | B45: ='[9]Ratio Analysis'!R25 -> 0.024047581 | C45: ='[9]Ratio Analysis'!S25 -> 0.018636321 | D45: ='[9]Ratio Analysis'!T25 -> 0.020933654 | E45: ='[9]Ratio Analysis'!U25 -> 0.11263798 | F45: ='[9]Ratio Analysis'!V25 -> 0.02115617 | G45: ='[9]Ratio Analysis'!W25 -> 0.020111062 | I45: R&D expense ratio | J45: ='[9]Ratio Analysis'!AP25 -> 0.077934607 | K45: ='[9]Ratio Analysis'!AQ25 -> 0.0482 | L45: ='[9]Ratio Analysis'!AR25 -> 0.05 | M45: ='[9]Ratio Analysis'!AS25 -> 0.16626077 | N45: ='[9]Ratio Analysis'!AT25 -> 0.059236836 | O45: ='[9]Ratio Analysis'!AU25 -> 0.15195627
A46: Export Revenue ratio | B46: ='[9]Ratio Analysis'!R26 -> 0.1 | C46: ='[9]Ratio Analysis'!S26 -> 0.092 | D46: ='[9]Ratio Analysis'!T26 -> 0.024 | E46: ='[9]Ratio Analysis'!U26 -> 0.034 | F46: ='[9]Ratio Analysis'!V26 -> 0.079 | G46: ='[9]Ratio Analysis'!W26 -> 0.09 | I46: Export Revenue ratio | J46: ='[9]Ratio Analysis'!AP26 -> 0.515 | K46: ='[9]Ratio Analysis'!AQ26 -> 0.5 | L46: ='[9]Ratio Analysis'!AR26 -> 0.587 | M46: ='[9]Ratio Analysis'!AS26 -> 0.57 | N46: ='[9]Ratio Analysis'!AT26 -> 0.573 | O46: ='[9]Ratio Analysis'!AU26 -> 0.57
A47: ROE | B47: ='[9]Ratio Analysis'!R10 -> 0.28765346 | C47: ='[9]Ratio Analysis'!S10 -> 0.26589694 | D47: ='[9]Ratio Analysis'!T10 -> 0.23003251 | E47: ='[9]Ratio Analysis'!U10 -> 0.17179922 | F47: ='[9]Ratio Analysis'!V10 -> 0.20267675 | G47: ='[9]Ratio Analysis'!W10 -> 0.13773786 | I47: ROE | J47: ='[9]Ratio Analysis'!AP10 -> 0.096112295 | K47: ='[9]Ratio Analysis'!AQ10 -> 0.13148794 | L47: ='[9]Ratio Analysis'!AR10 -> 0.13195002 | M47: ='[9]Ratio Analysis'!AS10 -> 0.12971112 | N47: ='[9]Ratio Analysis'!AT10 -> 0.16381791 | O47: ='[9]Ratio Analysis'!AU10 -> 0.1697993
A48: Debt to Equity | B48: ='[9]Ratio Analysis'!R16 -> 0.028952481 | C48: ='[9]Ratio Analysis'!S16 -> 0.045556088 | D48: ='[9]Ratio Analysis'!T16 -> 0.13822534 | E48: ='[9]Ratio Analysis'!U16 -> 0.022348728 | F48: ='[9]Ratio Analysis'!V16 -> 0.021634769 | G48: ='[9]Ratio Analysis'!W16 -> 0.58424937 | I48: Debt to Equity | J48: ='[9]Ratio Analysis'!AP16 -> 0.17539895 | K48: ='[9]Ratio Analysis'!AQ16 -> 0.082724304 | L48: ='[9]Ratio Analysis'!AR16 -> 0.049995785 | M48: ='[9]Ratio Analysis'!AS16 -> 0.033867571 | N48: ='[9]Ratio Analysis'!AT16 -> 0.020871693 | O48: ='[9]Ratio Analysis'!AU16 -> 0.01400449
A50: Forecasts | B50: 2026 | C50: 2027 | D50: 2028 | E50: 2029 | F50: 2030 | I50: Forecasts | J50: 2026 | K50: 2027 | L50: 2028 | M50: 2029 | N50: 2030
A51: Revenue | B51: ='[9]Income Statement Forecast'!P7 -> 14497.024 | C51: ='[9]Income Statement Forecast'!Q7 -> 16508.55 | D51: ='[9]Income Statement Forecast'!R7 -> 18822.251 | E51: ='[9]Income Statement Forecast'!S7 -> 21490.312 | F51: ='[9]Income Statement Forecast'!T7 -> 24575.782 | I51: Revenue | J51: ='[9]Income Statement Forecast'!AK7 -> 30804.735 | K51: ='[9]Income Statement Forecast'!AL7 -> 33401.927 | L51: ='[9]Income Statement Forecast'!AM7 -> 36218.093 | M51: ='[9]Income Statement Forecast'!AN7 -> 39271.696 | N51: ='[9]Income Statement Forecast'!AO7 -> 42582.753
A52: EBITDA | B52: ='[9]Income Statement Forecast'!P14 -> 3902.4652 | C52: ='[9]Income Statement Forecast'!Q14 -> 4539.5585 | D52: ='[9]Income Statement Forecast'!R14 -> 5300.52 | E52: ='[9]Income Statement Forecast'!S14 -> 6214.4051 | F52: ='[9]Income Statement Forecast'!T14 -> 7318.1303 | I52: EBITDA | J52: ='[9]Income Statement Forecast'!AK14 -> 4543.2404 | K52: ='[9]Income Statement Forecast'!AL14 -> 4926.2877 | L52: ='[9]Income Statement Forecast'!AM14 -> 5341.6304 | M52: ='[9]Income Statement Forecast'!AN14 -> 5791.9913 | N52: ='[9]Income Statement Forecast'!AO14 -> 6280.3231
A53: Net Profit | B53: ='[9]Income Statement Forecast'!P20 -> 2053.9001 | C53: ='[9]Income Statement Forecast'!Q20 -> 2506.502 | D53: ='[9]Income Statement Forecast'!R20 -> 3045.8548 | E53: ='[9]Income Statement Forecast'!S20 -> 3693.0091 | F53: ='[9]Income Statement Forecast'!T20 -> 4474.7806 | I53: Net Profit | J53: ='[9]Income Statement Forecast'!AK20 -> 2460.162 | K53: ='[9]Income Statement Forecast'!AL20 -> 2422.2435 | L53: ='[9]Income Statement Forecast'!AM20 -> 2335.7129 | M53: ='[9]Income Statement Forecast'!AN20 -> 2188.401 | N53: ='[9]Income Statement Forecast'!AO20 -> 2070.1792
A54: EBITDA Margin | B54: =B52/B51 -> 0.26919079 | C54: =C52/C51 -> 0.27498226 | D54: =D52/D51 -> 0.28160925 | E54: =E52/E51 -> 0.2891724 | F54: =F52/F51 -> 0.29777812 | I54: EBITDA Margin | J54: =J52/J51 -> 0.14748513 | K54: =K52/K51 -> 0.14748513 | L54: =L52/L51 -> 0.14748513 | M54: =M52/M51 -> 0.14748513 | N54: =N52/N51 -> 0.14748513
A55: Net Profit Margin | B55: =B53/B51 -> 0.14167736 | C55: =C53/C51 -> 0.15183054 | D55: =D53/D51 -> 0.16182203 | E55: =E53/E51 -> 0.1718453 | F55: =F53/F51 -> 0.1820809 | I55: Net Profit Margin | J55: =J53/J51 -> 0.079863114 | K55: =K53/K51 -> 0.072518077 | L55: =L53/L51 -> 0.064490224 | M55: =M53/M51 -> 0.055724637 | N55: =N53/N51 -> 0.048615438
A56: R&D expense ratio | B56: ='[9]Income Statement Forecast'!P11/'[9]Income Statement Forecast'!P7 -> 0.034488472 | C56: ='[9]Income Statement Forecast'!Q11/'[9]Income Statement Forecast'!Q7 -> 0.034215159 | D56: ='[9]Income Statement Forecast'!R11/'[9]Income Statement Forecast'!R7 -> 0.033902417 | E56: ='[9]Income Statement Forecast'!S11/'[9]Income Statement Forecast'!S7 -> 0.033545496 | F56: ='[9]Income Statement Forecast'!T11/'[9]Income Statement Forecast'!T7 -> 0.033139373 | I56: R&D expense ratio | J56: ='[9]Income Statement Forecast'!AK11/'[9]Income Statement Forecast'!AK7 -> 0.092264747 | K56: ='[9]Income Statement Forecast'!AL11/'[9]Income Statement Forecast'!AL7 -> 0.092264747 | L56: ='[9]Income Statement Forecast'!AM11/'[9]Income Statement Forecast'!AM7 -> 0.092264747 | M56: ='[9]Income Statement Forecast'!AN11/'[9]Income Statement Forecast'!AN7 -> 0.092264747 | N56: ='[9]Income Statement Forecast'!AO11/'[9]Income Statement Forecast'!AO7 -> 0.092264747

Sheet Tables-IT
A1: KPI | B1: 2020 | C1: 2021 | D1: 2022 | E1: 2023 | F1: 2024 | I1: KPI | J1: 2020 | K1: 2021 | L1: 2022 | M1: 2023 | N1: 2024
A2: Revenue | B2: ='[10]Income Statement'!B5 -> 161541 | C2: ='[10]Income Statement'!C5 -> 167311 | D2: ='[10]Income Statement'!D5 -> 195772 | E2: ='[10]Income Statement'!E5 -> 228907 | F2: ='[10]Income Statement'!F5 -> 245315 | I2: Revenue | J2: ='[10]Income Statement'!$W$6 -> 63862.6 | K2: ='[10]Income Statement'!$W$6 -> 63862.6 | L2: ='[10]Income Statement'!$W$6 -> 63862.6 | M2: ='[10]Income Statement'!$W$6 -> 63862.6 | N2: ='[10]Income Statement'!$W$6 -> 63862.6
A3: EBITDA | B3: ='[10]Income Statement'!B13+'[10]Income Statement'!B9+'[10]Income Statement'!B10 -> 46701 | C3: ='[10]Income Statement'!C13+'[10]Income Statement'!C9+'[10]Income Statement'!C10 -> 49680 | D3: ='[10]Income Statement'!D13+'[10]Income Statement'!D9+'[10]Income Statement'!D10 -> 57075 | E3: ='[10]Income Statement'!E13+'[10]Income Statement'!E9+'[10]Income Statement'!E10 -> 62708 | F3: ='[10]Income Statement'!F13+'[10]Income Statement'!F9+'[10]Income Statement'!F10 -> 68718 | I3: EBITDA | J3: ='[10]Income Statement'!$W$23+'[10]Income Statement'!$W$11+'[10]Income Statement'!$W$12 -> 15070.2 | K3: ='[10]Income Statement'!$W$23+'[10]Income Statement'!$W$11+'[10]Income Statement'!$W$12 -> 15070.2 | L3: ='[10]Income Statement'!$W$23+'[10]Income Statement'!$W$11+'[10]Income Statement'!$W$12 -> 15070.2 | M3: ='[10]Income Statement'!$W$23+'[10]Income Statement'!$W$11+'[10]Income Statement'!$W$12 -> 15070.2 | N3: ='[10]Income Statement'!$W$23+'[10]Income Statement'!$W$11+'[10]Income Statement'!$W$12 -> 15070.2
A4: Net Profit | B4: ='[10]Income Statement'!B21 -> 32447 | C4: ='[10]Income Statement'!C21 -> 32562 | D4: ='[10]Income Statement'!D21 -> 38449 | E4: ='[10]Income Statement'!E21 -> 42303 | F4: ='[10]Income Statement'!F21 -> 46099 | I4: Net Profit | J4: ='[10]Income Statement'!$W$28 -> 9771.8 | K4: ='[10]Income Statement'!$W$28 -> 9771.8 | L4: ='[10]Income Statement'!$W$28 -> 9771.8 | M4: ='[10]Income Statement'!$W$28 -> 9771.8 | N4: ='[10]Income Statement'!$W$28 -> 9771.8
A5: EBITDA Margin | B5: =B3/B2 -> 0.28909689 | C5: =C3/C2 -> 0.29693206 | D5: =D3/D2 -> 0.29153812 | E5: =E3/E2 -> 0.27394531 | F5: =F3/F2 -> 0.28012148 | I5: EBITDA Margin | J5: =J3/J2 -> 0.23597849 | K5: =K3/K2 -> 0.23597849 | L5: =L3/L2 -> 0.23597849 | M5: =M3/M2 -> 0.23597849 | N5: =N3/N2 -> 0.23597849
A6: Net Profit Margin | B6: =B4/B2 -> 0.20085922 | C6: =C4/C2 -> 0.1946196 | D6: =D4/D2 -> 0.19639683 | E6: =E4/E2 -> 0.18480431 | F6: =F4/F2 -> 0.18791758 | I6: Net Profit Margin | J6: =J4/J2 -> 0.15301287 | K6: =K4/K2 -> 0.15301287 | L6: =L4/L2 -> 0.15301287 | M6: =M4/M2 -> 0.15301287 | N6: =N4/N2 -> 0.15301287
A7: ROE | B7: ='[10]Financial Ratios'!C8 -> 0.38285997 | C7: ='[10]Financial Ratios'!D8 -> 0.37894296 | D7: ='[10]Financial Ratios'!E8 -> 0.43456492 | E7: ='[10]Financial Ratios'!F8 -> 0.46730221 | F7: ='[10]Financial Ratios'!G8 -> 0.50512533 | I7: ROE | J7: ='[10]Financial Ratios'!AA8 -> 0.17603929 | K7: ='[10]Financial Ratios'!AB8 -> 0.19659913 | L7: ='[10]Financial Ratios'!AC8 -> 0.20320102 | M7: ='[10]Financial Ratios'!AD8 -> 0.15877073 | N7: ='[10]Financial Ratios'!AE8 -> 0.14583402
A8: Debt to Equity | B8: ='[10]Financial Ratios'!C18 -> 0.096449516 | C8: ='[10]Financial Ratios'!D18 -> 0.089486614 | D8: ='[10]Financial Ratios'!E18 -> 0.08701556 | E8: ='[10]Financial Ratios'!F18 -> 0.0842927 | F8: ='[10]Financial Ratios'!G18 -> 0.087834952 | I8: Debt to Equity | J8: ='[10]Financial Ratios'!AA18 -> 0.10603648 | K8: ='[10]Financial Ratios'!AB18 -> 0.15137291 | L8: ='[10]Financial Ratios'!AC18 -> 0.23175794 | M8: ='[10]Financial Ratios'!AD18 -> 0.19310328 | N8: ='[10]Financial Ratios'!AE18 -> 0.18946255
A10: Forecasts | B10: 2025 | C10: 2026 | D10: 2027 | E10: 2028 | F10: 2029 | G10: 2030 | I10: Forecasts | J10: 2025 | K10: 2026 | L10: 2027 | M10: 2028 | N10: 2029 | O10: 2030
A11: Revenue | B11: =[10]Valuation!D3 -> 266693.46 | C11: =[10]Valuation!E3 -> 289935 | D11: =[10]Valuation!F3 -> 315201.96 | E11: =[10]Valuation!G3 -> 342670.86 | F11: =[10]Valuation!H3 -> 372533.59 | G11: =[10]Valuation!I3 -> 404998.77 | I11: Revenue | J11: =[10]Valuation!AH3 -> 99473.373 | K11: =[10]Valuation!AI3 -> 107098.54 | L11: =[10]Valuation!AJ3 -> 115308.22 | M11: =[10]Valuation!AK3 -> 124147.21 | N11: =[10]Valuation!AL3 -> 133663.76 | O11: =[10]Valuation!AM3 -> 143909.81
A12: EBITDA | B12: =[10]Valuation!D4+[10]Valuation!D8 -> 73202.386 | C12: =[10]Valuation!E4+[10]Valuation!E8 -> 79082.312 | D12: =[10]Valuation!F4+[10]Valuation!F8 -> 85434.985 | E12: =[10]Valuation!G4+[10]Valuation!G8 -> 92298.446 | F12: =[10]Valuation!H4+[10]Valuation!H8 -> 99713.799 | G12: =[10]Valuation!I4+[10]Valuation!I8 -> 107725.46 | I12: EBITDA | J12: =[10]Valuation!AH4+[10]Valuation!AH8 -> 20411.136 | K12: =[10]Valuation!AI4+[10]Valuation!AI8 -> 21503.861 | L12: =[10]Valuation!AJ4+[10]Valuation!AJ8 -> 22666.426 | M12: =[10]Valuation!AK4+[10]Valuation!AK8 -> 23904.22 | N12: =[10]Valuation!AL4+[10]Valuation!AL8 -> 25223.111 | O12: =[10]Valuation!AM4+[10]Valuation!AM8 -> 26629.493
A13: Net Profit | B13: =[10]Valuation!D7 -> 50895.622 | C13: =[10]Valuation!E7 -> 55019.021 | D13: =[10]Valuation!F7 -> 59476.486 | E13: =[10]Valuation!G7 -> 64295.08 | F13: =[10]Valuation!H7 -> 69504.061 | G13: =[10]Valuation!I7 -> 75135.056 | I13: Net Profit | J13: =[10]Valuation!AH7 -> 12489.443 | K13: =[10]Valuation!AI7 -> 13018.213 | L13: =[10]Valuation!AJ7 -> 13569.37 | M13: =[10]Valuation!AK7 -> 14143.862 | N13: =[10]Valuation!AL7 -> 14742.676 | O13: =[10]Valuation!AM7 -> 15366.842
A14: EBITDA Margin | B14: =B12/B11 -> 0.27448136 | C14: =C12/C11 -> 0.27275877 | D14: =D12/D11 -> 0.2710484 | E14: =E12/E11 -> 0.26935015 | F14: =F12/F11 -> 0.26766391 | G14: =G12/G11 -> 0.26598959 | I14: EBITDA Margin | J14: =J12/J11 -> 0.20519196 | K14: =K12/K11 -> 0.20078575 | L14: =L12/L11 -> 0.19657251 | M14: =M12/M11 -> 0.19254737 | N14: =N12/N11 -> 0.18870568 | O14: =O12/O11 -> 0.18504293
A15: Net Profit Margin | B15: =B13/B11 -> 0.1908394 | C15: =C13/C11 -> 0.1897633 | D15: =D13/D11 -> 0.18869326 | E15: =E13/E11 -> 0.18762926 | F15: =F13/F11 -> 0.18657126 | G15: =G13/G11 -> 0.18551922 | I15: Net Profit Margin | J15: =J13/J11 -> 0.12555564 | K15: =K13/K11 -> 0.1215536 | L15: =L13/L11 -> 0.11767912 | M15: =M13/M11 -> 0.11392815 | N15: =N13/N11 -> 0.11029673 | O15: =O13/O11 -> 0.10678106
A17: KPI | B17: 2020 | C17: 2021 | D17: 2022 | E17: 2023 | F17: 2024 | I17: KPI | J17: 2020 | K17: 2021 | L17: 2022 | M17: 2023 | N17: 2024
A18: Revenue | B18: ='[10]Income Statement'!I5 -> 93594 | C18: ='[10]Income Statement'!J5 -> 102673 | D18: ='[10]Income Statement'!K5 -> 123936 | E18: ='[10]Income Statement'!L5 -> 149468 | F18: ='[10]Income Statement'!M5 -> 166590 | I18: Revenue | J18: ='[10]Income Statement'!AD5 -> 11207.8 | K18: ='[10]Income Statement'!AE5 -> 12644.2 | L18: ='[10]Income Statement'!AF5 -> 26874.5 | M18: ='[10]Income Statement'!AG5 -> 33739.9 | N18: ='[10]Income Statement'!AH5 -> 36218.9
A19: EBITDA | B19: ='[10]Income Statement'!I17+'[10]Income Statement'!I14+'[10]Income Statement'!I13 -> 25070 | C19: ='[10]Income Statement'!J17+'[10]Income Statement'!J14+'[10]Income Statement'!J13 -> 30090 | D19: ='[10]Income Statement'!K17+'[10]Income Statement'!K14+'[10]Income Statement'!K13 -> 33786 | E19: ='[10]Income Statement'!L17+'[10]Income Statement'!L14+'[10]Income Statement'!L13 -> 37831 | F19: ='[10]Income Statement'!M17+'[10]Income Statement'!M14+'[10]Income Statement'!M13 -> 42836 | I19: EBITDA | J19: ='[10]Income Statement'!AD13+'[10]Income Statement'!AD9+'[10]Income Statement'!AD10 -> 2358.5 | K19: ='[10]Income Statement'!AE13+'[10]Income Statement'!AE9+'[10]Income Statement'!AE10 -> 2999.5 | L19: ='[10]Income Statement'!AF13+'[10]Income Statement'!AF9+'[10]Income Statement'!AF10 -> 6014.4 | M19: ='[10]Income Statement'!AG13+'[10]Income Statement'!AG9+'[10]Income Statement'!AG10 -> 6664.6 | N19: ='[10]Income Statement'!AH13+'[10]Income Statement'!AH9+'[10]Income Statement'!AH10 -> 7089.3
A20: Net Profit | B20: ='[10]Income Statement'!I22 -> 16639 | C20: ='[10]Income Statement'!J22 -> 19423 | D20: ='[10]Income Statement'!K22 -> 22146 | E20: ='[10]Income Statement'!L22 -> 24108 | F20: ='[10]Income Statement'!M22 -> 26750 | I20: Net Profit | J20: ='[10]Income Statement'!AD18 -> 1520.5 | K20: ='[10]Income Statement'!AE18 -> 1938.2 | L20: ='[10]Income Statement'!AF18 -> 3950 | M20: ='[10]Income Statement'!AG18 -> 4410.3 | N20: ='[10]Income Statement'!AH18 -> 4584.6
A21: EBITDA Margin | B21: =B19/B18 -> 0.26785905 | C21: =C19/C18 -> 0.29306634 | D21: =D19/D18 -> 0.27260844 | E21: =E19/E18 -> 0.25310434 | F21: =F19/F18 -> 0.25713428 | I21: EBITDA Margin | J21: =J19/J18 -> 0.21043381 | K21: =K19/K18 -> 0.23722339 | L21: =L19/L18 -> 0.22379579 | M21: =M19/M18 -> 0.19752874 | N21: =N19/N18 -> 0.19573482
A22: Net Profit Margin | B22: =B20/B18 -> 0.17777849 | C22: =C20/C18 -> 0.1891734 | D22: =D20/D18 -> 0.178689 | E22: =E20/E18 -> 0.16129205 | F22: =F20/F18 -> 0.16057386 | I22: Net Profit Margin | J22: =J20/J18 -> 0.13566445 | K22: =K20/K18 -> 0.15328767 | L22: =L20/L18 -> 0.14697948 | M22: =M20/M18 -> 0.13071467 | N22: =N20/N18 -> 0.12658032
A23: ROE | B23: ='[10]Financial Ratios'!K8 -> 0.25270336 | C23: ='[10]Financial Ratios'!L8 -> 0.27236268 | D23: ='[10]Financial Ratios'!M8 -> 0.29040507 | E23: ='[10]Financial Ratios'!N8 -> 0.31819232 | F23: ='[10]Financial Ratios'!O8 -> 0.32571109 | I23: ROE | J23: ='[10]Financial Ratios'!AI8 -> 0.28130839 | K23: ='[10]Financial Ratios'!AJ8 -> 0.30493542 | L23: ='[10]Financial Ratios'!AK8 -> 0.36574074 | M23: ='[10]Financial Ratios'!AL8 -> 0.28552931 | N23: ='[10]Financial Ratios'!AM8 -> 0.25034948
A24: Debt to Equity | B24: ='[10]Financial Ratios'!K18 -> 0.070363283 | C24: ='[10]Financial Ratios'!L18 -> 0.069352192 | D24: ='[10]Financial Ratios'!M18 -> 0.11534805 | E24: ='[10]Financial Ratios'!N18 -> 0.14409921 | F24: ='[10]Financial Ratios'!O18 -> 0.11706854 | I24: Debt to Equity | J24: ='[10]Financial Ratios'!AI18 -> 0.0059203345 | K24: ='[10]Financial Ratios'!AJ18 -> 0.0056657224 | L24: ='[10]Financial Ratios'!AK18 -> 0.0036311735 | M24: ='[10]Financial Ratios'!AL18 -> 0.0075485566 | N24: ='[10]Financial Ratios'!AM18 -> 0.0020323173
A26: Forecasts | B26: 2025 | C26: 2026 | D26: 2027 | E26: 2028 | F26: 2029 | G26: 2030 | I26: Forecasts | J26: 2025 | K26: 2026 | L26: 2027 | M26: 2028 | N26: 2029 | O26: 2030
A27: Revenue | B27: =[10]Valuation!N3 -> 186951.57 | C27: =[10]Valuation!O3 -> 209801.84 | D27: =[10]Valuation!P3 -> 235445 | E27: =[10]Valuation!Q3 -> 264222.42 | F27: =[10]Valuation!R3 -> 296517.17 | G27: =[10]Valuation!S3 -> 332759.17 | I27: Revenue | J27: =[10]Valuation!AR3 -> 45795.018 | K27: =[10]Valuation!AS3 -> 57903.019 | L27: =[10]Valuation!AT3 -> 73212.323 | M27: =[10]Valuation!AU3 -> 92569.339 | N27: =[10]Valuation!AV3 -> 117044.27 | O27: =[10]Valuation!AW3 -> 147990.25
A28: EBITDA | B28: =[10]Valuation!N4+[10]Valuation!N8 -> 47680.921 | C28: =[10]Valuation!O4+[10]Valuation!O8 -> 53074.017 | D28: =[10]Valuation!P4+[10]Valuation!P8 -> 59077.329 | E28: =[10]Valuation!Q4+[10]Valuation!Q8 -> 65759.927 | F28: =[10]Valuation!R4+[10]Valuation!R8 -> 73198.698 | G28: =[10]Valuation!S4+[10]Valuation!S8 -> 81479.237 | I28: EBITDA | J28: =[10]Valuation!AR4+[10]Valuation!AR8 -> 8834.8032 | K28: =[10]Valuation!AS4+[10]Valuation!AS8 -> 11010.078 | L28: =[10]Valuation!AT4+[10]Valuation!AT8 -> 13720.943 | M28: =[10]Valuation!AU4+[10]Valuation!AU8 -> 17099.268 | N28: =[10]Valuation!AV4+[10]Valuation!AV8 -> 21309.393 | O28: =[10]Valuation!AW4+[10]Valuation!AW8 -> 26556.121
A29: Net Profit | B29: =[10]Valuation!N7 -> 31765.088 | C29: =[10]Valuation!O7 -> 35381.893 | D29: =[10]Valuation!P7 -> 39410.511 | E29: =[10]Valuation!Q7 -> 43897.832 | F29: =[10]Valuation!R7 -> 48896.083 | G29: =[10]Valuation!S7 -> 54463.44 | I29: Net Profit | J29: =[10]Valuation!AR7 -> 5861.0243 | K29: =[10]Valuation!AS7 -> 7304.5006 | L29: =[10]Valuation!AT7 -> 9103.4821 | M29: =[10]Valuation!AU7 -> 11345.524 | N29: =[10]Valuation!AV7 -> 14139.744 | O29: =[10]Valuation!AW7 -> 17622.137
A30: EBITDA Margin | B30: =B28/B27 -> 0.25504424 | C30: =C28/C27 -> 0.25297212 | D30: =D28/D27 -> 0.25091774 | E30: =E28/E27 -> 0.24888095 | F30: =F28/F27 -> 0.24686158 | G30: =G28/G27 -> 0.24485948 | I30: EBITDA Margin | J30: =J28/J27 -> 0.19292062 | K30: =K28/K27 -> 0.19014688 | L30: =L28/L27 -> 0.18741302 | M30: =M28/M27 -> 0.18471848 | N30: =N28/N27 -> 0.18206268 | O30: =O28/O27 -> 0.17944507
A31: Net Profit Margin | B31: =B29/B27 -> 0.16991079 | C31: =C29/C27 -> 0.16864434 | D31: =D29/D27 -> 0.16738733 | E31: =E29/E27 -> 0.16613969 | F31: =F29/F27 -> 0.16490135 | G31: =G29/G27 -> 0.16367224 | I31: Net Profit Margin | J31: =J29/J27 -> 0.12798388 | K31: =K29/K27 -> 0.1261506 | L31: =L29/L27 -> 0.12434358 | M31: =M29/M27 -> 0.12256244 | N31: =N29/N27 -> 0.12080681 | O31: =O29/O27 -> 0.11907633
A33: KPI | B33: 2020 | C33: 2021 | D33: 2022 | E33: 2023 | F33: 2024
A34: Revenue | B34: ='[10]Income Statement'!P5 -> 71265 | C34: ='[10]Income Statement'!Q5 -> 76306 | D34: ='[10]Income Statement'!R5 -> 86718 | E34: ='[10]Income Statement'!S5 -> 102814 | F34: ='[10]Income Statement'!T5 -> 111408 | L34: TCS | M34: =(G13-B13)/B13 -> 0.47625776 | N34: =(G13/B13)^(1/6)-1 -> 0.067071938
A35: EBITDA | B35: ='[10]Income Statement'!P15+'[10]Income Statement'!P10+'[10]Income Statement'!P11 -> 17905 | C35: ='[10]Income Statement'!Q15+'[10]Income Statement'!Q10+'[10]Income Statement'!Q11 -> 20975 | D35: ='[10]Income Statement'!R15+'[10]Income Statement'!R10+'[10]Income Statement'!R11 -> 29785 | E35: ='[10]Income Statement'!S15+'[10]Income Statement'!S10+'[10]Income Statement'!S11 -> 34791 | F35: ='[10]Income Statement'!T15+'[10]Income Statement'!T10+'[10]Income Statement'!T11 -> 36098 | L35: Infosys | M35: =(G29-B29)/B29 -> 0.71456915 | N35: =(O13/J13)^(1/6)-1 -> 0.03515868
A36: Net Profit | B36: ='[10]Income Statement'!P20 -> 11057 | C36: ='[10]Income Statement'!Q20 -> 11169 | D36: ='[10]Income Statement'!R20 -> 13523 | E36: ='[10]Income Statement'!S20 -> 14845 | F36: ='[10]Income Statement'!T20 -> 15710 | L36: HCL | M36: =(G45-B45)/B45 -> 1.4539178 | N36: =(G29/B29)^(1/6)-1 -> 0.094021443
A37: EBITDA Margin | B37: =B35/B34 -> 0.25124535 | C37: =C35/C34 -> 0.27488009 | D37: =D35/D34 -> 0.34346964 | E37: =E35/E34 -> 0.33838777 | F37: =F35/F34 -> 0.32401623 | L37: Wipro | M37: =(O13-J13)/J13 -> 0.23038653 | N37: =(O29/J29)^(1/6)-1 -> 0.20138123
A38: Net Profit Margin | B38: =B36/B34 -> 0.1551533 | C38: =C36/C34 -> 0.14637119 | D38: =D36/D34 -> 0.15594225 | E38: =E36/E34 -> 0.14438695 | F38: =F36/F34 -> 0.14101321 | L38: LTI Mindtree | M38: =(O29-J29)/J29 -> 2.0066651 | N38: =(G45/B45)^(1/6)-1 -> 0.16138622
A39: ROE | B39: ='[10]Financial Ratios'!S8 -> 0.21502888 | C39: ='[10]Financial Ratios'!T8 -> 0.20033542 | D39: ='[10]Financial Ratios'!U8 -> 0.22152873 | E39: ='[10]Financial Ratios'!V8 -> 0.23303821 | F39: ='[10]Financial Ratios'!W8 -> 0.23505824 | M39: =AVERAGE(M34:M38) -> 0.97635927 | N39: =AVERAGE(N34:N38) -> 0.1118039
A40: Debt to Equity | B40: ='[10]Financial Ratios'!S18 -> 0.091266214 | C40: ='[10]Financial Ratios'!T18 -> 0.063712926 | D40: ='[10]Financial Ratios'!U18 -> 0.064267974 | E40: ='[10]Financial Ratios'!V18 -> 0.034420013 | F40: ='[10]Financial Ratios'!W18 -> 0.03408475
A42: Forecasts | B42: 2025 | C42: 2026 | D42: 2027 | E42: 2028 | F42: 2029 | G42: 2030
A43: Revenue | B43: =[10]Valuation!X3 -> 121821.63 | C43: =[10]Valuation!Y3 -> 133208.65 | D43: =[10]Valuation!Z3 -> 145660.04 | E43: =[10]Valuation!AA3 -> 159275.31 | F43: =[10]Valuation!AB3 -> 174163.23 | G43: =[10]Valuation!AC3 -> 190442.77
A44: EBITDA | B44: =[10]Valuation!X4+[10]Valuation!X8 -> 46877.83 | C44: =[10]Valuation!Y4+[10]Valuation!Y8 -> 55419.295 | D44: =[10]Valuation!Z4+[10]Valuation!Z8 -> 65613.039 | E44: =[10]Valuation!AA4+[10]Valuation!AA8 -> 77782.886 | F44: =[10]Valuation!AB4+[10]Valuation!AB8 -> 92316.302 | G44: =[10]Valuation!AC4+[10]Valuation!AC8 -> 109676.9
A45: Net Profit | B45: =[10]Valuation!X7 -> 31901.55 | C45: =[10]Valuation!Y7 -> 38175.417 | D45: =[10]Valuation!Z7 -> 45683.124 | E45: =[10]Valuation!AA7 -> 54667.322 | F45: =[10]Valuation!AB7 -> 65418.382 | G45: =[10]Valuation!AC7 -> 78283.783
A46: EBITDA Margin | B46: =B44/B43 -> 0.38480713 | C46: =C44/C43 -> 0.41603377 | D46: =D44/D43 -> 0.45045325 | E46: =E44/E43 -> 0.48835496 | F46: =F44/F43 -> 0.53005622 | G46: =G44/G43 -> 0.5759048
A47: Net Profit Margin | B47: =B45/B43 -> 0.26187099 | C47: =C45/C43 -> 0.28658363 | D47: =D45/D43 -> 0.31362839 | E47: =E45/E43 -> 0.34322534 | F47: =F45/F43 -> 0.37561535 | G47: =G45/G43 -> 0.41106199

Sheet Tables-Auto
A1: KPI | B1: 2020 | C1: 2021 | D1: 2022 | E1: 2023 | F1: 2024 | G1: 2025 | I1: KPI | J1: 2020 | K1: 2021 | L1: 2022 | M1: 2023 | N1: 2024
A2: Revenue | B2: ='[11]Income Statement'!B6 -> 78994.4 | C2: ='[11]Income Statement'!C6 -> 73308.3 | D2: ='[11]Income Statement'!D6 -> 90074.5 | E2: ='[11]Income Statement'!E6 -> 119712 | F2: ='[11]Income Statement'!F6 -> 144787.3 | G2: ='[11]Income Statement'!G6 -> 156650.5 | I2: Revenue | J2: ='[11]Income Statement'!Z6 -> 18901.14 | K2: ='[11]Income Statement'!AA6 -> 19468.04 | L2: ='[11]Income Statement'!AB6 -> 24388.18 | M2: ='[11]Income Statement'!AC6 -> 32111.99 | N2: ='[11]Income Statement'!AD6 -> 39250.56
A3: EBITDA margin | B3: ='[11]Financial Ratios'!C9 -> 0.14228655 | C3: ='[11]Financial Ratios'!D9 -> 0.12017422 | D3: ='[11]Financial Ratios'!E9 -> 0.086186089 | E3: ='[11]Financial Ratios'!F9 -> 0.11342734 | F3: ='[11]Financial Ratios'!G9 -> 0.15011213 | G3: ='[11]Financial Ratios'!H9 -> 0.15529455 | I3: EBITDA margin | J3: ='[11]Financial Ratios'!AD9 -> 0.12334032 | K3: ='[11]Financial Ratios'!AE9 -> 0.11765981 | L3: ='[11]Financial Ratios'!AF9 -> 0.11445143 | M3: ='[11]Financial Ratios'!AG9 -> 0.13152503 | N3: ='[11]Financial Ratios'!AH9 -> 0.14431645
A4: Net Profit Margin | B4: ='[11]Financial Ratios'!C8 -> 0.075040973 | C4: ='[11]Financial Ratios'!D8 -> 0.062369977 | D4: ='[11]Financial Ratios'!E8 -> 0.043920625 | E4: ='[11]Financial Ratios'!F8 -> 0.069838472 | F4: ='[11]Financial Ratios'!G8 -> 0.097891769 | G4: ='[11]Financial Ratios'!H8 -> 0.096166356 | I4: Net Profit Margin | J4: ='[11]Financial Ratios'!AD8 -> 0.033137553 | K4: ='[11]Financial Ratios'!AE8 -> 0.03059912 | L4: ='[11]Financial Ratios'!AF8 -> 0.031074127 | M4: ='[11]Financial Ratios'!AG8 -> 0.041554714 | N4: ='[11]Financial Ratios'!AH8 -> 0.043080373
A5: ROE | B5: ='[11]Financial Ratios'!C11 -> 0.11485631 | C5: ='[11]Financial Ratios'!D11 -> 0.083600949 | D5: ='[11]Financial Ratios'!E11 -> 0.070111235 | E5: ='[11]Financial Ratios'!F11 -> 0.13288278 | F5: ='[11]Financial Ratios'!G11 -> 0.15728728 | G5: ='[11]Financial Ratios'!H11 -> 0.14838586 | I5: ROE | J5: ='[11]Financial Ratios'!AD11 -> 0.17335916 | K5: ='[11]Financial Ratios'!AE11 -> 0.14100334 | L5: ='[11]Financial Ratios'!AF11 -> 0.14977607 | M5: ='[11]Financial Ratios'!AG11 -> 0.22482297 | N5: ='[11]Financial Ratios'!AH11 -> 0.22451675 | R5: =(F12-B12)/B12 -> 0.92815311 | S5: =(F12/B12)^(1/5)-1 -> 0.1403241
A6: Debt to Equity | B6: ='[11]Financial Ratios'!C5 -> 0.0022596607 | C6: ='[11]Financial Ratios'!D5 -> 0.0093637025 | D6: ='[11]Financial Ratios'!E5 -> 0.0069017864 | E6: ='[11]Financial Ratios'!F5 -> 0.019675909 | F6: ='[11]Financial Ratios'!G5 -> 0.00039413208 | G6: ='[11]Financial Ratios'!H5 -> 0 | I6: Debt to Equity | J6: ='[11]Financial Ratios'!AD5 -> 2.4984263 | K6: ='[11]Financial Ratios'!AE5 -> 2.2184097 | L6: ='[11]Financial Ratios'!AF5 -> 3.0273599 | M6: ='[11]Financial Ratios'!AG5 -> 3.6593535 | N6: ='[11]Financial Ratios'!AH5 -> 3.3665623 | R6: =(F27-B27)/B27 -> 0.81893628 | S6: =(F27/B27)^(1/5)-1 -> 0.12710272
A7: EV/EBITDA | B7: ='[11]Financial Ratios'!C21 -> 47.051721 | C7: ='[11]Financial Ratios'!D21 -> 59.938098 | D7: ='[11]Financial Ratios'!E21 -> 66.570316 | E7: ='[11]Financial Ratios'!F21 -> 38.064323 | F7: ='[11]Financial Ratios'!G21 -> 24.981344 | G7: ='[11]Financial Ratios'!H21 -> 22.469413 | I7: EV/EBITDA | J7: ='[11]Financial Ratios'!AD21 -> 75.1334 | K7: ='[11]Financial Ratios'!AE21 -> 76.378919 | L7: ='[11]Financial Ratios'!AF21 -> 64.791211 | M7: ='[11]Financial Ratios'!AG21 -> 44.354836 | N7: ='[11]Financial Ratios'!AH21 -> 33.577093 | R7: =(F42-B42)/B42 -> 0.18700038 | S7: =(F42/B42)^(1/5)-1 -> 0.034880424
R8: =(O12-J12)/J12 -> 1.6424121 | S8: =(O12/J12)^(1/6)-1 -> 0.17579992
A9: Forecasts | B9: 2026 | C9: 2027 | D9: 2028 | E9: 2029 | F9: 2030 | I9: Forecasts | J9: 2025 | K9: 2026 | L9: 2027 | M9: 2028 | N9: 2029 | O9: 2030 | R9: =(N27-J27)/J27 -> 0.14075466 | S9: =(N27/J27)^(1/5)-1 -> 0.026687916
A10: Revenue | B10: ='[11]Valuation-FCFF'!D3 -> 161753.62 | C10: ='[11]Valuation-FCFF'!E3 -> 180299.74 | D10: ='[11]Valuation-FCFF'!F3 -> 200972.29 | E10: ='[11]Valuation-FCFF'!G3 -> 224015.09 | F10: ='[11]Valuation-FCFF'!H3 -> 249699.91 | I10: Revenue | J10: ='[11]Valuation-FCFF'!AE3 -> 45305.299 | K10: ='[11]Valuation-FCFF'!AF3 -> 52435.401 | L10: ='[11]Valuation-FCFF'!AG3 -> 60687.631 | M10: ='[11]Valuation-FCFF'!AH3 -> 70238.589 | N10: ='[11]Valuation-FCFF'!AI3 -> 81292.666 | O10: ='[11]Valuation-FCFF'!AJ3 -> 94086.423 | R10: =(O42-J42)/J42 -> 1.625 | S10: =(O42/J42)^(1/6)-1 -> 0.17450504
A11: EBITDA | B11: ='[11]Valuation-FCFF'!D4+'[11]Valuation-FCFF'!D7 -> 25934.297 | C11: ='[11]Valuation-FCFF'!E4+'[11]Valuation-FCFF'!E7 -> 29950.589 | D11: ='[11]Valuation-FCFF'!F4+'[11]Valuation-FCFF'!F7 -> 34694.436 | E11: ='[11]Valuation-FCFF'!G4+'[11]Valuation-FCFF'!G7 -> 40295.416 | F11: ='[11]Valuation-FCFF'!H4+'[11]Valuation-FCFF'!H7 -> 46906.224 | I11: EBITDA | J11: ='[11]Valuation-FCFF'!AE4+'[11]Valuation-FCFF'!AE7 -> 6767.8158 | K11: ='[11]Valuation-FCFF'!AF4+'[11]Valuation-FCFF'!AF7 -> 8115.2617 | L11: ='[11]Valuation-FCFF'!AG4+'[11]Valuation-FCFF'!AG7 -> 9739.342 | M11: ='[11]Valuation-FCFF'!AH4+'[11]Valuation-FCFF'!AH7 -> 11697.922 | N11: ='[11]Valuation-FCFF'!AI4+'[11]Valuation-FCFF'!AI7 -> 14061.103 | O11: ='[11]Valuation-FCFF'!AJ4+'[11]Valuation-FCFF'!AJ7 -> 16913.83 | R11: =AVERAGE(R5:R10) -> 0.8903761 | S11: =AVERAGE(S5:S10) -> 0.11321669
A12: Net Profit | B12: ='[11]Valuation-FCFF'!D6 -> 17124.484 | C12: ='[11]Valuation-FCFF'!E6 -> 20179.15 | D12: ='[11]Valuation-FCFF'!F6 -> 23778.708 | E12: ='[11]Valuation-FCFF'!G6 -> 28020.355 | F12: ='[11]Valuation-FCFF'!H6 -> 33018.627 | I12: Net Profit | J12: ='[11]Valuation-FCFF'!AE6 -> 4257.5554 | K12: ='[11]Valuation-FCFF'!AF6 -> 5170.8318 | L12: ='[11]Valuation-FCFF'!AG6 -> 6280.0128 | M12: ='[11]Valuation-FCFF'!AH6 -> 7627.121 | N12: ='[11]Valuation-FCFF'!AI6 -> 9263.1938 | O12: ='[11]Valuation-FCFF'!AJ6 -> 11250.216
A13: EBITDA Margin | B13: =B11/B10 -> 0.1603321 | C13: =C11/C10 -> 0.16611554 | D13: =D11/D10 -> 0.17263293 | E13: =E11/E10 -> 0.17987813 | F13: =F11/F10 -> 0.18785039 | I13: EBITDA Margin | J13: =J11/J10 -> 0.14938243 | K13: =K11/K10 -> 0.15476685 | L13: =L11/L10 -> 0.16048315 | M13: =M11/M10 -> 0.16654551 | N13: =N11/N10 -> 0.1729689 | O13: =O11/O10 -> 0.17976908
A14: Net Profit margin | B14: =B12/B10 -> 0.1058677 | C14: =C12/C10 -> 0.11192002 | D14: =D12/D10 -> 0.11831834 | E14: =E12/E10 -> 0.12508244 | F14: =F12/F10 -> 0.13223324 | I14: Net Profit margin | J14: =J12/J10 -> 0.093974776 | K14: =K12/K10 -> 0.098613374 | L14: =L12/L10 -> 0.10348093 | M14: =M12/M10 -> 0.10858876 | N14: =N12/N10 -> 0.1139487 | O14: =O12/O10 -> 0.11957321
A16: KPI | B16: 2020 | C16: 2021 | D16: 2022 | E16: 2023 | F16: 2024 | G16: 2025 | I16: KPI | J16: 2020 | K16: 2021 | L16: 2022 | M16: 2023 | N16: 2024 | O16: 2025
A17: Revenue | B17: ='[11]Income Statement'!J6 -> 76410.62 | C17: ='[11]Income Statement'!K6 -> 75310.89 | D17: ='[11]Income Statement'!L6 -> 91105.08 | E17: ='[11]Income Statement'!M6 -> 122475.04 | F17: ='[11]Income Statement'!N6 -> 141254.69 | G17: ='[11]Income Statement'!O6 -> 161391.87 | I17: Revenue | J17: ='[11]Income Statement'!AH6 -> 14532.89 | K17: ='[11]Income Statement'!AI6 -> 15367.34 | L17: ='[11]Income Statement'!AJ6 -> 12851.29 | M17: ='[11]Income Statement'!AK6 -> 15202.9 | N17: ='[11]Income Statement'!AL6 -> 16859.68 | O17: ='[11]Income Statement'!AM6 -> 17350.65
A18: EBITDA margin | B18: ='[11]Financial Ratios'!L9 -> 0.18864282 | C18: ='[11]Financial Ratios'!M9 -> 0.19803581 | D18: ='[11]Financial Ratios'!N9 -> 0.17319797 | E18: ='[11]Financial Ratios'!O9 -> 0.17722468 | F18: ='[11]Financial Ratios'!P9 -> 0.19575128 | G18: ='[11]Financial Ratios'!Q9 -> 0.20597979 | I18: EBITDA margin | J18: ='[11]Financial Ratios'!AM9 -> 0.1042042 | K18: ='[11]Financial Ratios'!AN9 -> 0.10792194 | L18: ='[11]Financial Ratios'!AO9 -> 0.11431502 | M18: ='[11]Financial Ratios'!AP9 -> 0.11362593 | N18: ='[11]Financial Ratios'!AQ9 -> 0.11371918 | O18: ='[11]Financial Ratios'!AR9 -> 0.11085083
A19: Net Profit Margin | B19: ='[11]Financial Ratios'!L8 -> -0.004258315 | C19: ='[11]Financial Ratios'!M8 -> 0.020361271 | D19: ='[11]Financial Ratios'!N8 -> 0.080436555 | E19: ='[11]Financial Ratios'!O8 -> 0.093795795 | F19: ='[11]Financial Ratios'!P8 -> 0.088732153 | G19: ='[11]Financial Ratios'!Q8 -> 0.088650029 | I19: Net Profit Margin | J19: ='[11]Financial Ratios'!AM8 -> 0.052690172 | K19: ='[11]Financial Ratios'!AN8 -> 0.052500868 | L19: ='[11]Financial Ratios'!AO8 -> 0.05428869 | M19: ='[11]Financial Ratios'!AP8 -> 0.054567003 | N19: ='[11]Financial Ratios'!AQ8 -> 0.052643662 | O19: ='[11]Financial Ratios'!AR8 -> 0.046438506
A20: ROE | B20: ='[11]Financial Ratios'!L11 -> -0.0067350593 | C20: ='[11]Financial Ratios'!M11 -> 0.030766749 | D20: ='[11]Financial Ratios'!N11 -> 0.13496798 | E20: ='[11]Financial Ratios'!O11 -> 0.1835965 | F20: ='[11]Financial Ratios'!P11 -> 0.16971709 | G20: ='[11]Financial Ratios'!Q11 -> 0.16893818 | I20: ROE | J20: ='[11]Financial Ratios'!AM11 -> 0.11704783 | K20: ='[11]Financial Ratios'!AN11 -> 0.10973575 | L20: ='[11]Financial Ratios'!AO11 -> 0.065353282 | M20: ='[11]Financial Ratios'!AP11 -> 0.073848653 | N20: ='[11]Financial Ratios'!AQ11 -> 0.068427702 | O20: ='[11]Financial Ratios'!AR11 -> 0.05744891
A21: Debt to Equity | B21: ='[11]Financial Ratios'!L5 -> 1.3116702 | C21: ='[11]Financial Ratios'!M5 -> 1.1757261 | D21: ='[11]Financial Ratios'!N5 -> 1.3139787 | E21: ='[11]Financial Ratios'!O5 -> 1.3232591 | F21: ='[11]Financial Ratios'!P5 -> 1.3314941 | G21: ='[11]Financial Ratios'!Q5 -> 1.3599963 | I21: Debt to Equity | J21: ='[11]Financial Ratios'!AM5 -> 0.010343462 | K21: ='[11]Financial Ratios'!AN5 -> 0.018070668 | L21: ='[11]Financial Ratios'!AO5 -> 0.019694182 | M21: ='[11]Financial Ratios'!AP5 -> 0.025076068 | N21: ='[11]Financial Ratios'!AQ5 -> 0.054021625 | O21: ='[11]Financial Ratios'!AR5 -> 0.11203937
A22: EV/EBITDA | B22: ='[11]Financial Ratios'!L21 -> 33.872929 | C22: ='[11]Financial Ratios'!M21 -> 32.048168 | D22: ='[11]Financial Ratios'!N21 -> 27.405625 | E22: ='[11]Financial Ratios'!O21 -> 20.798969 | F22: ='[11]Financial Ratios'!P21 -> 18.36505 | G22: ='[11]Financial Ratios'!Q21 -> 15.63478 | I22: EV/EBITDA | J22: ='[11]Financial Ratios'!AM21 -> 22.532833 | K22: ='[11]Financial Ratios'!AN21 -> 20.614627 | L22: ='[11]Financial Ratios'!AO21 -> 23.435274 | M22: ='[11]Financial Ratios'!AP21 -> 20.072639 | N22: ='[11]Financial Ratios'!AQ21 -> 18.151806 | O22: ='[11]Financial Ratios'!AR21 -> 18.642475
A24: Forecasts | B24: 2026 | C24: 2027 | D24: 2028 | E24: 2029 | F24: 2030 | I24: Forecasts | J24: 2026 | K24: 2027 | L24: 2028 | M24: 2029 | N24: 2030
A25: Revenue | B25: ='[11]Valuation-FCFF'!M3 -> 179730.04 | C25: ='[11]Valuation-FCFF'!N3 -> 203483.09 | D25: ='[11]Valuation-FCFF'!O3 -> 230375.32 | E25: ='[11]Valuation-FCFF'!P3 -> 260821.62 | F25: ='[11]Valuation-FCFF'!Q3 -> 295291.68 | I25: Revenue | J25: ='[11]Valuation-FCFF'!AO3 -> 17747.907 | K25: ='[11]Valuation-FCFF'!AP3 -> 18273.056 | L25: ='[11]Valuation-FCFF'!AQ3 -> 18813.744 | M25: ='[11]Valuation-FCFF'!AR3 -> 19370.43 | N25: ='[11]Valuation-FCFF'!AS3 -> 19943.589
A26: EBITDA | B26: ='[11]Valuation-FCFF'!M4+'[11]Valuation-FCFF'!M7 -> 37622.286 | C26: ='[11]Valuation-FCFF'!N4+'[11]Valuation-FCFF'!N7 -> 43303.153 | D26: ='[11]Valuation-FCFF'!O4+'[11]Valuation-FCFF'!O7 -> 49860.338 | E26: ='[11]Valuation-FCFF'!P4+'[11]Valuation-FCFF'!P7 -> 57431.064 | F26: ='[11]Valuation-FCFF'!Q4+'[11]Valuation-FCFF'!Q7 -> 66174.264 | I26: EBITDA | J26: ='[11]Valuation-FCFF'!AO4+'[11]Valuation-FCFF'!AO7 -> 1988.4855 | K26: ='[11]Valuation-FCFF'!AP4+'[11]Valuation-FCFF'!AP7 -> 2069.5209 | L26: ='[11]Valuation-FCFF'!AQ4+'[11]Valuation-FCFF'!AQ7 -> 2154.0939 | M26: ='[11]Valuation-FCFF'!AR4+'[11]Valuation-FCFF'!AR7 -> 2242.3698 | N26: ='[11]Valuation-FCFF'!AS4+'[11]Valuation-FCFF'!AS7 -> 2334.5225
A27: Net Profit | B27: ='[11]Valuation-FCFF'!M6 -> 23190.754 | C27: ='[11]Valuation-FCFF'!N6 -> 26932.04 | D27: ='[11]Valuation-FCFF'!O6 -> 31276.894 | E27: ='[11]Valuation-FCFF'!P6 -> 36322.689 | F27: ='[11]Valuation-FCFF'!Q6 -> 42182.504 | I27: Net Profit | J27: ='[11]Valuation-FCFF'!AO6 -> 1029.7164 | K27: ='[11]Valuation-FCFF'!AP6 -> 1064.1814 | L27: ='[11]Valuation-FCFF'!AQ6 -> 1099.8001 | M27: ='[11]Valuation-FCFF'!AR6 -> 1136.6109 | N27: ='[11]Valuation-FCFF'!AS6 -> 1174.6537
A28: EBITDA Margin | B28: =B26/B25 -> 0.20932663 | C28: =C26/C25 -> 0.21280959 | D28: =D26/D25 -> 0.2164309 | E28: =E26/E25 -> 0.22019288 | F28: =F26/F25 -> 0.22409796 | I28: EBITDA Margin | J28: =J26/J25 -> 0.11204056 | K28: =K26/K25 -> 0.11325532 | L28: =L26/L25 -> 0.11449576 | M28: =M26/M25 -> 0.11576252 | N28: =N26/N25 -> 0.11705629
A29: Net Profit margin | B29: =B27/B25 -> 0.12903104 | C29: =C27/C25 -> 0.13235518 | D29: =D27/D25 -> 0.13576495 | E29: =E27/E25 -> 0.13926257 | F29: =F27/F25 -> 0.1428503 | I29: Net Profit margin | J29: =J27/J25 -> 0.058019032 | K29: =K27/K25 -> 0.058237738 | L29: =L27/L25 -> 0.058457268 | M29: =M27/M25 -> 0.058677627 | N29: =N27/N25 -> 0.058898815
A31: KPI | B31: 2020 | C31: 2021 | D31: 2022 | E31: 2023 | F31: 2024 | G31: 2025 | I31: KPI | J31: 2020 | K31: 2021 | L31: 2022 | M31: 2023 | N31: 2024
A32: Revenue | B32: ='[11]Income Statement'!R8 -> 264041.12 | C32: ='[11]Income Statement'!S8 -> 252437.94 | D32: ='[11]Income Statement'!T8 -> 281507.25 | E32: ='[11]Income Statement'!U8 -> 350600.15 | F32: ='[11]Income Statement'!V8 -> 439708 | G32: ='[11]Income Statement'!W8 -> 445939 | I32: Revenue | J32: ='[11]Income Statement'!AP8 -> 60953.5 | K32: ='[11]Income Statement'!AQ8 -> 57599.2 | L32: ='[11]Income Statement'!AR8 -> 64031.7 | M32: ='[11]Income Statement'!AS8 -> 78957.7 | N32: ='[11]Income Statement'!AT8 -> 98879.3
A33: EBITDA margin | B33: ='[11]Financial Ratios'!U9 -> 0.081054436 | C33: ='[11]Financial Ratios'!V9 -> 0.14143545 | D33: ='[11]Financial Ratios'!W9 -> 0.10090903 | E33: ='[11]Financial Ratios'!X9 -> 0.10660708 | F33: ='[11]Financial Ratios'!Y9 -> 0.14726167 | G33: ='[11]Financial Ratios'!Z9 -> 0.14280907 | I33: EBITDA margin | J33: ='[11]Financial Ratios'!AV9 -> 0.080934598 | K33: ='[11]Financial Ratios'!AW9 -> 0.080563569 | L33: ='[11]Financial Ratios'!AX9 -> 0.078763265 | M33: ='[11]Financial Ratios'!AY9 -> 0.083018388 | N33: ='[11]Financial Ratios'!AZ9 -> 0.09689362
A34: Net Profit Margin | B34: ='[11]Financial Ratios'!U8 -> -0.040913421 | C34: ='[11]Financial Ratios'!V8 -> -0.04241077 | D34: ='[11]Financial Ratios'!W8 -> -0.041087618 | E34: ='[11]Financial Ratios'!X8 -> 0.007845055 | F34: ='[11]Financial Ratios'!Y8 -> 0.073761862 | G34: ='[11]Financial Ratios'!Z8 -> 0.064440583 | I34: Net Profit Margin | J34: ='[11]Financial Ratios'!AV8 -> 0.02147539 | K34: ='[11]Financial Ratios'!AW8 -> 0.027556878 | L34: ='[11]Financial Ratios'!AX8 -> 0.01877283 | M34: ='[11]Financial Ratios'!AY8 -> 0.02144067 | N34: ='[11]Financial Ratios'!AZ8 -> 0.03088176
A35: ROE | B35: ='[11]Financial Ratios'!U11 -> -0.16559139 | C35: ='[11]Financial Ratios'!V11 -> -0.18434075 | D35: ='[11]Financial Ratios'!W11 -> -0.2315836 | E35: ='[11]Financial Ratios'!X11 -> 0.051138689 | F35: ='[11]Financial Ratios'!Y11 -> 0.34166541 | G35: ='[11]Financial Ratios'!Z11 -> 0.22931228 | I35: ROE | J35: ='[11]Financial Ratios'!AV11 -> 0.087313418 | K35: ='[11]Financial Ratios'!AW11 -> 0.094633952 | L35: ='[11]Financial Ratios'!AX11 -> 0.052829024 | M35: ='[11]Financial Ratios'!AY11 -> 0.068491071 | N35: ='[11]Financial Ratios'!AZ11 -> 0.10701919
A36: Debt to Equity | B36: ='[11]Financial Ratios'!U5 -> 1.5601016 | C36: ='[11]Financial Ratios'!V5 -> 2.0199778 | D36: ='[11]Financial Ratios'!W5 -> 2.8603412 | E36: ='[11]Financial Ratios'!X5 -> 2.3890046 | F36: ='[11]Financial Ratios'!Y5 -> 1.0580811 | G36: ='[11]Financial Ratios'!Z5 -> 0.50914023 | I36: Debt to Equity | J36: ='[11]Financial Ratios'!AV5 -> 0.78707532 | K36: ='[11]Financial Ratios'!AW5 -> 0.53221498 | L36: ='[11]Financial Ratios'!AX5 -> 0.57058476 | M36: ='[11]Financial Ratios'!AY5 -> 0.49906674 | N36: ='[11]Financial Ratios'!AZ5 -> 0.61495632
A37: EV/EBITDA | B37: ='[11]Financial Ratios'!U21 -> 16.137977 | C37: ='[11]Financial Ratios'!V21 -> 9.7370373 | D37: ='[11]Financial Ratios'!W21 -> 12.910162 | E37: ='[11]Financial Ratios'!X21 -> 9.5975724 | F37: ='[11]Financial Ratios'!Y21 -> 4.968917 | G37: ='[11]Financial Ratios'!Z21 -> 4.5717547 | I37: EV/EBITDA | J37: ='[11]Financial Ratios'!AV21 -> 23.919403 | K37: ='[11]Financial Ratios'!AW21 -> 24.589098 | L37: ='[11]Financial Ratios'!AX21 -> 23.759113 | M37: ='[11]Financial Ratios'!AY21 -> 18.178802 | N37: ='[11]Financial Ratios'!AZ21 -> 12.718858
A39: Forecasts | B39: 2026 | C39: 2027 | D39: 2028 | E39: 2029 | F39: 2030 | I39: Forecasts | J39: 2025 | K39: 2026 | L39: 2027 | M39: 2028 | N39: 2029 | O39: 2030
A40: Revenue | B40: ='[11]Valuation-FCFF'!V3 -> 476706.33 | C40: ='[11]Valuation-FCFF'!W3 -> 520233.52 | D40: ='[11]Valuation-FCFF'!X3 -> 567735.09 | E40: ='[11]Valuation-FCFF'!Y3 -> 619573.95 | F40: ='[11]Valuation-FCFF'!Z3 -> 676146.12 | I40: Revenue | J40: ='[11]Valuation-FCFF'!AX3 -> 107712.14 | K40: ='[11]Valuation-FCFF'!AY3 -> 118653.87 | L40: ='[11]Valuation-FCFF'!AZ3 -> 130707.1 | M40: ='[11]Valuation-FCFF'!BA3 -> 143984.74 | N40: ='[11]Valuation-FCFF'!BB3 -> 158611.16 | O40: ='[11]Valuation-FCFF'!BC3 -> 174723.38
A41: EBITDA | B41: ='[11]Valuation-FCFF'!V4+'[11]Valuation-FCFF'!V7 -> 64479.759 | C41: ='[11]Valuation-FCFF'!W4+'[11]Valuation-FCFF'!W7 -> 66658.897 | D41: ='[11]Valuation-FCFF'!X4+'[11]Valuation-FCFF'!X7 -> 68922.804 | E41: ='[11]Valuation-FCFF'!Y4+'[11]Valuation-FCFF'!Y7 -> 71275.017 | F41: ='[11]Valuation-FCFF'!Z4+'[11]Valuation-FCFF'!Z7 -> 73719.223 | I41: EBITDA | J41: ='[11]Valuation-FCFF'!AX4+'[11]Valuation-FCFF'!AX7 -> 10945.501 | K41: ='[11]Valuation-FCFF'!AY4+'[11]Valuation-FCFF'!AY7 -> 12692.02 | L41: ='[11]Valuation-FCFF'!AZ4+'[11]Valuation-FCFF'!AZ7 -> 14769.703 | M41: ='[11]Valuation-FCFF'!BA4+'[11]Valuation-FCFF'!BA7 -> 17246.22 | N41: ='[11]Valuation-FCFF'!BB4+'[11]Valuation-FCFF'!BB7 -> 20203.453 | O41: ='[11]Valuation-FCFF'!BC4+'[11]Valuation-FCFF'!BC7 -> 23740.506
A42: Net Profit | B42: ='[11]Valuation-FCFF'!V6 -> 30629.466 | C42: ='[11]Valuation-FCFF'!W6 -> 31970.7 | D42: ='[11]Valuation-FCFF'!X6 -> 33370.665 | E42: ='[11]Valuation-FCFF'!Y6 -> 34831.933 | F42: ='[11]Valuation-FCFF'!Z6 -> 36357.188 | I42: Net Profit | J42: ='[11]Valuation-FCFF'!AX6 -> 5152.1366 | K42: ='[11]Valuation-FCFF'!AY6 -> 6249.0389 | L42: ='[11]Valuation-FCFF'!AZ6 -> 7579.4744 | M42: ='[11]Valuation-FCFF'!BA6 -> 9193.1628 | N42: ='[11]Valuation-FCFF'!BB6 -> 11150.409 | O42: ='[11]Valuation-FCFF'!BC6 -> 13524.358
A43: EBITDA Margin | B43: =B41/B40 -> 0.13526097 | C43: =C41/C40 -> 0.12813265 | D43: =D41/D40 -> 0.12139958 | E43: =E41/E40 -> 0.11503876 | F43: =F41/F40 -> 0.10902854 | I43: EBITDA Margin | J43: =J41/J40 -> 0.10161809 | K43: =K41/K40 -> 0.10696676 | L43: =L41/L40 -> 0.11299847 | M43: =M41/M40 -> 0.11977811 | N43: =N41/N40 -> 0.12737725 | O43: =O41/O40 -> 0.13587481
A44: Net Profit margin | B44: =B42/B40 -> 0.064252275 | C44: =C42/C40 -> 0.061454518 | D44: =D42/D40 -> 0.058778584 | E44: =E42/E40 -> 0.056219169 | F44: =F42/F40 -> 0.0537712 | I44: Net Profit margin | J44: =J42/J40 -> 0.047832461 | K44: =K42/K40 -> 0.052666118 | L44: =L42/L40 -> 0.057988236 | M44: =M42/M40 -> 0.063848175 | N44: =N42/N40 -> 0.070300283 | O44: =O42/O40 -> 0.077404402

Sheet Tables-P&E
A1: KPI | B1: 2020 | C1: 2021 | D1: 2022 | E1: 2023 | F1: 2024 | I1: KPI | J1: 2020 | K1: 2021 | L1: 2022 | M1: 2023 | N1: 2024 | Q1: KPI | R1: 2020 | S1: 2021 | T1: 2022 | U1: 2023 | V1: 2024
A2: Revenue | B2: ='[12]Income Statement'!B6 -> 27841.81 | C2: ='[12]Income Statement'!C6 -> 28149.68 | D2: ='[12]Income Statement'!D6 -> 31686.47 | E2: ='[12]Income Statement'!E6 -> 43040.52 | F2: ='[12]Income Statement'!F6 -> 60281.48 | I2: Revenue | J2: ='[12]Income Statement'!P5 -> 29698.98 | K2: ='[12]Income Statement'!Q5 -> 32907.34 | L2: ='[12]Income Statement'!R5 -> 43735.63 | M2: ='[12]Income Statement'!S5 -> 56547.1 | N2: ='[12]Income Statement'!T5 -> 63272.32 | Q2: Revenue | R2: ='[12]Income Statement'!AD6 -> 112372.58 | S2: ='[12]Income Statement'!AE6 -> 115546.83 | T2: ='[12]Income Statement'!AF6 -> 134994.31 | U2: ='[12]Income Statement'!AG6 -> 177977.17 | V2: ='[12]Income Statement'!AH6 -> 181165.86
A3: EBITDA | B3: ='[12]Income Statement'!B16+'[12]Income Statement'!B12+'[12]Income Statement'!B13 -> 7059.39 | C3: ='[12]Income Statement'!C16+'[12]Income Statement'!C12+'[12]Income Statement'!C13 -> 10596.72 | D3: ='[12]Income Statement'!D16+'[12]Income Statement'!D12+'[12]Income Statement'!D13 -> 13789.45 | E3: ='[12]Income Statement'!E16+'[12]Income Statement'!E12+'[12]Income Statement'!E13 -> 14311.88 | F3: ='[12]Income Statement'!F16+'[12]Income Statement'!F12+'[12]Income Statement'!F13 -> 28110.93 | I3: EBITDA margin | J3: ='[12]Income Statement'!P17+'[12]Income Statement'!P13+'[12]Income Statement'!P14 -> 8505.43 | K3: ='[12]Income Statement'!Q17+'[12]Income Statement'!Q13+'[12]Income Statement'!Q14 -> 7366.92 | L3: ='[12]Income Statement'!R17+'[12]Income Statement'!R13+'[12]Income Statement'!R14 -> 8431.13 | M3: ='[12]Income Statement'!S17+'[12]Income Statement'!S13+'[12]Income Statement'!S14 -> 9144.34 | N3: ='[12]Income Statement'!T17+'[12]Income Statement'!T13+'[12]Income Statement'!T14 -> 12607.25 | Q3: EBITDA margin | R3: ='[12]Income Statement'!AD15+'[12]Income Statement'!AD11+'[12]Income Statement'!AD12 -> 34445.05 | S3: ='[12]Income Statement'!AE15+'[12]Income Statement'!AE11+'[12]Income Statement'!AE12 -> 37989.51 | T3: ='[12]Income Statement'!AF15+'[12]Income Statement'!AF11+'[12]Income Statement'!AF12 -> 42604.59 | U3: ='[12]Income Statement'!AG15+'[12]Income Statement'!AG11+'[12]Income Statement'!AG12 -> 49499.15 | V3: ='[12]Income Statement'!AH15+'[12]Income Statement'!AH11+'[12]Income Statement'!AH12 -> 53757.69
A4: Net Profit | B4: ='[12]Income Statement'!B37 -> -2264.45 | C4: ='[12]Income Statement'!C37 -> 1239.58 | D4: ='[12]Income Statement'!D37 -> 4955.21 | E4: ='[12]Income Statement'!E37 -> 10760.38 | F4: ='[12]Income Statement'!F37 -> 20801.3 | I4: Net Profit margin | J4: ='[12]Income Statement'!P44 -> 1316.44 | K4: ='[12]Income Statement'!Q44 -> 1438.65 | L4: ='[12]Income Statement'!R44 -> 2155.61 | M4: ='[12]Income Statement'!S44 -> 3809.67 | N4: ='[12]Income Statement'!T44 -> 4280.1 | Q4: Net Profit margin | R4: ='[12]Income Statement'!AD27 -> 11908.91 | S4: ='[12]Income Statement'!AE27 -> 14969.4 | T4: ='[12]Income Statement'!AF27 -> 16960.29 | U4: ='[12]Income Statement'!AG27 -> 17121.35 | V4: ='[12]Income Statement'!AH27 -> 21332.25
A5: ROE | B5: ='[12]Financial Ratio'!B8 -> -0.35102038 | C5: ='[12]Financial Ratio'!C8 -> 0.096851883 | D5: ='[12]Financial Ratio'!D8 -> 0.26260303 | E5: ='[12]Financial Ratio'!E8 -> 0.35904278 | F5: ='[12]Financial Ratio'!F8 -> 0.48276221 | I5: ROE | J5: ='[12]Financial Ratio'!P8 -> 0.060116741 | K5: ='[12]Financial Ratio'!Q8 -> 0.05697723 | L5: ='[12]Financial Ratio'!R8 -> 0.082817424 | M5: ='[12]Financial Ratio'!S8 -> 0.11138044 | N5: ='[12]Financial Ratio'!T8 -> 0.11165642 | Q5: ROE | R5: ='[12]Financial Ratio'!AD8 -> 0.097489079 | S5: ='[12]Financial Ratio'!AE8 -> 0.11580649 | T5: ='[12]Financial Ratio'!AF8 -> 0.12189883 | U5: ='[12]Financial Ratio'!AG8 -> 0.11342126 | V5: ='[12]Financial Ratio'!AH8 -> 0.12919062
A6: Debt to Equity | B6: ='[12]Financial Ratio'!B13 -> 8.0809435 | C6: ='[12]Financial Ratio'!C13 -> 3.9970158 | D6: ='[12]Financial Ratio'!D13 -> 2.6089147 | E6: ='[12]Financial Ratio'!E13 -> 1.4142633 | F6: ='[12]Financial Ratio'!F13 -> 0.79862872 | I6: Debt to Equity | J6: ='[12]Financial Ratio'!P13 -> 2.0339473 | K6: ='[12]Financial Ratio'!Q13 -> 1.5240361 | L6: ='[12]Financial Ratio'!R13 -> 1.8283832 | M6: ='[12]Financial Ratio'!S13 -> 1.4318284 | N6: ='[12]Financial Ratio'!T13 -> 1.2907966 | Q6: Debt to Equity | R6: ='[12]Financial Ratio'!AD13 -> 1.5764735 | S6: ='[12]Financial Ratio'!AE13 -> 1.5258642 | T6: ='[12]Financial Ratio'!AF13 -> 1.5061382 | U6: ='[12]Financial Ratio'!AG13 -> 1.4561107 | V6: ='[12]Financial Ratio'!AH13 -> 1.4234318
A7: EV/EBITDA | B7: ='[12]Financial Ratio'!B23 -> -51.755557 | C7: ='[12]Financial Ratio'!C23 -> 37.182539 | D7: ='[12]Financial Ratio'!D23 -> 18.154503 | E7: ='[12]Financial Ratio'!E23 -> 15.088671 | F7: ='[12]Financial Ratio'!F23 -> 11.504789 | I7: EV/EBITDA | J7: ='[12]Financial Ratio'!P23 -> 41.366567 | K7: ='[12]Financial Ratio'!Q23 -> 110.67905 | L7: ='[12]Financial Ratio'!R23 -> 83.293856 | M7: ='[12]Financial Ratio'!S23 -> 79.172137 | N7: ='[12]Financial Ratio'!T23 -> 41.100327 | Q7: EV/EBITDA | R7: ='[12]Financial Ratio'!AD23 -> 17.836179 | S7: ='[12]Financial Ratio'!AE23 -> 18.363634 | T7: ='[12]Financial Ratio'!AF23 -> 17.424103 | U7: ='[12]Financial Ratio'!AG23 -> 16.522864 | V7: ='[12]Financial Ratio'!AH23 -> 21.947466
A9: Forecasts | B9: 2025 | C9: 2026 | D9: 2027 | E9: 2028 | F9: 2029 | G9: 2030 | I9: Forecasts | J9: 2025 | K9: 2026 | L9: 2027 | M9: 2028 | N9: 2029 | O9: 2030 | Q9: Forecasts | R9: 2025 | S9: 2026 | T9: 2027 | U9: 2028 | V9: 2029 | W9: 2030
A10: Revenue | B10: ='[12]FCFF Projections (5y )'!D3 -> 73778.504 | C10: ='[12]FCFF Projections (5y )'!E3 -> 90297.512 | D10: ='[12]FCFF Projections (5y )'!F3 -> 110515.13 | E10: ='[12]FCFF Projections (5y )'!G3 -> 135259.47 | F10: ='[12]FCFF Projections (5y )'!H3 -> 165544.06 | G10: ='[12]FCFF Projections (5y )'!I3 -> 202609.38 | I10: Revenue | J10: ='[12]FCFF Projections (5y )'!X3 -> 76700.99 | K10: ='[12]FCFF Projections (5y )'!Y3 -> 92979.708 | L10: ='[12]FCFF Projections (5y )'!Z3 -> 112713.36 | M10: ='[12]FCFF Projections (5y )'!AA3 -> 136635.2 | N10: ='[12]FCFF Projections (5y )'!AB3 -> 165634.12 | O10: ='[12]FCFF Projections (5y )'!AC3 -> 200787.66 | Q10: Revenue | R10: ='[12]FCFF Projections (5y )'!AR3 -> 205300.64 | S10: ='[12]FCFF Projections (5y )'!AS3 -> 232650.64 | T10: ='[12]FCFF Projections (5y )'!AT3 -> 263644.18 | U10: ='[12]FCFF Projections (5y )'!AU3 -> 298766.67 | V10: ='[12]FCFF Projections (5y )'!AV3 -> 338568.14 | W10: ='[12]FCFF Projections (5y )'!AW3 -> 383671.93
A11: EBITDA | B11: ='[12]FCFF Projections (5y )'!D4+'[12]FCFF Projections (5y )'!D7 -> 30798.324 | C11: ='[12]FCFF Projections (5y )'!E4+'[12]FCFF Projections (5y )'!E7 -> 36002.381 | D11: ='[12]FCFF Projections (5y )'!F4+'[12]FCFF Projections (5y )'!F7 -> 42112.198 | E11: ='[12]FCFF Projections (5y )'!G4+'[12]FCFF Projections (5y )'!G7 -> 49290.792 | F11: ='[12]FCFF Projections (5y )'!H4+'[12]FCFF Projections (5y )'!H7 -> 57731.576 | G11: ='[12]FCFF Projections (5y )'!I4+'[12]FCFF Projections (5y )'!I7 -> 67664.232 | I11: EBITDA | J11: ='[12]FCFF Projections (5y )'!X4+'[12]FCFF Projections (5y )'!X7 -> 11533.415 | K11: ='[12]FCFF Projections (5y )'!Y4+'[12]FCFF Projections (5y )'!Y7 -> 12942.474 | L11: ='[12]FCFF Projections (5y )'!Z4+'[12]FCFF Projections (5y )'!Z7 -> 14611.549 | M11: ='[12]FCFF Projections (5y )'!AA4+'[12]FCFF Projections (5y )'!AA7 -> 16594.357 | N11: ='[12]FCFF Projections (5y )'!AB4+'[12]FCFF Projections (5y )'!AB7 -> 18955.962 | O11: ='[12]FCFF Projections (5y )'!AC4+'[12]FCFF Projections (5y )'!AC7 -> 21775.178 | Q11: EBITDA | R11: ='[12]FCFF Projections (5y )'!AR4+'[12]FCFF Projections (5y )'!AR7 -> 50598.844 | S11: ='[12]FCFF Projections (5y )'!AS4+'[12]FCFF Projections (5y )'!AS7 -> 57745.891 | T11: ='[12]FCFF Projections (5y )'!AT4+'[12]FCFF Projections (5y )'!AT7 -> 65904.497 | U11: ='[12]FCFF Projections (5y )'!AU4+'[12]FCFF Projections (5y )'!AU7 -> 75218.114 | V11: ='[12]FCFF Projections (5y )'!AV4+'[12]FCFF Projections (5y )'!AV7 -> 85850.577 | W11: ='[12]FCFF Projections (5y )'!AW4+'[12]FCFF Projections (5y )'!AW7 -> 97989.008
A12: Net Profit | B12: ='[12]FCFF Projections (5y )'!D6 -> 17618.497 | C12: ='[12]FCFF Projections (5y )'!E6 -> 20320.366 | D12: ='[12]FCFF Projections (5y )'!F6 -> 23436.578 | E12: ='[12]FCFF Projections (5y )'!G6 -> 27030.673 | F12: ='[12]FCFF Projections (5y )'!H6 -> 31175.938 | G12: ='[12]FCFF Projections (5y )'!I6 -> 35956.897 | I12: Net Profit | J12: ='[12]FCFF Projections (5y )'!X6 -> 4440.9523 | K12: ='[12]FCFF Projections (5y )'!Y6 -> 4607.8496 | L12: ='[12]FCFF Projections (5y )'!Z6 -> 4781.0192 | M12: ='[12]FCFF Projections (5y )'!AA6 -> 4960.6968 | N12: ='[12]FCFF Projections (5y )'!AB6 -> 5147.1269 | O12: ='[12]FCFF Projections (5y )'!AC6 -> 5340.5633 | Q12: Net Profit | R12: ='[12]FCFF Projections (5y )'!AR6 -> 23306.429 | S12: ='[12]FCFF Projections (5y )'!AS6 -> 26715.667 | T12: ='[12]FCFF Projections (5y )'!AT6 -> 30623.605 | U12: ='[12]FCFF Projections (5y )'!AU6 -> 35103.192 | V12: ='[12]FCFF Projections (5y )'!AV6 -> 40238.048 | W12: ='[12]FCFF Projections (5y )'!AW6 -> 46124.024
A13: EBITDA Margin | B13: =B11/B10 -> 0.41744306 | C13: =C11/C10 -> 0.39870844 | D13: =D11/D10 -> 0.3810537 | E13: =E11/E10 -> 0.36441658 | F13: =F11/F10 -> 0.34873843 | G13: =G11/G10 -> 0.33396397 | I13: EBITDA Margin | J13: =J11/J10 -> 0.15036853 | K13: =K11/K10 -> 0.13919676 | L13: =L11/L10 -> 0.12963459 | M13: =M11/M10 -> 0.12145009 | N13: =N11/N10 -> 0.11444479 | O13: =O11/O10 -> 0.10844879 | Q13: EBITDA Margin | R13: =R11/R10 -> 0.24646218 | S13: =S11/S10 -> 0.24820861 | T13: =T11/T10 -> 0.24997516 | U13: =U11/U10 -> 0.25176207 | V13: =V11/V10 -> 0.25356957 | W13: =W11/W10 -> 0.2553979
A14: Net Profit margin | B14: =B12/B10 -> 0.23880258 | C14: =C12/C10 -> 0.22503794 | D14: =D12/D10 -> 0.2120667 | E14: =E12/E10 -> 0.19984312 | F14: =F12/F10 -> 0.18832411 | G14: =G12/G10 -> 0.17746906 | I14: Net Profit margin | J14: =J12/J10 -> 0.057899543 | K14: =K12/K10 -> 0.049557583 | L14: =L12/L10 -> 0.042417503 | M14: =M12/M10 -> 0.036306141 | N14: =N12/N10 -> 0.031075281 | O14: =O12/O10 -> 0.026598065 | Q14: Net Profit margin | R14: =R12/R10 -> 0.11352341 | S14: =S12/S10 -> 0.11483169 | T14: =T12/T10 -> 0.11615506 | U14: =U12/U10 -> 0.11749367 | V14: =V12/V10 -> 0.11884771 | W14: =W12/W10 -> 0.12021735
A16: KPI | B16: 2020 | C16: 2021 | D16: 2022 | E16: 2023 | F16: 2024 | I16: KPI | J16: 2020 | K16: 2021 | L16: 2022 | M16: 2023 | N16: 2024
A17: Revenue | B17: ='[12]Income Statement'!I6 -> 8202.41 | C17: ='[12]Income Statement'!J6 -> 8388.6 | D17: ='[12]Income Statement'!K6 -> 7686.73 | E17: ='[12]Income Statement'!L6 -> 7882.74 | F17: ='[12]Income Statement'!M6 -> 8260.23 | I17: Revenue | J17: ='[12]Income Statement'!W6 -> 8559.69 | K17: ='[12]Income Statement'!X6 -> 7159.65 | L17: ='[12]Income Statement'!Y6 -> 8735.84 | M17: ='[12]Income Statement'!Z6 -> 10867.05 | N17: ='[12]Income Statement'!AA6 -> 11942.34 | T17: =(G12-B12)/B12 -> 1.0408606 | U17: =(G12/B12)^(1/6)-1 -> 0.12625195
A18: EBITDA margin | B18: ='[12]Income Statement'!I14+'[12]Income Statement'!I10+'[12]Income Statement'!I11 -> 3662.77 | C18: ='[12]Income Statement'!J14+'[12]Income Statement'!J10+'[12]Income Statement'!J11 -> 4029.55 | D18: ='[12]Income Statement'!K14+'[12]Income Statement'!K10+'[12]Income Statement'!K11 -> 2904.96 | E18: ='[12]Income Statement'!L14+'[12]Income Statement'!L10+'[12]Income Statement'!L11 -> 2225.03 | F18: ='[12]Income Statement'!M14+'[12]Income Statement'!M10+'[12]Income Statement'!M11 -> 1524.94 | I18: EBITDA margin | J18: ='[12]Income Statement'!W17+'[12]Income Statement'!W12+'[12]Income Statement'!W13 -> 3271.88 | K18: ='[12]Income Statement'!X17+'[12]Income Statement'!X12+'[12]Income Statement'!X13 -> 3161.18 | L18: ='[12]Income Statement'!Y17+'[12]Income Statement'!Y12+'[12]Income Statement'!Y13 -> 4146.23 | M18: ='[12]Income Statement'!Z17+'[12]Income Statement'!Z12+'[12]Income Statement'!Z13 -> 3836.37 | N18: ='[12]Income Statement'!AA17+'[12]Income Statement'!AA12+'[12]Income Statement'!AA13 -> 5854.72 | T18: =(G27-B27)/B27 -> -0.38069371 | U18: =(G27/B27)^(1/6)-1 -> -0.076753688
A19: Net Profit margin | B19: ='[12]Income Statement'!I38 -> -4050.27 | C19: ='[12]Income Statement'!J38 -> 229.73 | D19: ='[12]Income Statement'!K38 -> -604.93 | E19: ='[12]Income Statement'!L38 -> -506.7 | F19: ='[12]Income Statement'!M38 -> -2065.22 | I19: Net Profit margin | J19: ='[12]Income Statement'!W24 -> 1081.18 | K19: ='[12]Income Statement'!X24 -> 822.68 | L19: ='[12]Income Statement'!Y24 -> 1743.48 | M19: ='[12]Income Statement'!Z24 -> 1480.12 | N19: ='[12]Income Statement'!AA24 -> 1725.65 | T19: =(O12-J12)/J12 -> 0.20257164 | U19: =(O12/J12)^(1/6)-1 -> 0.031221184
A20: ROE | B20: ='[12]Financial Ratio'!I8 -> -0.62905971 | C20: ='[12]Financial Ratio'!J8 -> 0.017435901 | D20: ='[12]Financial Ratio'!K8 -> -0.032395645 | E20: ='[12]Financial Ratio'!L8 -> -0.015757644 | F20: ='[12]Financial Ratio'!M8 -> -0.047940168 | I20: ROE | J20: ='[12]Financial Ratio'!W8 -> 0.0930305 | K20: ='[12]Financial Ratio'!X8 -> 0.056743283 | L20: ='[12]Financial Ratio'!Y8 -> 0.10010243 | M20: ='[12]Financial Ratio'!Z8 -> 0.079006394 | N20: ='[12]Financial Ratio'!AA8 -> 0.082118126 | T20: =(O27-J27)/J27 -> 1.2529202 | U20: =(O27/J27)^(1/6)-1 -> 0.14496173
A21: Debt to Equity | B21: ='[12]Financial Ratio'!I13 -> 1.8313805 | C21: ='[12]Financial Ratio'!J13 -> 1.493053 | D21: ='[12]Financial Ratio'!K13 -> 1.641145 | E21: ='[12]Financial Ratio'!L13 -> 1.5982406 | F21: ='[12]Financial Ratio'!M13 -> 1.6158133 | I21: Debt to Equity | J21: ='[12]Financial Ratio'!W13 -> 0.71251908 | K21: ='[12]Financial Ratio'!X13 -> 0.50091321 | L21: ='[12]Financial Ratio'!Y13 -> 0.51056786 | M21: ='[12]Financial Ratio'!Z13 -> 1.3247028 | N21: ='[12]Financial Ratio'!AA13 -> 1.4907325 | T21: =(W12-R12)/R12 -> 0.97902582 | U21: =(W12/R12)^(1/6)-1 -> 0.12049153
A22: EV/EBITDA | B22: ='[12]Financial Ratio'!I23 -> -113.61153 | C22: ='[12]Financial Ratio'!J23 -> 54.64044 | D22: ='[12]Financial Ratio'!K23 -> -54.722603 | E22: ='[12]Financial Ratio'!L23 -> -18.820515 | F22: ='[12]Financial Ratio'!M23 -> -15.07119 | I22: EV/EBITDA | J22: ='[12]Financial Ratio'!W23 -> 15.537889 | K22: ='[12]Financial Ratio'!X23 -> 20.232409 | L22: ='[12]Financial Ratio'!Y23 -> 27.274339 | M22: ='[12]Financial Ratio'!Z23 -> 34.796292 | N22: ='[12]Financial Ratio'!AA23 -> 55.601246 | T22: =AVERAGE(T17:T21) -> 0.61893692 | U22: =AVERAGE(U17:U21) -> 0.069234541
A24: Forecasts | B24: 2025 | C24: 2026 | D24: 2027 | E24: 2028 | F24: 2029 | G24: 2030 | I24: Forecasts | J24: 2025 | K24: 2026 | L24: 2027 | M24: 2028 | N24: 2029 | O24: 2030
A25: Revenue | B25: ='[12]FCFF Projections (5y )'!N3 -> 8285.8736 | C25: ='[12]FCFF Projections (5y )'!O3 -> 8311.5969 | D25: ='[12]FCFF Projections (5y )'!P3 -> 8337.4 | E25: ='[12]FCFF Projections (5y )'!Q3 -> 8363.2832 | F25: ='[12]FCFF Projections (5y )'!R3 -> 8389.2468 | G25: ='[12]FCFF Projections (5y )'!S3 -> 8415.291 | I25: Revenue | J25: ='[12]FCFF Projections (5y )'!AH3 -> 13117.004 | K25: ='[12]FCFF Projections (5y )'!AI3 -> 14407.209 | L25: ='[12]FCFF Projections (5y )'!AJ3 -> 15824.321 | M25: ='[12]FCFF Projections (5y )'!AK3 -> 17380.822 | N25: ='[12]FCFF Projections (5y )'!AL3 -> 19090.422 | O25: ='[12]FCFF Projections (5y )'!AM3 -> 20968.18
A26: EBITDA | B26: ='[12]FCFF Projections (5y )'!N4+'[12]FCFF Projections (5y )'!$N$7 -> -797.49359 | C26: ='[12]FCFF Projections (5y )'!O4+'[12]FCFF Projections (5y )'!$N$7 -> -629.09277 | D26: ='[12]FCFF Projections (5y )'!P4+'[12]FCFF Projections (5y )'!$N$7 -> -476.08084 | E26: ='[12]FCFF Projections (5y )'!Q4+'[12]FCFF Projections (5y )'!$N$7 -> -337.05152 | F26: ='[12]FCFF Projections (5y )'!R4+'[12]FCFF Projections (5y )'!$N$7 -> -210.72705 | G26: ='[12]FCFF Projections (5y )'!S4+'[12]FCFF Projections (5y )'!$N$7 -> -95.946423 | I26: EBITDA | J26: ='[12]FCFF Projections (5y )'!AH4+'[12]FCFF Projections (5y )'!AH7 -> 4316.6017 | K26: ='[12]FCFF Projections (5y )'!AI4+'[12]FCFF Projections (5y )'!AI7 -> 4940.1695 | L26: ='[12]FCFF Projections (5y )'!AJ4+'[12]FCFF Projections (5y )'!AJ7 -> 5660.1694 | M26: ='[12]FCFF Projections (5y )'!AK4+'[12]FCFF Projections (5y )'!AK7 -> 6492.2771 | N26: ='[12]FCFF Projections (5y )'!AL4+'[12]FCFF Projections (5y )'!AL7 -> 7454.8023 | O26: ='[12]FCFF Projections (5y )'!AM4+'[12]FCFF Projections (5y )'!AM7 -> 8569.1399
A27: Net Profit | B27: ='[12]FCFF Projections (5y )'!N6 -> -2037.284 | C27: ='[12]FCFF Projections (5y )'!O6 -> -1851.1119 | D27: ='[12]FCFF Projections (5y )'!P6 -> -1681.9527 | E27: ='[12]FCFF Projections (5y )'!Q6 -> -1528.2516 | F27: ='[12]FCFF Projections (5y )'!R6 -> -1388.5962 | G27: ='[12]FCFF Projections (5y )'!S6 -> -1261.7028 | I27: Net Profit | J27: ='[12]FCFF Projections (5y )'!AH6 -> 2030.0273 | K27: ='[12]FCFF Projections (5y )'!AI6 -> 2388.0919 | L27: ='[12]FCFF Projections (5y )'!AJ6 -> 2809.3135 | M27: ='[12]FCFF Projections (5y )'!AK6 -> 3304.8319 | N27: ='[12]FCFF Projections (5y )'!AL6 -> 3887.7518 | O27: ='[12]FCFF Projections (5y )'!AM6 -> 4573.4896
A28: EBITDA Margin | B28: =B26/B25 -> -0.096247375 | C28: =C26/C25 -> -0.075688557 | D28: =D26/D25 -> -0.057101835 | E28: =E26/E25 -> -0.04030134 | F28: =F26/F25 -> -0.025118709 | G28: =G26/G25 -> -0.011401439 | I28: EBITDA Margin | J28: =J26/J25 -> 0.32908442 | K28: =K26/K25 -> 0.34289565 | L28: =L26/L25 -> 0.35768797 | M28: =M26/M25 -> 0.37353108 | N28: =N26/N25 -> 0.39049961 | O28: =O26/O25 -> 0.40867351
A29: Net Profit margin | B29: =B27/B25 -> -0.24587437 | C29: =C27/C25 -> -0.22271435 | D29: =D27/D25 -> -0.20173587 | E29: =E27/E25 -> -0.18273345 | F29: =F27/F25 -> -0.16552096 | G29: =G27/G25 -> -0.14992979 | I29: Net Profit margin | J29: =J27/J25 -> 0.15476303 | K29: =K27/K25 -> 0.16575673 | L29: =L27/L25 -> 0.17753138 | M29: =M27/M25 -> 0.19014244 | N29: =N27/N25 -> 0.20364934 | O29: =O27/O25 -> 0.21811571

Sheet Tables-Telecom
A1: KPI | B1: 2020 | C1: 2021 | D1: 2022 | E1: 2023 | F1: 2024 | G1: 2025 | I1: KPI | J1: 2020 | K1: 2021 | L1: 2022 | M1: 2023 | N1: 2024 | O1: 2025
A2: Revenue | B2: ='[13]Income Statement'!B6 -> 56559.6 | C2: ='[13]Income Statement'!C6 -> 66713.8 | D2: ='[13]Income Statement'!D6 -> 71399 | E2: ='[13]Income Statement'!E6 -> 87353.9 | F2: ='[13]Income Statement'!F6 -> 151417.8 | G2: ='[13]Income Statement'!G6 -> 174558.9 | I2: Revenue | J2: ='[13]Income Statement'!Z6 -> 17137.67 | K2: ='[13]Income Statement'!AA6 -> 17256.86 | L2: ='[13]Income Statement'!AB6 -> 17056.82 | M2: ='[13]Income Statement'!AC6 -> 18201.41 | N2: ='[13]Income Statement'!AD6 -> 21048.8 | O2: ='[13]Income Statement'!AE6 -> 23238.89
A3: EBITDA Margin | B3: ='[13]Ratio Analysis'!C4 -> 0.39561984 | C3: ='[13]Ratio Analysis'!D4 -> 0.45525813 | D3: ='[13]Ratio Analysis'!E4 -> 0.49446771 | E3: ='[13]Ratio Analysis'!F4 -> 0.53154467 | F3: ='[13]Ratio Analysis'!G4 -> 0.52653783 | G3: ='[13]Ratio Analysis'!H4 -> 0.54269877 | I3: EBITDA Margin | J3: ='[13]Ratio Analysis'!AD4 -> 0.19597938 | K3: ='[13]Ratio Analysis'!AE4 -> 0.25597588 | L3: ='[13]Ratio Analysis'!AF4 -> 0.26727198 | M3: ='[13]Ratio Analysis'!AG4 -> 0.25719876 | N3: ='[13]Ratio Analysis'!AH4 -> 0.21765231 | O3: ='[13]Ratio Analysis'!AI4 -> 0.20221835
A4: Net Profit Margin | B4: ='[13]Ratio Analysis'!C6 -> -0.63805614 | C4: ='[13]Ratio Analysis'!D6 -> -0.37769697 | D4: ='[13]Ratio Analysis'!E6 -> -0.054114203 | E4: ='[13]Ratio Analysis'!F6 -> -0.0010257126 | F4: ='[13]Ratio Analysis'!G6 -> 0.056519115 | G4: ='[13]Ratio Analysis'!H6 -> 0.21472007 | I4: Net Profit Margin | J4: ='[13]Ratio Analysis'!AD6 -> -0.0049499144 | K4: ='[13]Ratio Analysis'!AE6 -> 0.072523043 | L4: ='[13]Ratio Analysis'!AF6 -> 0.087042602 | M4: ='[13]Ratio Analysis'!AG6 -> 0.098941236 | N4: ='[13]Ratio Analysis'!AH6 -> 0.05343345 | O4: ='[13]Ratio Analysis'!AI6 -> 0.069955579 | S4: =(F31-B31)/B31 -> 1.1197783 | T4: =(F31/B31)^(1/5)-1 -> 0.16213904
A5: ARPU | B5: ='[13]Ratio Analysis'!C14 -> 1336.1998 | C5: ='[13]Ratio Analysis'!D14 -> 1415.3411 | D5: ='[13]Ratio Analysis'!E14 -> 1457.9288 | E5: ='[13]Ratio Analysis'!F14 -> 1684.918 | F5: ='[13]Ratio Analysis'!G14 -> 2694.4107 | G5: ='[13]Ratio Analysis'!H14 -> 2956.0502 | I5: ROCE | J5: ='[13]Ratio Analysis'!AD12 -> 0.092753803 | K5: ='[13]Ratio Analysis'!AE12 -> 0.15504495 | L5: ='[13]Ratio Analysis'!AF12 -> 0.20950551 | M5: ='[13]Ratio Analysis'!AG12 -> 0.22472759 | N5: ='[13]Ratio Analysis'!AH12 -> 0.2005355 | O5: ='[13]Ratio Analysis'!AI12 -> 0.14965516 | S5: =(F36-B36)/B36 -> 1.6989336 | T5: =(F36/B36)^(1/5)-1 -> 0.21965905
A6: Subsriber base | B6: ='[13]Income Statement'!B32 -> 42.3287 | C6: ='[13]Income Statement'!C32 -> 47.1362 | D6: ='[13]Income Statement'!D32 -> 48.9729 | E6: ='[13]Income Statement'!E32 -> 51.8446 | F6: ='[13]Income Statement'!F32 -> 56.197 | G6: ='[13]Income Statement'!G32 -> 59.0514 | I6: Debt to Equity | J6: ='[13]Ratio Analysis'!AD9 -> -8.4632187 | K6: ='[13]Ratio Analysis'!AE9 -> 78.230732 | L6: ='[13]Ratio Analysis'!AF9 -> 9.5405615 | M6: ='[13]Ratio Analysis'!AG9 -> 5.5383185 | N6: ='[13]Ratio Analysis'!AH9 -> 6.2912193 | O6: ='[13]Ratio Analysis'!AI9 -> 4.086037 | S6: =(F41-B41)/B41 -> 1.1013102 | T6: =(F41/B41)^(1/5)-1 -> 0.16010696
A7: ROCE | B7: ='[13]Ratio Analysis'!C12 -> 0.052678682 | C7: ='[13]Ratio Analysis'!D12 -> 0.08993993 | D7: ='[13]Ratio Analysis'!E12 -> 0.11321485 | E7: ='[13]Ratio Analysis'!F12 -> 0.123967 | F7: ='[13]Ratio Analysis'!G12 -> 0.19547595 | G7: ='[13]Ratio Analysis'!H12 -> 0.22964169 | S7: =(N31-J31)/J31 -> 0.22511184 | T7: =(N31/J31)^(1/5)-1 -> 0.041442142
A8: Debt to Equity | B8: ='[13]Ratio Analysis'!C9 -> 0.81202652 | C8: ='[13]Ratio Analysis'!D9 -> 1.2203668 | D8: ='[13]Ratio Analysis'!E9 -> 1.4374674 | E8: ='[13]Ratio Analysis'!F9 -> 1.7804146 | F8: ='[13]Ratio Analysis'!G9 -> 1.4390952 | G8: ='[13]Ratio Analysis'!H9 -> 0.96640726 | S8: =(N36-J36)/J36 -> 0.15388835 | T8: =(N36/J36)^(1/5)-1 -> 0.029041188
S9: =(N41-J41)/J41 -> 0.64792761 | T9: =(N41/J41)^(1/5)-1 -> 0.1050645
A10: KPI | B10: 2020 | C10: 2021 | D10: 2022 | E10: 2023 | F10: 2024 | G10: 2025 | I10: KPI | J10: 2020 | K10: 2021 | L10: 2022 | M10: 2023 | N10: 2024 | O10: 2025 | S10: =AVERAGE(S4:S9) -> 0.82449165 | T10: =AVERAGE(T4:T9) -> 0.11957548
A11: Revenue | B11: ='[13]Income Statement'!J6 -> 6871.7 | C11: ='[13]Income Statement'!K6 -> 14151.2 | D11: ='[13]Income Statement'!L6 -> 28069.7 | E11: ='[13]Income Statement'!M6 -> 28743.1 | F11: ='[13]Income Statement'!N6 -> 28961.7 | G11: ='[13]Income Statement'!O6 -> 30468.6 | I11: Revenue | J11: ='[13]Income Statement'!AH8 -> 45996.8 | K11: ='[13]Income Statement'!AI8 -> 42126.4 | L11: ='[13]Income Statement'!AJ8 -> 38644.9 | M11: ='[13]Income Statement'!AK8 -> 42488.5 | N11: ='[13]Income Statement'!AL8 -> 42764.9 | O11: ='[13]Income Statement'!AM8 -> 44591.9
A12: EBITDA Margin | B12: ='[13]Ratio Analysis'!L4 -> 0.54517805 | C12: ='[13]Ratio Analysis'!M4 -> 0.52693764 | D12: ='[13]Ratio Analysis'!N4 -> 0.54490785 | E12: ='[13]Ratio Analysis'!O4 -> 0.35237327 | F12: ='[13]Ratio Analysis'!P4 -> 0.51982446 | G12: ='[13]Ratio Analysis'!Q4 -> 0.6954865 | I12: EBITDA Margin | J12: ='[13]Ratio Analysis'!AM4 -> 0.34680239 | K12: ='[13]Ratio Analysis'!AN4 -> 0.40639362 | L12: ='[13]Ratio Analysis'!AO4 -> 0.41830875 | M12: ='[13]Ratio Analysis'!AP4 -> 0.40312791 | N12: ='[13]Ratio Analysis'!AQ4 -> 0.40311564 | O12: ='[13]Ratio Analysis'!AR4 -> 0.4293874
A13: Net Profit Margin | B13: ='[13]Ratio Analysis'!L6 -> 0.48004133 | C13: ='[13]Ratio Analysis'!M6 -> 0.26704449 | D13: ='[13]Ratio Analysis'!N6 -> 0.22704553 | E13: ='[13]Ratio Analysis'!O6 -> 0.070973555 | F13: ='[13]Ratio Analysis'!P6 -> 0.20842009 | G13: ='[13]Ratio Analysis'!Q6 -> 0.32596509 | I13: Net Profit Margin | J13: ='[13]Ratio Analysis'!AM6 -> -1.6061574 | K13: ='[13]Ratio Analysis'!AN6 -> -1.050009 | L13: ='[13]Ratio Analysis'!AO6 -> -0.73089593 | M13: ='[13]Ratio Analysis'!AP6 -> -0.68962425 | N13: ='[13]Ratio Analysis'!AQ6 -> -0.73046821 | O13: ='[13]Ratio Analysis'!AR6 -> -0.61408911
A14: ARPU | B14: ='[13]Ratio Analysis'!L14 -> 720515.46 | C14: ='[13]Ratio Analysis'!M14 -> 789577.35 | D14: ='[13]Ratio Analysis'!N14 -> 1489527.6 | E14: ='[13]Ratio Analysis'!O14 -> 1490252.7 | F14: ='[13]Ratio Analysis'!P14 -> 1318022.5 | G14: ='[13]Ratio Analysis'!Q14 -> 1171869.2 | I14: ARPU | J14: ='[13]Ratio Analysis'!AM14 -> 1566.1151 | K14: ='[13]Ratio Analysis'!AN14 -> 1704.1424 | L14: ='[13]Ratio Analysis'!AO14 -> 1585.1066 | M14: ='[13]Ratio Analysis'!AP14 -> 1905.3139 | N14: ='[13]Ratio Analysis'!AQ14 -> 2011.5193 | O14: ='[13]Ratio Analysis'!AR14 -> 2249.8436
A15: Subsriber base | B15: ='[13]Income Statement'!J32 -> 0.0095372 | C15: ='[13]Income Statement'!K32 -> 0.0179225 | D15: ='[13]Income Statement'!L32 -> 0.0188447 | E15: ='[13]Income Statement'!M32 -> 0.0192874 | F15: ='[13]Income Statement'!N32 -> 0.0219736 | G15: ='[13]Income Statement'!O32 -> 0.026 | I15: Subsriber base | J15: ='[13]Income Statement'!AH38 -> 29.37 | K15: ='[13]Income Statement'!AI38 -> 24.72 | L15: ='[13]Income Statement'!AJ38 -> 24.38 | M15: ='[13]Income Statement'!AK38 -> 22.3 | N15: ='[13]Income Statement'!AL38 -> 21.26 | O15: ='[13]Income Statement'!AM38 -> 19.82
A16: ROCE | B16: ='[13]Ratio Analysis'!L12 -> 0.23410307 | C16: ='[13]Ratio Analysis'!M12 -> 0.2220462 | D16: ='[13]Ratio Analysis'!N12 -> 0.35392571 | E16: ='[13]Ratio Analysis'!O12 -> 0.22632623 | F16: ='[13]Ratio Analysis'!P12 -> 0.31244927 | G16: ='[13]Ratio Analysis'!Q12 -> 0.36797207 | I16: ROCE | J16: ='[13]Ratio Analysis'!AM12 -> 0.23752569 | K16: ='[13]Ratio Analysis'!AN12 -> 0.23061083 | L16: ='[13]Ratio Analysis'!AO12 -> 0.23204893 | M16: ='[13]Ratio Analysis'!AP12 -> 0.21324726 | N16: ='[13]Ratio Analysis'!AQ12 -> 0.23679125 | O16: ='[13]Ratio Analysis'!AR12 -> 0.22833861
A17: Debt to Equity | B17: ='[13]Ratio Analysis'!L9 -> 0.17858119 | C17: ='[13]Ratio Analysis'!M9 -> 0.43901871 | D17: ='[13]Ratio Analysis'!N9 -> 0.24770547 | E17: ='[13]Ratio Analysis'!O9 -> 0.22324546 | F17: ='[13]Ratio Analysis'!P9 -> 0.15946714 | G17: ='[13]Ratio Analysis'!Q9 -> 0.069615949 | I17: Debt to Equity | J17: ='[13]Ratio Analysis'!AM9 -> 16.106055 | K17: ='[13]Ratio Analysis'!AN9 -> -4.1178063 | L17: ='[13]Ratio Analysis'!AO9 -> -3.4497182 | M17: ='[13]Ratio Analysis'!AP9 -> -3.1975374 | N17: ='[13]Ratio Analysis'!AQ9 -> -2.3405634 | O17: ='[13]Ratio Analysis'!AR9 -> -3.3166672
A19: KPI | B19: 2020 | C19: 2021 | D19: 2022 | E19: 2023 | F19: 2024 | G19: 2025 | I19: KPI | J19: 2020 | K19: 2021 | L19: 2022 | M19: 2023 | N19: 2024 | O19: 2025
A20: Revenue | B20: ='[13]Income Statement'!R7 -> 1165.79 | C20: ='[13]Income Statement'!S7 -> 1411.29 | D20: ='[13]Income Statement'!T7 -> 1577.73 | E20: ='[13]Income Statement'!U7 -> 2002.2 | F20: ='[13]Income Statement'!V7 -> 2622.17 | G20: ='[13]Income Statement'!W7 -> 3551.04 | I20: Revenue | J20: ='[13]Income Statement'!AP6 -> 54403 | K20: ='[13]Income Statement'!AQ6 -> 70436 | L20: ='[13]Income Statement'!AR6 -> 77585 | M20: ='[13]Income Statement'!AS6 -> 91741 | N20: ='[13]Income Statement'!AT6 -> 100577 | O20: ='[13]Income Statement'!AU6 -> 115088
A21: EBITDA Margin | B21: ='[13]Ratio Analysis'!U4 -> 0.32315426 | C21: ='[13]Ratio Analysis'!V4 -> 0.25895457 | D21: ='[13]Ratio Analysis'!W4 -> 0.25287597 | E21: ='[13]Ratio Analysis'!X4 -> 0.21185696 | F21: ='[13]Ratio Analysis'!Y4 -> 0.19947601 | G21: ='[13]Ratio Analysis'!Z4 -> 0.17255227 | I21: EBITDA Margin | J21: ='[13]Ratio Analysis'!AV4 -> 0.39802952 | K21: ='[13]Ratio Analysis'!AW4 -> 0.4466608 | L21: ='[13]Ratio Analysis'!AX4 -> 0.49055874 | M21: ='[13]Ratio Analysis'!AY4 -> 0.5152004 | N21: ='[13]Ratio Analysis'!AZ4 -> 0.52574644 | O21: ='[13]Ratio Analysis'!BA4 -> 0.53205373
A22: Net Profit Margin | B22: ='[13]Ratio Analysis'!U6 -> 0.12100807 | C22: ='[13]Ratio Analysis'!V6 -> 0.10093602 | D22: ='[13]Ratio Analysis'!W6 -> 0.068921805 | E22: ='[13]Ratio Analysis'!X6 -> 0.094431126 | F22: ='[13]Ratio Analysis'!Y6 -> 0.093895514 | G22: ='[13]Ratio Analysis'!Z6 -> 0.084428787 | I22: Net Profit Margin | J22: ='[13]Ratio Analysis'!AV6 -> 0.10223701 | K22: ='[13]Ratio Analysis'!AW6 -> 0.17058039 | L22: ='[13]Ratio Analysis'!AX6 -> 0.19145453 | M22: ='[13]Ratio Analysis'!AY6 -> 0.19946371 | N22: ='[13]Ratio Analysis'!AZ6 -> 0.20348589 | O22: ='[13]Ratio Analysis'!BA6 -> 0.21544383
A23: ARPU | B23: ='[13]Ratio Analysis'!U14 -> 38859.667 | C23: ='[13]Ratio Analysis'!V14 -> 35282.25 | D23: ='[13]Ratio Analysis'!W14 -> 33426.483 | E23: ='[13]Ratio Analysis'!X14 -> 38802.326 | F23: ='[13]Ratio Analysis'!Y14 -> 46164.965 | G23: ='[13]Ratio Analysis'!Z14 -> 61757.217 | I23: ARPU | J23: ='[13]Ratio Analysis'!AV14 -> 1403.9484 | K23: ='[13]Ratio Analysis'!AW14 -> 1665.5474 | L23: ='[13]Ratio Analysis'!AX14 -> 1895.646 | M23: ='[13]Ratio Analysis'!AY14 -> 2091.8688 | N23: ='[13]Ratio Analysis'!AZ14 -> 2087.5259 | O23: ='[13]Ratio Analysis'!BA14 -> 2414.8726
A24: Subsriber base | B24: ='[13]Income Statement'!R32 -> 0.03 | C24: ='[13]Income Statement'!S32 -> 0.04 | D24: ='[13]Income Statement'!T32 -> 0.0472 | E24: ='[13]Income Statement'!U32 -> 0.0516 | F24: ='[13]Income Statement'!V32 -> 0.0568 | G24: ='[13]Income Statement'!W32 -> 0.0575 | I24: Subsriber base | J24: ='[13]Income Statement'!AP29 -> 38.75 | K24: ='[13]Income Statement'!AQ29 -> 42.29 | L24: ='[13]Income Statement'!AR29 -> 40.928 | M24: ='[13]Income Statement'!AS29 -> 43.856 | N24: ='[13]Income Statement'!AT29 -> 48.18 | O24: ='[13]Income Statement'!AU29 -> 47.658
A25: ROCE | B25: ='[13]Ratio Analysis'!U12 -> 0.15898656 | C25: ='[13]Ratio Analysis'!V12 -> 0.12655967 | D25: ='[13]Ratio Analysis'!W12 -> 0.14117879 | E25: ='[13]Ratio Analysis'!X12 -> 0.14389883 | F25: ='[13]Ratio Analysis'!Y12 -> 0.18434037 | G25: ='[13]Ratio Analysis'!Z12 -> 0.19201876 | I25: ROCE | J25: ='[13]Ratio Analysis'!AV12 -> 0.070137984 | K25: ='[13]Ratio Analysis'!AW12 -> 0.090641134 | L25: ='[13]Ratio Analysis'!AX12 -> 0.08897412 | M25: ='[13]Ratio Analysis'!AY12 -> 0.074880775 | N25: ='[13]Ratio Analysis'!AZ12 -> 0.074534397 | O25: ='[13]Ratio Analysis'!BA12 -> 0.083920162
A26: Debt to Equity | B26: ='[13]Ratio Analysis'!U9 -> 0.031066288 | C26: ='[13]Ratio Analysis'!V9 -> 0.021361532 | D26: ='[13]Ratio Analysis'!W9 -> 0.020639152 | E26: ='[13]Ratio Analysis'!X9 -> 0.025344476 | F26: ='[13]Ratio Analysis'!Y9 -> 0.024966616 | G26: ='[13]Ratio Analysis'!Z9 -> 0.022274232 | I26: Debt to Equity | J26: ='[13]Ratio Analysis'!AV9 -> 0.13595311 | K26: ='[13]Ratio Analysis'!AW9 -> 0.060877834 | L26: ='[13]Ratio Analysis'!AX9 -> 0.26492132 | M26: ='[13]Ratio Analysis'!AY9 -> 0.22809546 | N26: ='[13]Ratio Analysis'!AZ9 -> 0.27648719 | O26: ='[13]Ratio Analysis'!BA9 -> 0.31766376
A28: Forecasts | B28: 2026 | C28: 2027 | D28: 2028 | E28: 2029 | F28: 2030 | I28: Forecasts | J28: 2026 | K28: 2027 | L28: 2028 | M28: 2029 | N28: 2030
A29: Revenue | B29: =[13]DCF!D4 -> 210627.27 | C29: =[13]DCF!E4 -> 254148.31 | D29: =[13]DCF!F4 -> 306661.91 | E29: =[13]DCF!G4 -> 370026.17 | F29: =[13]DCF!H4 -> 446483.13 | I29: Revenue | J29: =[13]DCF!AE4 -> 24448.899 | K29: =[13]DCF!AF4 -> 25721.912 | L29: =[13]DCF!AG4 -> 27061.208 | M29: =[13]DCF!AH4 -> 28470.239 | N29: =[13]DCF!AI4 -> 29952.636
A30: EBITDA | B30: =[13]DCF!D5 -> 107026.26 | C30: =[13]DCF!E5 -> 129140.64 | D30: =[13]DCF!F5 -> 155824.43 | E30: =[13]DCF!G5 -> 188021.78 | F30: =[13]DCF!H5 -> 226871.94 | I30: EBITDA | J30: =[13]DCF!AE5 -> 5642.6674 | K30: =[13]DCF!AF5 -> 5936.4715 | L30: =[13]DCF!AG5 -> 6245.5735 | M30: =[13]DCF!AH5 -> 6570.7698 | N30: =[13]DCF!AI5 -> 6912.8986
A31: Net Profit | B31: =[13]DCF!D9 -> 33974.627 | C31: =[13]DCF!E9 -> 40994.661 | D31: =[13]DCF!F9 -> 49465.217 | E31: =[13]DCF!G9 -> 59686.007 | F31: =[13]DCF!H9 -> 72018.677 | I31: Net Profit | J31: =[13]DCF!AE9 -> 1958.4502 | K31: =[13]DCF!AF9 -> 2060.4233 | L31: =[13]DCF!AG9 -> 2167.7061 | M31: =[13]DCF!AH9 -> 2280.5748 | N31: =[13]DCF!AI9 -> 2399.3205
A33: Forecasts | B33: 2026 | C33: 2027 | D33: 2028 | E33: 2029 | F33: 2030 | I33: Forecasts | J33: 2026 | K33: 2027 | L33: 2028 | M33: 2029 | N33: 2030
A34: Revenue | B34: =[13]DCF!M4 -> 39052.654 | C34: =[13]DCF!N4 -> 50055.131 | D34: =[13]DCF!O4 -> 64157.385 | E34: =[13]DCF!P4 -> 82232.729 | F34: =[13]DCF!Q4 -> 105400.52 | I34: Revenue | J34: =[13]DCF!AN4 -> 46216.486 | K34: =[13]DCF!AO4 -> 47900.26 | L34: =[13]DCF!AP4 -> 49645.378 | M34: =[13]DCF!AQ4 -> 51454.074 | N34: =[13]DCF!AR4 -> 53328.665
A35: EBITDA | B35: =[13]DCF!M5 -> 20732.422 | C35: =[13]DCF!N5 -> 26573.46 | D35: =[13]DCF!O5 -> 34060.118 | E35: =[13]DCF!P5 -> 43656.026 | F35: =[13]DCF!Q5 -> 55955.432 | I35: EBITDA | J35: =[13]DCF!AN5 -> 18505.783 | K35: =[13]DCF!AO5 -> 19179.991 | L35: =[13]DCF!AP5 -> 19878.763 | M35: =[13]DCF!AQ5 -> 20602.992 | N35: =[13]DCF!AR5 -> 21353.607
A36: Net Profit | B36: =[13]DCF!M9 -> 9611.8503 | C36: =[13]DCF!N9 -> 12319.839 | D36: =[13]DCF!O9 -> 15790.762 | E36: =[13]DCF!P9 -> 20239.564 | F36: =[13]DCF!Q9 -> 25941.746 | I36: Net Profit | J36: =[13]DCF!AN9 -> 3024.3158 | K36: =[13]DCF!AO9 -> 3134.4986 | L36: =[13]DCF!AP9 -> 3248.6956 | M36: =[13]DCF!AQ9 -> 3367.0532 | N36: =[13]DCF!AR9 -> 3489.7227
A38: Forecasts | B38: 2026 | C38: 2027 | D38: 2028 | E38: 2029 | F38: 2030 | I38: Forecasts | J38: 2026 | K38: 2027 | L38: 2028 | M38: 2029 | N38: 2030
A39: Revenue | B39: =[13]DCF!V4 -> 4275.4133 | C39: =[13]DCF!W4 -> 5147.5508 | D39: =[13]DCF!X4 -> 6197.5949 | E39: =[13]DCF!Y4 -> 7461.8364 | F39: =[13]DCF!Z4 -> 8983.9694 | I39: Revenue | J39: =[13]DCF!AW4 -> 130396.09 | K39: =[13]DCF!AX4 -> 147740.34 | L39: =[13]DCF!AY4 -> 167391.59 | M39: =[13]DCF!AZ4 -> 189656.69 | N39: =[13]DCF!BA4 -> 214883.32
A40: EBITDA | B40: =[13]DCF!V5 -> 926.04216 | C40: =[13]DCF!W5 -> 1114.9446 | D40: =[13]DCF!X5 -> 1342.3811 | E40: =[13]DCF!Y5 -> 1616.2122 | F40: =[13]DCF!Z5 -> 1945.9018 | I40: EBITDA | J40: =[13]DCF!AW5 -> 64593.42 | K40: =[13]DCF!AX5 -> 73185.124 | L40: =[13]DCF!AY5 -> 82919.628 | M40: =[13]DCF!AZ5 -> 93948.939 | N40: =[13]DCF!BA5 -> 106445.28
A41: Net Profit | B41: =[13]DCF!V9 -> 449.34988 | C41: =[13]DCF!W9 -> 541.01234 | D41: =[13]DCF!X9 -> 651.37294 | E41: =[13]DCF!Y9 -> 784.24589 | F41: =[13]DCF!Z9 -> 944.22347 | I41: Net Profit | J41: =[13]DCF!AW9 -> 30075.145 | K41: =[13]DCF!AX9 -> 34075.502 | L41: =[13]DCF!AY9 -> 38607.955 | M41: =[13]DCF!AZ9 -> 43743.278 | N41: =[13]DCF!BA9 -> 49561.662

Sheet Tables-defence
A1: KPI | B1: 2020 | C1: 2021 | D1: 2022 | E1: 2023 | F1: 2024 | H1: KPI | I1: 2020 | J1: 2021 | K1: 2022 | L1: 2023 | M1: 2024 | O1: KPI | P1: 2020 | Q1: 2021 | R1: 2022 | S1: 2023 | T1: 2024 | U1: 2025
A2: Revenue | B2: ='[14]Income Statement'!$M$9 -> 13067.07 | C2: ='[14]Income Statement'!$L$9 -> 14189.93 | D2: ='[14]Income Statement'!$K$9 -> 15547.35 | E2: ='[14]Income Statement'!$J$9 -> 18006.22 | F2: ='[14]Income Statement'!$I$9 -> 20925.23 | H2: Revenue | I2: ='[14]Income Statement'!W6 -> 3192.9223 | J2: ='[14]Income Statement'!X6 -> 2008.3731 | K2: ='[14]Income Statement'!Y6 -> 2928.6132 | L2: ='[14]Income Statement'!Z6 -> 2644.7947 | M2: ='[14]Income Statement'!AA6 -> 2731.1044 | O2: Revenue | P2: ='[14]Income Statement'!AD6 -> 21741.73 | Q2: ='[14]Income Statement'!AE6 -> 23112.77 | R2: ='[14]Income Statement'!AF6 -> 25604.95 | S2: ='[14]Income Statement'!AG6 -> 28597.58 | T2: ='[14]Income Statement'!AH6 -> 32277.68 | U2: ='[14]Income Statement'!AI6 -> 33542.64
A3: EBITDA Margin | B3: ='[14]Ratio Analysis'!I5 -> 0.1350762 | C3: ='[14]Ratio Analysis'!J5 -> 0.15793436 | D3: ='[14]Ratio Analysis'!K5 -> 0.12756145 | E3: ='[14]Ratio Analysis'!L5 -> 0.16735592 | F3: ='[14]Ratio Analysis'!M5 -> 0.23210494 | H3: EBITDA Margin | I3: ='[14]Ratio Analysis'!O5 -> 0.23398931 | J3: ='[14]Ratio Analysis'!P5 -> 0.17167821 | K3: ='[14]Ratio Analysis'!Q5 -> 0.25504307 | L3: ='[14]Ratio Analysis'!R5 -> 0.18388569 | M3: ='[14]Ratio Analysis'!S5 -> 0.30439722 | O3: EBITDA Margin | P3: ='[14]Ratio Analysis'!AA5 -> 0.19323025 | Q3: ='[14]Ratio Analysis'!AB5 -> 0.19596656 | R3: ='[14]Ratio Analysis'!AC5 -> 0.20632573 | S3: ='[14]Ratio Analysis'!AD5 -> 0.22955089 | T3: ='[14]Ratio Analysis'!AE5 -> 0.31695246 | U3: ='[14]Ratio Analysis'!AF5 -> 0.32285443
A4: Net Profit margin | B4: ='[14]Ratio Analysis'!I6 -> 0.086186526 | C4: ='[14]Ratio Analysis'!J6 -> 0.1111789 | D4: ='[14]Ratio Analysis'!K6 -> 0.095099491 | E4: ='[14]Ratio Analysis'!L6 -> 0.12560153 | F4: ='[14]Ratio Analysis'!M6 -> 0.17402165 | H4: Net Profit margin | I4: ='[14]Ratio Analysis'!O6 -> 0.16752703 | J4: ='[14]Ratio Analysis'!P6 -> 0.12834528 | K4: ='[14]Ratio Analysis'!Q6 -> 0.17070346 | L4: ='[14]Ratio Analysis'!R6 -> 0.13386669 | M4: ='[14]Ratio Analysis'!S6 -> 0.22434909 | O4: Net Profit margin | P4: ='[14]Ratio Analysis'!AA6 -> 0.13258605 | Q4: ='[14]Ratio Analysis'!AB6 -> 0.14014158 | R4: ='[14]Ratio Analysis'!AC6 -> 0.19839445 | S4: ='[14]Ratio Analysis'!AD6 -> 0.20378403 | T4: ='[14]Ratio Analysis'!AE6 -> 0.23610588 | U4: ='[14]Ratio Analysis'!AF6 -> 0.24935545
A5: Order Book | B5: ='[15]Macro-Defense'!$D$2 -> 51973 | C5: ='[15]Macro-Defense'!$D$3 -> 53434 | D5: ='[15]Macro-Defense'!$D$4 -> 57570 | E5: =[15]!Table7[[#This Row],[BEL-Order Book]] -> #REF! | F5: ='[15]Macro-Defense'!$D$6 -> 75934 | H5: Order Book | I5: ='[15]Macro-Defense'!$M$2 -> 7413 | J5: ='[15]Macro-Defense'!$M$3 -> 8386 | K5: ='[15]Macro-Defense'!$M$4 -> 10170 | L5: =[15]!Table7[[#This Row],[BDL-Order book]] -> #REF! | M5: ='[15]Macro-Defense'!$M$6 -> 19434 | O5: Order Book | P5: ='[15]Macro-Defense'!$G$2 -> 52965 | Q5: ='[15]Macro-Defense'!$G$3 -> 53000 | R5: ='[15]Macro-Defense'!$G$4 -> 83858 | S5: =[15]!Table7[[#This Row],[HAL-Order book]] -> #REF! | T5: ='[15]Macro-Defense'!$G$6 -> 94000 | U5: ='[15]Macro-Defense'!$G$7 -> 180000
A6: ROE | B6: ='[14]Ratio Analysis'!I9 -> 0.15593682 | C6: ='[14]Ratio Analysis'!J9 -> 0.14973876 | D6: ='[14]Ratio Analysis'!K9 -> 0.15202661 | E6: ='[14]Ratio Analysis'!L9 -> 0.25678147 | F6: ='[14]Ratio Analysis'!M9 -> 0.29557762 | H6: ROE | I6: ='[14]Ratio Analysis'!O9 -> 0.20519208 | J6: ='[14]Ratio Analysis'!P9 -> 0.096010976 | K6: ='[14]Ratio Analysis'!Q9 -> 0.1649612 | L6: ='[14]Ratio Analysis'!R9 -> 0.11024448 | M6: ='[14]Ratio Analysis'!S9 -> 0.16847692 | O6: ROE | P6: ='[14]Ratio Analysis'!AA9 -> 0.2175122 | Q6: ='[14]Ratio Analysis'!AB9 -> 0.21010782 | R6: ='[14]Ratio Analysis'!AC9 -> 0.26297622 | S6: ='[14]Ratio Analysis'!AD9 -> 0.24719024 | T6: ='[14]Ratio Analysis'!AE9 -> 0.26151258 | U6: ='[14]Ratio Analysis'!AF9 -> 0.23907387
A7: Capex | B7: ='[14]Cash Flow Statement'!$F$62 -> 652.53 | C7: ='[14]Cash Flow Statement'!$E$62 -> 590.45 | D7: ='[14]Cash Flow Statement'!$D$62 -> 554.56 | E7: ='[14]Cash Flow Statement'!$C$62 -> 469.25 | F7: ='[14]Cash Flow Statement'!$B$62 -> 762.2 | H7: Capex | I7: ='[14]Cash Flow Statement'!P52 -> 56.8884 | J7: ='[14]Cash Flow Statement'!Q52 -> 56.6091 | K7: ='[14]Cash Flow Statement'!R52 -> 102.0442 | L7: ='[14]Cash Flow Statement'!S52 -> 108.2571 | M7: ='[14]Cash Flow Statement'!T52 -> 80.8897 | O7: Capex | P7: ='[14]Cash Flow Statement'!AD56 -> 890.23 | Q7: ='[14]Cash Flow Statement'!AE56 -> 762.98 | R7: ='[14]Cash Flow Statement'!AF56 -> 799.29 | S7: ='[14]Cash Flow Statement'!AG56 -> 782.42 | T7: ='[14]Cash Flow Statement'!AH56 -> 916.42 | U7: ='[14]Cash Flow Statement'!AI56 -> 930.09
A8: Debt/Equity | B8: ='[14]Ratio Analysis'!I14 -> 0 | C8: ='[14]Ratio Analysis'!J14 -> 0 | D8: ='[14]Ratio Analysis'!K14 -> 0 | E8: ='[14]Ratio Analysis'!L14 -> 0 | F8: ='[14]Ratio Analysis'!M14 -> 0 | H8: Debt/Equity | I8: ='[14]Ratio Analysis'!O14 -> 0.0041963616 | J8: ='[14]Ratio Analysis'!P14 -> 0.0028724865 | K8: ='[14]Ratio Analysis'!Q14 -> 0.0021537622 | L8: ='[14]Ratio Analysis'!R14 -> 0.0016215176 | M8: ='[14]Ratio Analysis'!S14 -> 0.0010286725 | O8: Debt/Equity | P8: ='[14]Ratio Analysis'!AA14 -> 0.44416962 | Q8: ='[14]Ratio Analysis'!AB14 -> 0.0005883429 | R8: ='[14]Ratio Analysis'!AC14 -> 0.0001289028 | S8: ='[14]Ratio Analysis'!AD14 -> 0.00011240297 | T8: ='[14]Ratio Analysis'!AE14 -> 3.7746454e-05 | U8: ='[14]Ratio Analysis'!AF14 -> 3.3156906e-05
A10: KPI | B10: 2020 | C10: 2021 | D10: 2022 | E10: 2023 | F10: 2024 | H10: KPI | I10: 2020 | J10: 2021 | K10: 2022 | L10: 2023 | M10: 2024
A11: Revenue | B11: ='[14]Income Statement'!$F$9 -> 5535.32 | C11: ='[14]Income Statement'!$E$9 -> 4621.92 | D11: ='[14]Income Statement'!$D$9 -> 6166.91 | E11: ='[14]Income Statement'!$C$9 -> 8540.66 | F11: ='[14]Income Statement'!$B$9 -> 10604.6 | H11: Revenue | I11: ='[14]Income Statement'!P6 -> 1658.7947 | J11: ='[14]Income Statement'!Q6 -> 1328.4309 | K11: ='[14]Income Statement'!R6 -> 1918.16 | L11: ='[14]Income Statement'!S6 -> 2762.9806 | M11: ='[14]Income Statement'!T6 -> 3892.2642
A12: EBITDA Margin | B12: ='[14]Ratio Analysis'!C5 -> 0.18966761 | C12: ='[14]Ratio Analysis'!D5 -> 0.20682343 | D12: ='[14]Ratio Analysis'!E5 -> 0.20310857 | E12: ='[14]Ratio Analysis'!F5 -> 0.22130575 | F12: ='[14]Ratio Analysis'!G5 -> 0.25493435 | H12: EBITDA Margin | I12: ='[14]Ratio Analysis'!U5 -> 0.14215961 | J12: ='[14]Ratio Analysis'!V5 -> 0.17356401 | K12: ='[14]Ratio Analysis'!W5 -> 0.13850961 | L12: ='[14]Ratio Analysis'!X5 -> 0.11281245 | M12: ='[14]Ratio Analysis'!Y5 -> 0.12650994
A13: Net Profit margin | B13: ='[14]Ratio Analysis'!C6 -> 0.13964263 | C13: ='[14]Ratio Analysis'!D6 -> 0.14555533 | D13: ='[14]Ratio Analysis'!E6 -> 0.15108234 | E13: ='[14]Ratio Analysis'!F6 -> 0.16697952 | F13: ='[14]Ratio Analysis'!G6 -> 0.19211258 | H13: Net Profit margin | I13: ='[14]Ratio Analysis'!U6 -> 0.098554511 | J13: ='[14]Ratio Analysis'!V6 -> 0.11552818 | K13: ='[14]Ratio Analysis'!W6 -> 0.098802655 | L13: ='[14]Ratio Analysis'!X6 -> 0.08256446 | M13: ='[14]Ratio Analysis'!Y6 -> 0.09178917
A14: Order Book | B14: ='[15]Macro-Defense'!$J$2 -> 54074 | C14: ='[15]Macro-Defense'!$J$3 -> 42000 | D14: ='[15]Macro-Defense'!$J$4 -> 0 | E14: ='[15]Macro-Defense'!$J$5 -> 37500 | F14: ='[15]Macro-Defense'!$J$6 -> 36839 | H14: Order Book | I14: ='[15]Macro-Defense'!$P$2 -> 26000 | J14: ='[15]Macro-Defense'!$P$3 -> 25707 | K14: ='[15]Macro-Defense'!$P$4 -> 22930 | L14: ='[15]Macro-Defense'!$P$5 -> 23740 | M14: ='[15]Macro-Defense'!$P$6 -> 24221.37
A15: ROE | B15: ='[14]Ratio Analysis'!C9 -> 0.18519548 | C15: ='[14]Ratio Analysis'!D9 -> 0.18650115 | D15: ='[14]Ratio Analysis'!E9 -> 0.19093468 | E15: ='[14]Ratio Analysis'!F9 -> 0.14881212 | F15: ='[14]Ratio Analysis'!G9 -> 0.24595595 | H15: ROE | I15: ='[14]Ratio Analysis'!U9 -> 0.15715903 | J15: ='[14]Ratio Analysis'!V9 -> 0.13496511 | K15: ='[14]Ratio Analysis'!W9 -> 0.15066436 | L15: ='[14]Ratio Analysis'!X9 -> 0.16135322 | M15: ='[14]Ratio Analysis'!Y9 -> 0.21349312
A16: Capex | B16: ='[14]Cash Flow Statement'!I49 -> 109.5 | C16: ='[14]Cash Flow Statement'!J49 -> 41.9 | D16: ='[14]Cash Flow Statement'!K49 -> 32.01 | E16: ='[14]Cash Flow Statement'!L49 -> 135.57 | F16: ='[14]Cash Flow Statement'!M49 -> 103.03 | H16: Capex | I16: ='[14]Cash Flow Statement'!W50 -> 67.3676 | J16: ='[14]Cash Flow Statement'!X50 -> 163.844 | K16: ='[14]Cash Flow Statement'!Y50 -> 54.8278 | L16: ='[14]Cash Flow Statement'!Z50 -> 42.2584 | M16: ='[14]Cash Flow Statement'!AA50 -> 48.0691
A17: Debt/Equity | B17: ='[14]Ratio Analysis'!C14 -> 0 | C17: ='[14]Ratio Analysis'!D14 -> 0.00022754834 | D17: ='[14]Ratio Analysis'!E14 -> 0.0042837623 | E17: ='[14]Ratio Analysis'!F14 -> 0.0044195058 | F17: ='[14]Ratio Analysis'!G14 -> 0.0038245539 | H17: Debt/Equity | I17: ='[14]Ratio Analysis'!U14 -> 0 | J17: ='[14]Ratio Analysis'!V14 -> 0 | K17: ='[14]Ratio Analysis'!W14 -> 0.0089071332 | L17: ='[14]Ratio Analysis'!X14 -> 0.22075515 | M17: ='[14]Ratio Analysis'!Y14 -> 0.039242903
A19: Forecasts | B19: 2025 | C19: 2026 | D19: 2027 | E19: 2028 | F19: 2029 | G19: 2030
A20: Revenue | B20: =[14]DCF!D4 -> 12077.154 | C20: =[14]DCF!E4 -> 13754.187 | D20: =[14]DCF!F4 -> 15664.092 | E20: =[14]DCF!G4 -> 17839.207 | F20: =[14]DCF!H4 -> 20316.358 | G20: =[14]DCF!I4 -> 23137.486 | J20: =(G22-B22)/B22 -> 2.2584715 | K20: =(G22/B22)^(1/6)-1 -> 0.2175935
A21: EBITDA | B21: =[14]DCF!D5+[14]DCF!D8 -> 3210.1685 | C21: =[14]DCF!E5+[14]DCF!E8 -> 4045.9999 | D21: =[14]DCF!F5+[14]DCF!F8 -> 5103.81 | E21: =[14]DCF!G5+[14]DCF!G8 -> 6442.7247 | F21: =[14]DCF!H5+[14]DCF!H8 -> 8137.6255 | G21: =[14]DCF!I5+[14]DCF!I8 -> 10283.348 | J21: =(G28-B28)/B28 -> 1.1521273 | K21: =(G28/B28)^(1/6)-1 -> 0.13626072
A22: Net Profit | B22: =[14]DCF!D7 -> 2342.8537 | C22: =[14]DCF!E7 -> 2967.2077 | D22: =[14]DCF!F7 -> 3757.9478 | E22: =[14]DCF!G7 -> 4759.4144 | F22: =[14]DCF!H7 -> 6027.765 | G22: =[14]DCF!I7 -> 7634.122 | J22: =(G34-B34)/B34 -> 2.0045143 | K22: =(G34/B34)^(1/6)-1 -> 0.20123795
A23: Capex | B23: =[14]DCF!D9 -> 786.25358 | C23: =[14]DCF!E9 -> 811.06625 | D23: =[14]DCF!F9 -> 836.66196 | E23: =[14]DCF!G9 -> 863.06541 | F23: =[14]DCF!H9 -> 890.30212 | G23: =[14]DCF!I9 -> 918.39836 | J23: =(G40-B40)/B40 -> 1.0881327 | K23: =(G40/B40)^(1/6)-1 -> 0.13055844
J24: =(F46-B46)/B46 -> 0.87999422 | K24: =(F46/B46)^(1/5)-1 -> 0.13457002
A25: Forecasts | B25: 2025 | C25: 2026 | D25: 2027 | E25: 2028 | F25: 2029 | G25: 2030 | J25: =AVERAGE(J20:J24) -> 1.476648 | K25: =AVERAGE(K20:K24) -> 0.16404413
A26: Revenue | B26: =[14]DCF!N4 -> 22991.571 | C26: =[14]DCF!O4 -> 25261.96 | D26: =[14]DCF!P4 -> 27756.548 | E26: =[14]DCF!Q4 -> 30497.473 | F26: =[14]DCF!R4 -> 33509.061 | G26: =[14]DCF!S4 -> 36818.04
A27: EBITDA | B27: =[14]DCF!N5+[14]DCF!N8 -> 6647.5509 | C27: =[14]DCF!O5+[14]DCF!O8 -> 7687.8707 | D27: =[14]DCF!P5+[14]DCF!P8 -> 8899.2593 | E27: =[14]DCF!Q5+[14]DCF!Q8 -> 10310.03 | F27: =[14]DCF!R5+[14]DCF!R8 -> 11953.186 | G27: =[14]DCF!S5+[14]DCF!S8 -> 13867.198
A28: Net Profit | B28: =[14]DCF!N7 -> 4669.8679 | C28: =[14]DCF!O7 -> 5443.4995 | D28: =[14]DCF!P7 -> 6345.2944 | E28: =[14]DCF!Q7 -> 7396.4848 | F28: =[14]DCF!R7 -> 8621.8202 | G28: =[14]DCF!S7 -> 10050.15
A29: Capex | B29: =[14]DCF!N9 -> 118.70775 | C29: =[14]DCF!O9 -> 130.42999 | D29: =[14]DCF!P9 -> 143.3098 | E29: =[14]DCF!Q9 -> 157.46146 | F29: =[14]DCF!R9 -> 173.01059 | G29: =[14]DCF!S9 -> 190.09517
A31: Forecasts | B31: 2025 | C31: 2026 | D31: 2027 | E31: 2028 | F31: 2029 | G31: 2030
A32: Revenue | B32: =[14]DCF!X4 -> 2949.2513 | C32: =[14]DCF!Y4 -> 3184.8227 | D32: =[14]DCF!Z4 -> 3439.2103 | E32: =[14]DCF!AA4 -> 3713.9171 | F32: =[14]DCF!AB4 -> 4010.5662 | G32: =[14]DCF!AC4 -> 4330.91
A33: EBITDA | B33: =[14]DCF!X5+[14]DCF!X8 -> 1128.8823 | C33: =[14]DCF!Y5+[14]DCF!Y8 -> 1391.2565 | D33: =[14]DCF!Z5+[14]DCF!Z8 -> 1716.9682 | E33: =[14]DCF!AA5+[14]DCF!AA8 -> 2121.5069 | F33: =[14]DCF!AB5+[14]DCF!AB8 -> 2624.1656 | G33: =[14]DCF!AC5+[14]DCF!AC8 -> 3248.9775
A34: Net Profit | B34: =[14]DCF!X7 -> 776.95364 | C34: =[14]DCF!Y7 -> 968.1663 | D34: =[14]DCF!Z7 -> 1206.4375 | E34: =[14]DCF!AA7 -> 1503.3485 | F34: =[14]DCF!AB7 -> 1873.331 | G34: =[14]DCF!AC7 -> 2334.3683
A35: Capex | B35: =[14]DCF!X9 -> 88.37147 | C35: =[14]DCF!Y9 -> 95.430139 | D35: =[14]DCF!Z9 -> 103.05262 | E35: =[14]DCF!AA9 -> 111.28394 | F35: =[14]DCF!AB9 -> 120.17275 | G35: =[14]DCF!AC9 -> 129.77154
A37: Forecasts | B37: 2025 | C37: 2026 | D37: 2027 | E37: 2028 | F37: 2029 | G37: 2030
A38: Revenue | B38: =[14]DCF!AH4 -> 4616.1961 | C38: =[14]DCF!AI4 -> 5474.7738 | D38: =[14]DCF!AJ4 -> 6493.0406 | E38: =[14]DCF!AK4 -> 7700.6973 | F38: =[14]DCF!AL4 -> 9132.969 | G38: =[14]DCF!AM4 -> 10831.633
A39: EBITDA | B39: =[14]DCF!AH5+[14]DCF!AH8 -> 614.56466 | C39: =[14]DCF!AI5+[14]DCF!AI8 -> 707.96366 | D39: =[14]DCF!AJ5+[14]DCF!AJ8 -> 815.91156 | E39: =[14]DCF!AK5+[14]DCF!AK8 -> 940.6989 | F39: =[14]DCF!AL5+[14]DCF!AL8 -> 1084.9785 | G39: =[14]DCF!AM5+[14]DCF!AM8 -> 1251.8227
A40: Net Profit | B40: =[14]DCF!AH7 -> 427.89759 | C40: =[14]DCF!AI7 -> 495.7828 | D40: =[14]DCF!AJ7 -> 574.43789 | E40: =[14]DCF!AK7 -> 665.57147 | F40: =[14]DCF!AL7 -> 771.16324 | G40: =[14]DCF!AM7 -> 893.50696
A41: Capex | B41: =[14]DCF!AH9 -> 150.28449 | C41: =[14]DCF!AI9 -> 178.23627 | D41: =[14]DCF!AJ9 -> 211.38688 | E41: =[14]DCF!AK9 -> 250.70324 | F41: =[14]DCF!AL9 -> 297.33216 | G41: =[14]DCF!AM9 -> 352.63371
A43: Forecasts | B43: 2026 | C43: 2027 | D43: 2028 | E43: 2029 | F43: 2030
A44: Revenue | B44: =[14]DCF!AR4 -> 36056.295 | C44: =[14]DCF!AS4 -> 38758.321 | D44: =[14]DCF!AT4 -> 41662.834 | E44: =[14]DCF!AU4 -> 44785.009 | F44: =[14]DCF!AV4 -> 48141.157
A45: EBITDA | B45: =[14]DCF!AR5+[14]DCF!AR8 -> 14088.481 | C45: =[14]DCF!AS5+[14]DCF!AS8 -> 16327.077 | D45: =[14]DCF!AT5+[14]DCF!AT8 -> 18939.823 | E45: =[14]DCF!AU5+[14]DCF!AU8 -> 21990.251 | F45: =[14]DCF!AV5+[14]DCF!AV8 -> 25552.731
A46: Net Profit | B46: =[14]DCF!AR7 -> 9510.5227 | C46: =[14]DCF!AS7 -> 11136.366 | D46: =[14]DCF!AT7 -> 13040.152 | E46: =[14]DCF!AU7 -> 15269.393 | F46: =[14]DCF!AV7 -> 17879.728
A47: Capex | B47: =[14]DCF!AR9 -> 1111.2353 | C47: =[14]DCF!AS9 -> 1194.5103 | D47: =[14]DCF!AT9 -> 1284.0258 | E47: =[14]DCF!AU9 -> 1380.2496 | F47: =[14]DCF!AV9 -> 1483.6842

Sheet Tables-Oil&Gas
A1: KPI | B1: 2020 | C1: 2021 | D1: 2022 | E1: 2023 | F1: 2024 | G1: 2025 | I1: KPI | J1: 2020 | K1: 2021 | L1: 2022 | M1: 2023 | N1: 2024 | O1: 2025 | Q1: KPI | R1: 2020 | S1: 2021 | T1: 2022 | U1: 2023 | V1: 2024 | W1: 2025
A2: Revenue | B2: ='[16]Income Statement'!B8 -> 330662.09 | C2: ='[16]Income Statement'!C8 -> 306209.43 | D2: ='[16]Income Statement'!D8 -> 435051.84 | E2: ='[16]Income Statement'!E8 -> 535651.54 | F2: ='[16]Income Statement'!F8 -> 509227.33 | G2: ='[16]Income Statement'!G8 -> 503202.2 | I2: Revenue | J2: ='[16]Income Statement'!R9 -> 289423.67 | K2: ='[16]Income Statement'!S9 -> 273221.69 | L2: ='[16]Income Statement'!T9 -> 376565.91 | M2: ='[16]Income Statement'!U9 -> 467964.52 | N2: ='[16]Income Statement'!V9 -> 463886.08 | O2: ='[16]Income Statement'!W9 -> 468811.53 | Q2: Revenue | R2: ='[16]Income Statement'!AH8 -> 434038.1 | S2: ='[16]Income Statement'!AI8 -> 369895.33 | T2: ='[16]Income Statement'!AJ8 -> 539230.25 | U2: ='[16]Income Statement'!AK8 -> 692903.3 | V2: ='[16]Income Statement'!AL8 -> 665201.46 | W2: ='[16]Income Statement'!AM8 -> 675655.88
A3: EBITDA | B3: ='[16]Income Statement'!B19+'[16]Income Statement'!B15+'[16]Income Statement'!B16 -> 9720.62 | C3: ='[16]Income Statement'!C19+'[16]Income Statement'!C15+'[16]Income Statement'!C16 -> 21475.08 | D3: ='[16]Income Statement'!D19+'[16]Income Statement'!D15+'[16]Income Statement'!D16 -> 21655.38 | E3: ='[16]Income Statement'!E19+'[16]Income Statement'!E15+'[16]Income Statement'!E16 -> 13140.62 | F3: ='[16]Income Statement'!F19+'[16]Income Statement'!F15+'[16]Income Statement'!F16 -> 46316.91 | G3: ='[16]Income Statement'!G19+'[16]Income Statement'!G15+'[16]Income Statement'!G16 -> 28086.1 | I3: EBITDA | J3: ='[16]Income Statement'!R20+'[16]Income Statement'!R16+'[16]Income Statement'!R17 -> 7344.11 | K3: ='[16]Income Statement'!S20+'[16]Income Statement'!S16+'[16]Income Statement'!S17 -> 18647.09 | L3: ='[16]Income Statement'!T20+'[16]Income Statement'!T16+'[16]Income Statement'!T17 -> 12683.25 | M3: ='[16]Income Statement'!U20+'[16]Income Statement'!U16+'[16]Income Statement'!U17 -> -5741.17 | N3: ='[16]Income Statement'!V20+'[16]Income Statement'!V16+'[16]Income Statement'!V17 -> 26844.72 | O3: ='[16]Income Statement'!W20+'[16]Income Statement'!W16+'[16]Income Statement'!W17 -> 18639.05 | Q3: EBITDA | R3: ='[16]Income Statement'!AH19+'[16]Income Statement'!AH15+'[16]Income Statement'!AH16 -> 61181.999 | S3: ='[16]Income Statement'!AI19+'[16]Income Statement'!AI15+'[16]Income Statement'!AI16 -> 58789.019 | T3: ='[16]Income Statement'!AJ19+'[16]Income Statement'!AJ15+'[16]Income Statement'!AJ16 -> 87311.293 | U3: ='[16]Income Statement'!AK19+'[16]Income Statement'!AK15+'[16]Income Statement'!AK16 -> 83601.054 | V3: ='[16]Income Statement'!AL19+'[16]Income Statement'!AL15+'[16]Income Statement'!AL16 -> 114413.73 | W3: ='[16]Income Statement'!AM19+'[16]Income Statement'!AM15+'[16]Income Statement'!AM16 -> 101254.29
A4: Net Profit | B4: ='[16]Income Statement'!B27 -> 2683.19 | C4: ='[16]Income Statement'!C27 -> 19041.67 | D4: ='[16]Income Statement'!D27 -> 11363.35 | E4: ='[16]Income Statement'!E27 -> 1870.1 | F4: ='[16]Income Statement'!F27 -> 25263.33 | G4: ='[16]Income Statement'!G27 -> 11447.89 | I4: Net Profit | J4: ='[16]Income Statement'!R30 -> 2115.71 | K4: ='[16]Income Statement'!S30 -> 10662.89 | L4: ='[16]Income Statement'!T30 -> 10993.01 | M4: ='[16]Income Statement'!U30 -> -6980.23 | N4: ='[16]Income Statement'!V30 -> 16014.61 | O4: ='[16]Income Statement'!W30 -> 6735.7 | Q4: Net Profit | R4: ='[16]Income Statement'!AH29 -> 11456.259 | S4: ='[16]Income Statement'!AI29 -> 21343.446 | T4: ='[16]Income Statement'!AJ29 -> 49294.057 | U4: ='[16]Income Statement'!AK29 -> 32777.605 | V4: ='[16]Income Statement'!AL29 -> 55273.149 | W4: ='[16]Income Statement'!AM29 -> 38328.61
A5: ROE | B5: ='[16]Financial Ratios'!C14 -> 0.080783986 | C5: ='[16]Financial Ratios'!D14 -> 0.35555301 | D5: ='[16]Financial Ratios'!E14 -> 0.21892331 | E5: ='[16]Financial Ratios'!F14 -> 0.034940537 | F5: ='[16]Financial Ratios'!G14 -> 0.33401591 | G5: ='[16]Financial Ratios'!H14 -> 0.14066498 | I5: ROE | J5: ='[16]Financial Ratios'!U14 -> 0.068291403 | K5: ='[16]Financial Ratios'!V14 -> 0.28000654 | L5: ='[16]Financial Ratios'!W14 -> 0.26550464 | M5: ='[16]Financial Ratios'!X14 -> -0.21635222 | N5: ='[16]Financial Ratios'!Y14 -> 0.34130753 | O5: ='[16]Financial Ratios'!Z14 -> 0.13169994 | Q5: ROE | R5: ='[16]Financial Ratios'!AM14 -> 0.051255969 | S5: ='[16]Financial Ratios'!AN14 -> 0.087979096 | T5: ='[16]Financial Ratios'!AO14 -> 0.1739824 | U5: ='[16]Financial Ratios'!AP14 -> 0.10880351 | V5: ='[16]Financial Ratios'!AQ14 -> 0.15369694 | W5: ='[16]Financial Ratios'!AR14 -> 0.10241853
A6: D/E | B6: ='[16]Financial Ratios'!C7 -> 1.3245489 | C6: ='[16]Financial Ratios'!D7 -> 0.87155523 | D6: ='[16]Financial Ratios'!E7 -> 1.0775843 | E6: ='[16]Financial Ratios'!F7 -> 1.1295206 | F6: ='[16]Financial Ratios'!G7 -> 0.60137322 | G6: ='[16]Financial Ratios'!H7 -> 0.62740661 | I6: D/E | J6: ='[16]Financial Ratios'!U7 -> 1.2713028 | K6: ='[16]Financial Ratios'!V7 -> 1.1206173 | L6: ='[16]Financial Ratios'!W7 -> 1.0863323 | M6: ='[16]Financial Ratios'!X7 -> 2.0781619 | N6: ='[16]Financial Ratios'!Y7 -> 1.3386895 | O6: ='[16]Financial Ratios'!Z7 -> 1.2988523 | Q6: D/E | R6: ='[16]Financial Ratios'!AM7 -> 0.46725816 | S6: ='[16]Financial Ratios'!AN7 -> 0.45268395 | T6: ='[16]Financial Ratios'!AO7 -> 0.38039257 | U6: ='[16]Financial Ratios'!AP7 -> 0.42882455 | V6: ='[16]Financial Ratios'!AQ7 -> 0.43847317 | W6: ='[16]Financial Ratios'!AR7 -> 0.41031933
A7: EV/EBITDA | B7: ='[16]Financial Ratios'!C19 -> 19.918236 | C7: ='[16]Financial Ratios'!D19 -> 7.2562915 | D7: ='[16]Financial Ratios'!E19 -> 6.9765098 | E7: ='[16]Financial Ratios'!F19 -> 20.927611 | F7: ='[16]Financial Ratios'!G19 -> 7.5002389 | G7: ='[16]Financial Ratios'!H19 -> 67.68234 | I7: EV/EBITDA | J7: ='[16]Financial Ratios'!U19 -> 18.58446 | K7: ='[16]Financial Ratios'!V19 -> 7.4810075 | L7: ='[16]Financial Ratios'!W19 -> 11.199827 | M7: ='[16]Financial Ratios'!X19 -> -28.536892 | N7: ='[16]Financial Ratios'!Y19 -> 5.9541914 | O7: ='[16]Financial Ratios'!Z19 -> 8.775554 | Q7: EV/EBITDA | R7: ='[16]Financial Ratios'!AM19 -> 6.6009669 | S7: ='[16]Financial Ratios'!AN19 -> 6.9741596 | T7: ='[16]Financial Ratios'!AO19 -> 4.66085 | U7: ='[16]Financial Ratios'!AP19 -> 5.1524381 | V7: ='[16]Financial Ratios'!AQ19 -> 4.0008112 | W7: ='[16]Financial Ratios'!AR19 -> 4.4759116
A9: KPI | B9: 2020 | C9: 2021 | D9: 2022 | E9: 2023 | F9: 2024 | G9: 2025 | I9: KPI | J9: 2020 | K9: 2021 | L9: 2022 | M9: 2023 | N9: 2024 | O9: 2025 | Q9: KPI | R9: 2020 | S9: 2021 | T9: 2022 | U9: 2023 | V9: 2024 | W9: 2025
A10: Revenue | B10: ='[16]Income Statement'!J8 -> 74114.13 | C10: ='[16]Income Statement'!K8 -> 58548.46 | D10: ='[16]Income Statement'!L8 -> 94046.07 | E10: ='[16]Income Statement'!M8 -> 147203.5 | F10: ='[16]Income Statement'!N8 -> 134507.35 | G10: ='[16]Income Statement'!O8 -> 143559.06 | I10: Revenue | J10: ='[16]Income Statement'!Z8 -> 578763.32 | K10: ='[16]Income Statement'!AA8 -> 523736.38 | L10: ='[16]Income Statement'!AB8 -> 739813.06 | M10: ='[16]Income Statement'!AC8 -> 955608.86 | N10: ='[16]Income Statement'!AD8 -> 885074.01 | O10: ='[16]Income Statement'!AE8 -> 862876.46 | Q10: Revenue | R10: =[16]!Table12[[#This Row],[2020]] -> 365421 | S10: =[16]!Table12[[#This Row],[2021]] -> 279887 | T10: =[16]!Table12[[#This Row],[2022]] -> 457838 | U10: =[16]!Table12[[#This Row],[2023]] -> 553020 | V10: =[16]!Table12[[#This Row],[2024]] -> 560070 | W10: =[16]!Table12[[#This Row],[2025]] -> 548886
A11: EBITDA | B11: ='[16]Income Statement'!J19+'[16]Income Statement'!J14+'[16]Income Statement'!J15 -> 10571.44 | C11: ='[16]Income Statement'!K19+'[16]Income Statement'!K14+'[16]Income Statement'!K15 -> 8363.96 | D11: ='[16]Income Statement'!L19+'[16]Income Statement'!L14+'[16]Income Statement'!L15 -> 16323.83 | E11: ='[16]Income Statement'!M19+'[16]Income Statement'!M14+'[16]Income Statement'!M15 -> 8815.93 | F11: ='[16]Income Statement'!N19+'[16]Income Statement'!N14+'[16]Income Statement'!N15 -> 15304.13 | G11: ='[16]Income Statement'!O19+'[16]Income Statement'!O14+'[16]Income Statement'!O15 -> 16699.46 | I11: EBITDA | J11: ='[16]Income Statement'!Z23+'[16]Income Statement'!Z15+'[16]Income Statement'!Z17+'[16]Income Statement'!Z18 -> 19613.67 | K11: ='[16]Income Statement'!AA23+'[16]Income Statement'!AA15+'[16]Income Statement'!AA17+'[16]Income Statement'!AA18 -> 44084.57 | L11: ='[16]Income Statement'!AB23+'[16]Income Statement'!AB15+'[16]Income Statement'!AB17+'[16]Income Statement'!AB18 -> 50823.9 | M11: ='[16]Income Statement'!AC23+'[16]Income Statement'!AC15+'[16]Income Statement'!AC17+'[16]Income Statement'!AC18 -> 34897.91 | N11: ='[16]Income Statement'!AD23+'[16]Income Statement'!AD15+'[16]Income Statement'!AD17+'[16]Income Statement'!AD18 -> 79433.62 | O11: ='[16]Income Statement'!AE23+'[16]Income Statement'!AE15+'[16]Income Statement'!AE17+'[16]Income Statement'!AE18 -> 39504.27 | Q11: EBITDA | R11: ='[16]Income Statement'!AP21+'[16]Income Statement'!AP17+'[16]Income Statement'!AP18 -> 66394 | S11: ='[16]Income Statement'!AQ21+'[16]Income Statement'!AQ17+'[16]Income Statement'!AQ18 -> 48318 | T11: ='[16]Income Statement'!AR21+'[16]Income Statement'!AR17+'[16]Income Statement'!AR18 -> 64783 | U11: ='[16]Income Statement'!AS21+'[16]Income Statement'!AS17+'[16]Income Statement'!AS18 -> 76877 | V11: ='[16]Income Statement'!AT21+'[16]Income Statement'!AT17+'[16]Income Statement'!AT18 -> 86393 | W11: ='[16]Income Statement'!AU21+'[16]Income Statement'!AU17+'[16]Income Statement'!AU18 -> 74163
A12: Net Profit | B12: ='[16]Income Statement'!J27 -> 9514.64 | C12: ='[16]Income Statement'!K27 -> 6142.82 | D12: ='[16]Income Statement'!L27 -> 12303.63 | E12: ='[16]Income Statement'!M27 -> 5595.35 | F12: ='[16]Income Statement'!N27 -> 9902.81 | G12: ='[16]Income Statement'!O27 -> 12462.87 | I12: Net Profit | J12: ='[16]Income Statement'!Z32 -> -1876.32 | K12: ='[16]Income Statement'!AA32 -> 21762.22 | L12: ='[16]Income Statement'!AB32 -> 25726.6 | M12: ='[16]Income Statement'!AC32 -> 11704.26 | N12: ='[16]Income Statement'!AD32 -> 43161.15 | O12: ='[16]Income Statement'!AE32 -> 13788.83 | Q12: Net Profit | R12: ='[16]Income Statement'!AP28 -> 30903 | S12: ='[16]Income Statement'!AQ28 -> 31944 | T12: ='[16]Income Statement'!AR28 -> 37937 | U12: ='[16]Income Statement'!AS28 -> 43017 | V12: ='[16]Income Statement'!AT28 -> 42042 | W12: ='[16]Income Statement'!AU28 -> 35262
A13: ROE | B13: ='[16]Financial Ratios'!L14 -> 0.19277852 | C13: ='[16]Financial Ratios'!M14 -> 0.11529354 | D13: ='[16]Financial Ratios'!N14 -> 0.19133103 | E13: ='[16]Financial Ratios'!O14 -> 0.085940862 | F13: ='[16]Financial Ratios'!P14 -> 0.12828175 | G13: ='[16]Financial Ratios'!Q14 -> 0.14620835 | I13: ROE | J13: ='[16]Financial Ratios'!AD14 -> -0.019489338 | K13: ='[16]Financial Ratios'!AE14 -> 0.19290356 | L13: ='[16]Financial Ratios'!AF14 -> 0.19038879 | M13: ='[16]Financial Ratios'!AG14 -> 0.081725475 | N13: ='[16]Financial Ratios'!AH14 -> 0.22938173 | O13: ='[16]Financial Ratios'!AI14 -> 0.072183508 | Q13: ROE | R13: ='[16]Financial Ratios'!AV14 -> 0.07899237 | S13: ='[16]Financial Ratios'!AW14 -> 0.067323803 | T13: ='[16]Financial Ratios'!AX14 -> 0.080455626 | U13: ='[16]Financial Ratios'!AY14 -> 0.089788225 | V13: ='[16]Financial Ratios'!AZ14 -> 0.081619737 | W13: ='[16]Financial Ratios'!BA14 -> 0.064928824
A14: D/E | B14: ='[16]Financial Ratios'!L7 -> 0.12840771 | C14: ='[16]Financial Ratios'!M7 -> 0.12688291 | D14: ='[16]Financial Ratios'!N7 -> 0.12176758 | E14: ='[16]Financial Ratios'!O7 -> 0.24997166 | F14: ='[16]Financial Ratios'!P7 -> 0.24104945 | G14: ='[16]Financial Ratios'!Q7 -> 0.19131016 | I14: D/E | J14: ='[16]Financial Ratios'!AD7 -> 1.3084303 | K14: ='[16]Financial Ratios'!AE7 -> 0.96189231 | L14: ='[16]Financial Ratios'!AF7 -> 0.91432815 | M14: ='[16]Financial Ratios'!AG7 -> 0.97835747 | N14: ='[16]Financial Ratios'!AH7 -> 0.65609914 | O14: ='[16]Financial Ratios'!AI7 -> 0.74629056 | Q14: D/E | R14: ='[16]Financial Ratios'!AV7 -> 0.65002876 | S14: ='[16]Financial Ratios'!AW7 -> 0.40833918 | T14: ='[16]Financial Ratios'!AX7 -> 0.41262324 | U14: ='[16]Financial Ratios'!AY7 -> 0.45048153 | V14: ='[16]Financial Ratios'!AZ7 -> 0.41116607 | W14: ='[16]Financial Ratios'!BA7 -> 0.36607947
A15: EV/EBITDA | B15: ='[16]Financial Ratios'!L19 -> 11.581608 | C15: ='[16]Financial Ratios'!M19 -> 12.262019 | D15: ='[16]Financial Ratios'!N19 -> 13.685881 | E15: ='[16]Financial Ratios'!O19 -> 36.254757 | F15: ='[16]Financial Ratios'!P19 -> 122.08939 | G15: ='[16]Financial Ratios'!Q19 -> 7.9185993 | I15: EV/EBITDA | J15: ='[16]Financial Ratios'!AD19 -> 17.405888 | K15: ='[16]Financial Ratios'!AE19 -> 7.3629746 | L15: ='[16]Financial Ratios'!AF19 -> 6.6746828 | M15: ='[16]Financial Ratios'!AG19 -> 10.200564 | N15: ='[16]Financial Ratios'!AH19 -> 4.2685563 | O15: ='[16]Financial Ratios'!AI19 -> 9.0812115 | Q15: EV/EBITDA | R15: ='[16]Financial Ratios'!AV19 -> 31.572823 | S15: ='[16]Financial Ratios'!AW19 -> 42.191461 | T15: ='[16]Financial Ratios'!AX19 -> 31.56433 | U15: ='[16]Financial Ratios'!AY19 -> 26.869649 | V15: ='[16]Financial Ratios'!AZ19 -> 23.068675 | W15: ='[16]Financial Ratios'!BA19 -> 26.519585
A17: Forecasts | B17: 2026 | C17: 2027 | D17: 2028 | E17: 2029 | F17: 2030 | I17: Forecasts | J17: 2026 | K17: 2027 | L17: 2028 | M17: 2029 | N17: 2030 | Q17: Forecasts | R17: 2026 | S17: 2027 | T17: 2028 | U17: 2029 | V17: 2030
A18: Revenue | B18: =[16]FCFF!D5 -> 539679.04 | C18: =[16]FCFF!E5 -> 578800.07 | D18: =[16]FCFF!F5 -> 620756.95 | E18: =[16]FCFF!G5 -> 665755.27 | F18: =[16]FCFF!H5 -> 714015.49 | I18: Revenue | J18: =[16]FCFF!V5 -> 508052.97 | K18: =[16]FCFF!W5 -> 550579.07 | L18: =[16]FCFF!X5 -> 596664.78 | M18: =[16]FCFF!Y5 -> 646608.05 | N18: =[16]FCFF!Z5 -> 700731.78 | Q18: Revenue | R18: =[16]FCFF!AN5 -> 727375.24 | S18: =[16]FCFF!AO5 -> 783053.56 | T18: =[16]FCFF!AP5 -> 842993.87 | U18: =[16]FCFF!AQ5 -> 907522.44 | V18: =[16]FCFF!AR5 -> 976990.46 | Y18: =(F20-B20)/B20 -> 0.32303728 | Z18: =(F20/B20)^(1/5)-1 -> 0.057582892
A19: EBITDA | B19: =[16]FCFF!D6+[16]FCFF!D9 -> 28919.067 | C19: =[16]FCFF!E6+[16]FCFF!E9 -> 31015.393 | D19: =[16]FCFF!F6+[16]FCFF!F9 -> 33263.681 | E19: =[16]FCFF!G6+[16]FCFF!G9 -> 35674.947 | F19: =[16]FCFF!H6+[16]FCFF!H9 -> 38261.003 | I19: EBITDA | J19: =[16]FCFF!V6+[16]FCFF!V9 -> 17026.569 | K19: =[16]FCFF!W6+[16]FCFF!W9 -> 18451.762 | L19: =[16]FCFF!X6+[16]FCFF!X9 -> 19996.249 | M19: =[16]FCFF!Y6+[16]FCFF!Y9 -> 21670.017 | N19: =[16]FCFF!Z6+[16]FCFF!Z9 -> 23483.886 | Q19: EBITDA | R19: =[16]FCFF!AN6+[16]FCFF!AN9 -> 109109.03 | S19: =[16]FCFF!AO6+[16]FCFF!AO9 -> 117460.99 | T19: =[16]FCFF!AP6+[16]FCFF!AP9 -> 126452.26 | U19: =[16]FCFF!AQ6+[16]FCFF!AQ9 -> 136131.79 | V19: =[16]FCFF!AR6+[16]FCFF!AR9 -> 146552.25 | Y19: =(F26-B26)/B26 -> 0.55388805 | Z19: =(F26/B26)^(1/5)-1 -> 0.092154163
A20: Net Profit | B20: =[16]FCFF!D8 -> 15461.808 | C20: =[16]FCFF!E8 -> 16582.625 | D20: =[16]FCFF!F8 -> 17784.69 | E20: =[16]FCFF!G8 -> 19073.892 | F20: =[16]FCFF!H8 -> 20456.548 | I20: Net Profit | J20: =[16]FCFF!V8 -> 8305.6614 | K20: =[16]FCFF!W8 -> 9000.8791 | L20: =[16]FCFF!X8 -> 9754.2893 | M20: =[16]FCFF!Y8 -> 10570.763 | N20: =[16]FCFF!Z8 -> 11455.579 | Q20: Net Profit | R20: =[16]FCFF!AN8 -> 53143.755 | S20: =[16]FCFF!AO8 -> 57211.745 | T20: =[16]FCFF!AP8 -> 61591.126 | U20: =[16]FCFF!AQ8 -> 66305.736 | V20: =[16]FCFF!AR8 -> 71381.234 | Y20: =(Table3242[[#This Row],[2030]]-Table3242[[#This Row],[2026]])/Table3242[[#This Row],[2026]] -> 0.37924947 | Z20: =(Table3242[[#This Row],[2030]]/Table3242[[#This Row],[2026]])^(1/5)-1 -> 0.066420697
A21: Capex | B21: =[16]FCFF!D10 -> 10389.195 | C21: =[16]FCFF!E10 -> 11142.302 | D21: =[16]FCFF!F10 -> 11950.001 | E21: =[16]FCFF!G10 -> 12816.25 | F21: =[16]FCFF!H10 -> 13745.293 | I21: Capex | J21: =[16]FCFF!V10 -> 10554.265 | K21: =[16]FCFF!W10 -> 11437.7 | L21: =[16]FCFF!X10 -> 12395.082 | M21: =[16]FCFF!Y10 -> 13432.601 | N21: =[16]FCFF!Z10 -> 14556.964 | Q21: Capex | R21: =[16]FCFF!AN10 -> 48250.176 | S21: =[16]FCFF!AO10 -> 51943.577 | T21: =[16]FCFF!AP10 -> 55919.696 | U21: =[16]FCFF!AQ10 -> 60200.175 | V21: =[16]FCFF!AR10 -> 64808.312 | Y21: =(N26-J26)/J26 -> 0.30506381 | Z21: =(N26/J26)^(1/5)-1 -> 0.054693695
Y22: =(V20-R20)/R20 -> 0.34317255 | Z22: =(V20/R20)^(1/5)-1 -> 0.060782537
A23: Forecasts | B23: 2026 | C23: 2027 | D23: 2028 | E23: 2029 | F23: 2030 | I23: Forecasts | J23: 2026 | K23: 2027 | L23: 2028 | M23: 2029 | N23: 2030 | Q23: Forecasts | R23: 2026 | S23: 2027 | T23: 2028 | U23: 2029 | V23: 2030 | Y23: =(V26-R26)/R26 -> 0.3115729 | Z23: =(V26/R26)^(1/5)-1 -> 0.055743672
A24: Revenue | B24: =[16]FCFF!M5 -> 160282.29 | C24: =[16]FCFF!N5 -> 178953.61 | D24: =[16]FCFF!O5 -> 199799.96 | E24: =[16]FCFF!P5 -> 223074.71 | F24: =[16]FCFF!Q5 -> 249060.73 | I24: Revenue | J24: =[16]FCFF!AE5 -> 922266.76 | K24: =[16]FCFF!AF5 -> 985744.8 | L24: =[16]FCFF!AG5 -> 1053591.9 | M24: =[16]FCFF!AH5 -> 1126108.8 | N24: =[16]FCFF!AI5 -> 1203617 | Q24: Revenue | R24: =[16]FCFF!AW5 -> 587395.02 | S24: =[16]FCFF!AX5 -> 628605.78 | T24: =[16]FCFF!AY5 -> 672707.83 | U24: =[16]FCFF!AZ5 -> 719904 | V24: =[16]FCFF!BA5 -> 770411.39 | Y24: =AVERAGE(Y18:Y23) -> 0.36933068 | Z24: =AVERAGE(Z18:Z23) -> 0.064562942
A25: EBITDA | B25: =[16]FCFF!M6+[16]FCFF!M9 -> 18703.186 | C25: =[16]FCFF!N6+[16]FCFF!N9 -> 20881.924 | D25: =[16]FCFF!O6+[16]FCFF!O9 -> 23314.465 | E25: =[16]FCFF!P6+[16]FCFF!P9 -> 26030.372 | F25: =[16]FCFF!Q6+[16]FCFF!Q9 -> 29062.657 | I25: EBITDA | J25: =[16]FCFF!AE6+[16]FCFF!AE9 -> 54444.473 | K25: =[16]FCFF!AF6+[16]FCFF!AF9 -> 58191.792 | L25: =[16]FCFF!AG6+[16]FCFF!AG9 -> 62197.033 | M25: =[16]FCFF!AH6+[16]FCFF!AH9 -> 66477.948 | N25: =[16]FCFF!AI6+[16]FCFF!AI9 -> 71053.511 | Q25: EBITDA | R25: =[16]FCFF!AW6+[16]FCFF!AW9 -> 91534.351 | S25: =[16]FCFF!AX6+[16]FCFF!AX9 -> 97956.265 | T25: =[16]FCFF!AY6+[16]FCFF!AY9 -> 104828.73 | U25: =[16]FCFF!AZ6+[16]FCFF!AZ9 -> 112183.36 | V25: =[16]FCFF!BA6+[16]FCFF!BA9 -> 120053.97
A26: Net Profit | B26: =[16]FCFF!M8 -> 11275.102 | C26: =[16]FCFF!N8 -> 12588.541 | D26: =[16]FCFF!O8 -> 14054.983 | E26: =[16]FCFF!P8 -> 15692.252 | F26: =[16]FCFF!Q8 -> 17520.246 | I26: Net Profit | J26: =[16]FCFF!AE8 -> 30980.978 | K26: =[16]FCFF!AF8 -> 33113.346 | L26: =[16]FCFF!AG8 -> 35392.48 | M26: =[16]FCFF!AH8 -> 37828.484 | N26: =[16]FCFF!AI8 -> 40432.154 | Q26: Net Profit | R26: =[16]FCFF!AW8 -> 55528.808 | S26: =[16]FCFF!AX8 -> 59424.626 | T26: =[16]FCFF!AY8 -> 63593.769 | U26: =[16]FCFF!AZ8 -> 68055.413 | V26: =[16]FCFF!BA8 -> 72830.079
A27: Capex | B27: =[16]FCFF!M10 -> 11696.631 | C27: =[16]FCFF!N10 -> 13059.174 | D27: =[16]FCFF!O10 -> 14580.44 | E27: =[16]FCFF!P10 -> 16278.919 | F27: =[16]FCFF!Q10 -> 18175.254 | I27: Capex | J27: =[16]FCFF!AE10 -> 6629.72 | K27: =[16]FCFF!AF10 -> 7086.0322 | L27: =[16]FCFF!AG10 -> 7573.7517 | M27: =[16]FCFF!AH10 -> 8095.04 | N27: =[16]FCFF!AI10 -> 8652.2077 | Q27: Capex | R27: =[16]FCFF!AW10 -> 35390.884 | S27: =[16]FCFF!AX10 -> 37873.856 | T27: =[16]FCFF!AY10 -> 40531.029 | U27: =[16]FCFF!AZ10 -> 43374.626 | V27: =[16]FCFF!BA10 -> 46417.725

Sheet Tables-Infra
A1: KPI | B1: 2020 | C1: 2021 | D1: 2022 | E1: 2023 | F1: 2024 | G1: 2025 | I1: KPI | J1: 2020 | K1: 2021 | L1: 2022 | M1: 2023 | N1: 2024 | O1: 2025 | Q1: KPI | R1: 2020 | S1: 2021 | T1: 2022 | U1: 2023 | V1: 2024 | W1: 2025
A2: Revenue | B2: ='[17]Income Statement'!B8 -> 13734.42 | C2: ='[17]Income Statement'!C8 -> 14519.83 | D2: ='[17]Income Statement'!D8 -> 19342.51 | E2: ='[17]Income Statement'!E8 -> 22405.39 | F2: ='[17]Income Statement'!F8 -> 28209.98 | G2: ='[17]Income Statement'!G8 -> 32383.08 | I2: Revenue | J2: ='[17]Income Statement'!R7 -> 11976.47 | K2: ='[17]Income Statement'!S7 -> 13144.12 | L2: ='[17]Income Statement'!T7 -> 13755.69 | M2: ='[17]Income Statement'!U7 -> 17313.03 | N2: ='[17]Income Statement'!V7 -> 19966.58 | O2: ='[17]Income Statement'!W7 -> 21917.56 | Q2: Revenue | R2: ='[17]Income Statement'!AH7 -> 10323.923 | S2: ='[17]Income Statement'!AI7 -> 14776.264 | T2: ='[17]Income Statement'!AJ7 -> 16142.95 | U2: ='[17]Income Statement'!AK7 -> 20181.94 | V2: ='[17]Income Statement'!AL7 -> 21278.01 | W2: ='[17]Income Statement'!AM7 -> 23074.8
A3: EBITDA Margin | B3: ='[17]Ratio Analysis'!B6 -> 0.56794244 | C3: ='[17]Ratio Analysis'!C6 -> 0.73478202 | D3: ='[17]Ratio Analysis'!D6 -> 0.60737515 | E3: ='[17]Ratio Analysis'!E6 -> 0.55792869 | F3: ='[17]Ratio Analysis'!F6 -> 0.61150416 | G3: ='[17]Ratio Analysis'!G6 -> 0.61909707 | I3: EBITDA Margin | J3: ='[17]Ratio Analysis'!R6 -> 0.10399141 | K3: ='[17]Ratio Analysis'!S6 -> 0.089099156 | L3: ='[17]Ratio Analysis'!T6 -> 0.066658234 | M3: ='[17]Ratio Analysis'!U6 -> 0.049734218 | N3: ='[17]Ratio Analysis'!V6 -> 0.063455033 | O3: ='[17]Ratio Analysis'!W6 -> 0.071849239 | Q3: EBITDA Margin | R3: ='[17]Ratio Analysis'!AH6 -> 0.076148978 | S3: ='[17]Ratio Analysis'!AI6 -> 0.069853184 | T3: ='[17]Ratio Analysis'!AJ6 -> 0.10029456 | U3: ='[17]Ratio Analysis'!AK6 -> 0.098269542 | V3: ='[17]Ratio Analysis'!AL6 -> 0.10540741 | W3: ='[17]Ratio Analysis'!AM6 -> 0.11000745
A4: Net Profit Margin | B4: ='[17]Ratio Analysis'!B7 -> 0.27555077 | C4: ='[17]Ratio Analysis'!C7 -> 0.34771344 | D4: ='[17]Ratio Analysis'!D7 -> 0.25607742 | E4: ='[17]Ratio Analysis'!E7 -> 0.24068985 | F4: ='[17]Ratio Analysis'!F7 -> 0.28727387 | G4: ='[17]Ratio Analysis'!G7 -> 0.34157529 | I4: Net Profit Margin | J4: ='[17]Ratio Analysis'!R7 -> 0.047219256 | K4: ='[17]Ratio Analysis'!S7 -> 0.042050742 | L4: ='[17]Ratio Analysis'!T7 -> 0.027313788 | M4: ='[17]Ratio Analysis'!U7 -> 0.010167487 | N4: ='[17]Ratio Analysis'!V7 -> 0.017368022 | O4: ='[17]Ratio Analysis'!W7 -> 0.026040307 | Q4: Net Profit Margin | R4: ='[17]Ratio Analysis'!AH7 -> 0.066616487 | S4: ='[17]Ratio Analysis'!AI7 -> 0.050981946 | T4: ='[17]Ratio Analysis'!AJ7 -> 0.061424337 | U4: ='[17]Ratio Analysis'!AK7 -> 0.058601403 | V4: ='[17]Ratio Analysis'!AL7 -> 0.063058059 | W4: ='[17]Ratio Analysis'!AM7 -> 0.068233311
A5: ROE | B5: ='[17]Ratio Analysis'!B8 -> 0.14644268 | C5: ='[17]Ratio Analysis'!C8 -> 0.17427534 | D5: ='[17]Ratio Analysis'!D8 -> 0.13301105 | E5: ='[17]Ratio Analysis'!E8 -> 0.12077411 | F5: ='[17]Ratio Analysis'!F8 -> 0.15973947 | G5: ='[17]Ratio Analysis'!G8 -> 0.18510038 | I5: ROE | J5: ='[17]Ratio Analysis'!R8 -> 0.20214614 | K5: ='[17]Ratio Analysis'!S8 -> 0.17953411 | L5: ='[17]Ratio Analysis'!T8 -> 0.10766202 | M5: ='[17]Ratio Analysis'!U8 -> 0.047631353 | N5: ='[17]Ratio Analysis'!V8 -> 0.088159326 | O5: ='[17]Ratio Analysis'!W8 -> 0.12087916 | Q5: ROE | R5: ='[17]Ratio Analysis'!AH8 -> 0.13443257 | S5: ='[17]Ratio Analysis'!AI8 -> 0.14012726 | T5: ='[17]Ratio Analysis'!AJ8 -> 0.16480187 | U5: ='[17]Ratio Analysis'!AK8 -> 0.1733692 | V5: ='[17]Ratio Analysis'!AL8 -> 0.16780213 | W5: ='[17]Ratio Analysis'!AM8 -> 0.18129061
A6: ROCE | B6: ='[17]Ratio Analysis'!B9 -> 0.11228021 | C6: ='[17]Ratio Analysis'!C9 -> 0.12549505 | D6: ='[17]Ratio Analysis'!D9 -> 0.09759218 | E6: ='[17]Ratio Analysis'!E9 -> 0.087702338 | F6: ='[17]Ratio Analysis'!F9 -> 0.13035841 | G6: ='[17]Ratio Analysis'!G9 -> 0.13697719 | I6: ROCE | J6: ='[17]Ratio Analysis'!R9 -> 0.34828924 | K6: ='[17]Ratio Analysis'!S9 -> 0.27086535 | L6: ='[17]Ratio Analysis'!T9 -> 0.17908339 | M6: ='[17]Ratio Analysis'!U9 -> 0.15687079 | N6: ='[17]Ratio Analysis'!V9 -> 0.24047917 | O6: ='[17]Ratio Analysis'!W9 -> 0.23367557 | Q6: ROCE | R6: ='[17]Ratio Analysis'!AH9 -> 0.080504549 | S6: ='[17]Ratio Analysis'!AI9 -> 0.086393764 | T6: ='[17]Ratio Analysis'!AJ9 -> 0.12244693 | U6: ='[17]Ratio Analysis'!AK9 -> 0.14116388 | V6: ='[17]Ratio Analysis'!AL9 -> 0.14771428 | W6: ='[17]Ratio Analysis'!AM9 -> 0.18142261
A7: D/E | B7: ='[17]Ratio Analysis'!B14 -> 1.0728385 | C7: ='[17]Ratio Analysis'!C14 -> 1.0385958 | D7: ='[17]Ratio Analysis'!D14 -> 1.0724865 | E7: ='[17]Ratio Analysis'!E14 -> 1.0617453 | F7: ='[17]Ratio Analysis'!F14 -> 0.84849073 | G7: ='[17]Ratio Analysis'!G14 -> 0.70505887 | I7: D/E | J7: ='[17]Ratio Analysis'!R14 -> 0.73699412 | K7: ='[17]Ratio Analysis'!S14 -> 0.54868753 | L7: ='[17]Ratio Analysis'!T14 -> 0.79081916 | M7: ='[17]Ratio Analysis'!U14 -> 0.84701518 | N7: ='[17]Ratio Analysis'!V14 -> 0.92494079 | O7: ='[17]Ratio Analysis'!W14 -> 0.69212428 | Q7: D/E | R7: ='[17]Ratio Analysis'!AH14 -> 0.83204415 | S7: ='[17]Ratio Analysis'!AI14 -> 1.0471462 | T7: ='[17]Ratio Analysis'!AJ14 -> 1.0309469 | U7: ='[17]Ratio Analysis'!AK14 -> 0.88430764 | V7: ='[17]Ratio Analysis'!AL14 -> 0.68464014 | W7: ='[17]Ratio Analysis'!AM14 -> 0.62490665
A8: FCF Margin | B8: ='[17]Ratio Analysis'!B26 -> 0.27525007 | C8: ='[17]Ratio Analysis'!C26 -> 0.38583578 | D8: ='[17]Ratio Analysis'!D26 -> 0.3415503 | E8: ='[17]Ratio Analysis'!E26 -> 0.12534796 | F8: ='[17]Ratio Analysis'!F26 -> 0.26945358 | G8: ='[17]Ratio Analysis'!G26 -> 0.28339985 | I8: FCF Margin | J8: ='[17]Ratio Analysis'!R26 -> -0.0099361498 | K8: ='[17]Ratio Analysis'!S26 -> 0.050552643 | L8: ='[17]Ratio Analysis'!T26 -> -0.031030795 | M8: ='[17]Ratio Analysis'!U26 -> 0.024746679 | N8: ='[17]Ratio Analysis'!V26 -> 0.0036946738 | O8: ='[17]Ratio Analysis'!W26 -> 0.010793172 | Q8: FCF Margin | R8: ='[17]Ratio Analysis'!AH26 -> -0.095051976 | S8: ='[17]Ratio Analysis'!AI26 -> 0.025629618 | T8: ='[17]Ratio Analysis'!AJ26 -> 0.29649723 | U8: ='[17]Ratio Analysis'!AK26 -> -0.2018686 | V8: ='[17]Ratio Analysis'!AL26 -> 0.13338042 | W8: ='[17]Ratio Analysis'!AM26 -> 0.064497634
A10: KPI | B10: 2020 | C10: 2021 | D10: 2022 | E10: 2023 | F10: 2024 | G10: 2025 | I10: KPI | J10: 2020 | K10: 2021 | L10: 2022 | M10: 2023 | N10: 2024 | O10: 2025 | Q10: Forecasts | R10: 2026 | S10: 2027 | T10: 2028 | U10: 2029 | V10: 2030
A11: Revenue | B11: ='[17]Income Statement'!J7 -> 12719.88 | C11: ='[17]Income Statement'!K7 -> 13016.46 | D11: ='[17]Income Statement'!L7 -> 14866.3 | E11: ='[17]Income Statement'!M7 -> 16401.14 | F11: ='[17]Income Statement'!N7 -> 19690.42 | G11: ='[17]Income Statement'!O7 -> 22378.26 | I11: Revenue | J11: ='[17]Income Statement'!Z8 -> 147813.26 | K11: ='[17]Income Statement'!AA8 -> 139408.38 | L11: ='[17]Income Statement'!AB8 -> 158788.31 | M11: ='[17]Income Statement'!AC8 -> 186269.87 | N11: ='[17]Income Statement'!AD8 -> 225270.94 | O11: ='[17]Income Statement'!AE8 -> 259859.27 | Q11: Revenue | R11: =[17]DCF!AN4 -> 26384.78 | S11: =[17]DCF!AO4 -> 30169.562 | T11: =[17]DCF!AP4 -> 34497.255 | U11: =[17]DCF!AQ4 -> 39445.736 | V11: =[17]DCF!AR4 -> 45104.056
A12: EBITDA Margin | B12: ='[17]Ratio Analysis'!J6 -> 0.12009076 | C12: ='[17]Ratio Analysis'!K6 -> 0.12115429 | D12: ='[17]Ratio Analysis'!L6 -> 0.085998534 | E12: ='[17]Ratio Analysis'!M6 -> 0.085923296 | F12: ='[17]Ratio Analysis'!N6 -> 0.085958552 | G12: ='[17]Ratio Analysis'!O6 -> 0.084751898 | I12: EBITDA Margin | J12: ='[17]Ratio Analysis'!Z6 -> 0.12644251 | K12: ='[17]Ratio Analysis'!AA6 -> 0.13667363 | L12: ='[17]Ratio Analysis'!AB6 -> 0.12892442 | M12: ='[17]Ratio Analysis'!AC6 -> 0.12714053 | N12: ='[17]Ratio Analysis'!AD6 -> 0.12274854 | O12: ='[17]Ratio Analysis'!AE6 -> 0.11760042 | Q12: EBITDA margin | R12: =([17]DCF!AN5+[17]DCF!AN8)/[17]DCF!AN4 -> 0.096446484 | S12: =([17]DCF!AO5+[17]DCF!AO8)/[17]DCF!AO4 -> 0.096446484 | T12: =([17]DCF!AP5+[17]DCF!AP8)/[17]DCF!AP4 -> 0.096446484 | U12: =([17]DCF!AQ5+[17]DCF!AQ8)/[17]DCF!AQ4 -> 0.096446484 | V12: =([17]DCF!AR5+[17]DCF!AR8)/[17]DCF!AR4 -> 0.096446484
